Workbook

Sheet Summary
A1: Personal Ledger Summary
A2: Workbook year: 2026
A4: Annual Overview
A5: Month | B5: Income | C5: Expenses | D5: Existing Savings | E5: Transfers | F5: Net Cash Flow | G5: Current Balance
A6: Jan 2026 | B6: ='Jan 2026'!$B$5 | C6: ='Jan 2026'!$B$6 | D6: ='Jan 2026'!$B$7 | E6: ='Jan 2026'!$B$8 | F6: ='Jan 2026'!$B$9 | G6: ='Jan 2026'!$B$10 -> 0
A7: Feb 2026 | B7: ='Feb 2026'!$B$5 | C7: ='Feb 2026'!$B$6 | D7: ='Feb 2026'!$B$7 | E7: ='Feb 2026'!$B$8 | F7: ='Feb 2026'!$B$9 | G7: ='Feb 2026'!$B$10 -> 0
A8: Mar 2026 | B8: ='Mar 2026'!$B$5 | C8: ='Mar 2026'!$B$6 | D8: ='Mar 2026'!$B$7 | E8: ='Mar 2026'!$B$8 | F8: ='Mar 2026'!$B$9 | G8: ='Mar 2026'!$B$10 -> 0
A9: Apr 2026 | B9: ='Apr 2026'!$B$5 | C9: ='Apr 2026'!$B$6 | D9: ='Apr 2026'!$B$7 | E9: ='Apr 2026'!$B$8 | F9: ='Apr 2026'!$B$9 | G9: ='Apr 2026'!$B$10 -> 0
A10: May 2026 | B10: ='May 2026'!$B$5 | C10: ='May 2026'!$B$6 | D10: ='May 2026'!$B$7 | E10: ='May 2026'!$B$8 | F10: ='May 2026'!$B$9 | G10: ='May 2026'!$B$10 -> 0
A11: Jun 2026 | B11: ='Jun 2026'!$B$5 | C11: ='Jun 2026'!$B$6 | D11: ='Jun 2026'!$B$7 | E11: ='Jun 2026'!$B$8 | F11: ='Jun 2026'!$B$9 | G11: ='Jun 2026'!$B$10 -> 0
A12: Jul 2026 | B12: ='Jul 2026'!$B$5 | C12: ='Jul 2026'!$B$6 | D12: ='Jul 2026'!$B$7 | E12: ='Jul 2026'!$B$8 | F12: ='Jul 2026'!$B$9 | G12: ='Jul 2026'!$B$10 -> 0
A13: Aug 2026 | B13: ='Aug 2026'!$B$5 -> 4988 | C13: ='Aug 2026'!$B$6 -> 2741.56 | D13: ='Aug 2026'!$B$7 -> 7300 | E13: ='Aug 2026'!$B$8 -> 1700 | F13: ='Aug 2026'!$B$9 -> 2246.44 | G13: ='Aug 2026'!$B$10 -> 8242.24
A14: Sep 2026 | B14: ='Sep 2026'!$B$5 -> 3126 | C14: ='Sep 2026'!$B$6 -> 2841.18 | D14: ='Sep 2026'!$B$7 -> 0 | E14: ='Sep 2026'!$B$8 -> 106 | F14: ='Sep 2026'!$B$9 -> 284.82 | G14: ='Sep 2026'!$B$10 -> 9127.06
A15: Oct 2026 | B15: ='Oct 2026'!$B$5 -> 0 | C15: ='Oct 2026'!$B$6 -> 1536.47 | D15: ='Oct 2026'!$B$7 -> 0 | E15: ='Oct 2026'!$B$8 -> 0 | F15: ='Oct 2026'!$B$9 -> -1536.47 | G15: ='Oct 2026'!$B$10 -> 7590.59
A16: Nov 2026 | B16: ='Nov 2026'!$B$5 | C16: ='Nov 2026'!$B$6 | D16: ='Nov 2026'!$B$7 | E16: ='Nov 2026'!$B$8 | F16: ='Nov 2026'!$B$9 | G16: ='Nov 2026'!$B$10 -> 0
A17: Dec 2026 | B17: ='Dec 2026'!$B$5 | C17: ='Dec 2026'!$B$6 | D17: ='Dec 2026'!$B$7 | E17: ='Dec 2026'!$B$8 | F17: ='Dec 2026'!$B$9 | G17: ='Dec 2026'!$B$10 -> 0
A18: Total | B18: =SUM(B6:B17) -> 8114 | C18: =SUM(C6:C17) -> 7119.21 | D18: =SUM(D6:D17) -> 7300 | E18: =SUM(E6:E17) -> 1806 | F18: =SUM(F6:F17) -> 994.79 | G18: =LOOKUP(2,1/(G6:G17<>0),G6:G17) -> 7590.59
A20: Annual Category Summary
A21: Category | B21: Expenses | C21: Income | D21: Existing Savings | E21: Net
A22: Housing | B22: =SUMIFS('Jan 2026'!$J$29:$J$528,'Jan 2026'!$E$29:$E$528,$A22,'Jan 2026'!$I$29:$I$528,"Expense")+SUMIFS('Feb 2026'!$J$29:$J$528,'Feb 2026'!$E$29:$E$528,$A22,'Feb 2026'!$I$29:$I$528,"Expense")+SUMIFS('Mar 2026'!$J$29:$J$528,'Mar 2026'!$E$29:$E$528,$A22,'Mar 2026'!$I$29:$I$528,"Expense")+SUMIFS('Apr 2026'!$J$29:$J$528,'Apr 2026'!$E$29:$E$528,$A22,'Apr 2026'!$I$29:$I$528,"Expense")+SUMIFS('May 2026'!$J$29:$J$528,'May 2026'!$E$29:$E$528,$A22,'May 2026'!$I$29:$I$528,"Expense")+SUMIFS('Jun 2026'!$J$29:$J$528,'Jun 2026'!$E$29:$E$528,$A22,'Jun 2026'!$I$29:$I$528,"Expense")+SUMIFS('Jul 2026'!$J$29:$J$528,'Jul 2026'!$E$29:$E$528,$A22,'Jul 2026'!$I$29:$I$528,"Expense")+SUMIFS('Aug 2026'!$J$29:$J$528,'Aug 2026'!$E$29:$E$528,$A22,'Aug 2026'!$I$29:$I$528,"Expense")+SUMIFS('Sep 2026'!$J$29:$J$528,'Sep 2026'!$E$29:$E$528,$A22,'Sep 2026'!$I$29:$I$528,"Expense")+SUMIFS('Oct 2026'!$J$29:$J$528,'Oct 2026'!$E$29:$E$528,$A22,'Oct 2026'!$I$29:$I$528,"Expense")+SUMIFS('Nov 2026'!$J$29:$J$528,'Nov 2026'!$E$29:$E$528,$A22,'Nov 2026'!$I$29:$I$528,"Expense")+SUMIFS('Dec 2026'!$J$29:$J$528,'Dec 2026'!$E$29:$E$528,$A22,'Dec 2026'!$I$29:$I$528,"Expense") -> 3300 | C22: =SUMIFS('Jan 2026'!$J$29:$J$528,'Jan 2026'!$E$29:$E$528,$A22,'Jan 2026'!$I$29:$I$528,"Income")+SUMIFS('Feb 2026'!$J$29:$J$528,'Feb 2026'!$E$29:$E$528,$A22,'Feb 2026'!$I$29:$I$528,"Income")+SUMIFS('Mar 2026'!$J$29:$J$528,'Mar 2026'!$E$29:$E$528,$A22,'Mar 2026'!$I$29:$I$528,"Income")+SUMIFS('Apr 2026'!$J$29:$J$528,'Apr 2026'!$E$29:$E$528,$A22,'Apr 2026'!$I$29:$I$528,"Income")+SUMIFS('May 2026'!$J$29:$J$528,'May 2026'!$E$29:$E$528,$A22,'May 2026'!$I$29:$I$528,"Income")+SUMIFS('Jun 2026'!$J$29:$J$528,'Jun 2026'!$E$29:$E$528,$A22,'Jun 2026'!$I$29:$I$528,"Income")+SUMIFS('Jul 2026'!$J$29:$J$528,'Jul 2026'!$E$29:$E$528,$A22,'Jul 2026'!$I$29:$I$528,"Income")+SUMIFS('Aug 2026'!$J$29:$J$528,'Aug 2026'!$E$29:$E$528,$A22,'Aug 2026'!$I$29:$I$528,"Income")+SUMIFS('Sep 2026'!$J$29:$J$528,'Sep 2026'!$E$29:$E$528,$A22,'Sep 2026'!$I$29:$I$528,"Income")+SUMIFS('Oct 2026'!$J$29:$J$528,'Oct 2026'!$E$29:$E$528,$A22,'Oct 2026'!$I$29:$I$528,"Income")+SUMIFS('Nov 2026'!$J$29:$J$528,'Nov 2026'!$E$29:$E$528,$A22,'Nov 2026'!$I$29:$I$528,"Income")+SUMIFS('Dec 2026'!$J$29:$J$528,'Dec 2026'!$E$29:$E$528,$A22,'Dec 2026'!$I$29:$I$528,"Income") -> 0 | D22: =SUMIFS('Jan 2026'!$J$29:$J$528,'Jan 2026'!$E$29:$E$528,$A22,'Jan 2026'!$I$29:$I$528,"Opening Balance")+SUMIFS('Feb 2026'!$J$29:$J$528,'Feb 2026'!$E$29:$E$528,$A22,'Feb 2026'!$I$29:$I$528,"Opening Balance")+SUMIFS('Mar 2026'!$J$29:$J$528,'Mar 2026'!$E$29:$E$528,$A22,'Mar 2026'!$I$29:$I$528,"Opening Balance")+SUMIFS('Apr 2026'!$J$29:$J$528,'Apr 2026'!$E$29:$E$528,$A22,'Apr 2026'!$I$29:$I$528,"Opening Balance")+SUMIFS('May 2026'!$J$29:$J$528,'May 2026'!$E$29:$E$528,$A22,'May 2026'!$I$29:$I$528,"Opening Balance")+SUMIFS('Jun 2026'!$J$29:$J$528,'Jun 2026'!$E$29:$E$528,$A22,'Jun 2026'!$I$29:$I$528,"Opening Balance")+SUMIFS('Jul 2026'!$J$29:$J$528,'Jul 2026'!$E$29:$E$528,$A22,'Jul 2026'!$I$29:$I$528,"Opening Balance")+SUMIFS('Aug 2026'!$J$29:$J$528,'Aug 2026'!$E$29:$E$528,$A22,'Aug 2026'!$I$29:$I$528,"Opening Balance")+SUMIFS('Sep 2026'!$J$29:$J$528,'Sep 2026'!$E$29:$E$528,$A22,'Sep 2026'!$I$29:$I$528,"Opening Balance")+SUMIFS('Oct 2026'!$J$29:$J$528,'Oct 2026'!$E$29:$E$528,$A22,'Oct 2026'!$I$29:$I$528,"Opening Balance")+SUMIFS('Nov 2026'!$J$29:$J$528,'Nov 2026'!$E$29:$E$528,$A22,'Nov 2026'!$I$29:$I$528,"Opening Balance")+SUMIFS('Dec 2026'!$J$29:$J$528,'Dec 2026'!$E$29:$E$528,$A22,'Dec 2026'!$I$29:$I$528,"Opening Balance") -> 0 | E22: =C22+D22-B22 -> -3300
A23: Utilities | B23: =SUMIFS('Jan 2026'!$J$29:$J$528,'Jan 2026'!$E$29:$E$528,$A23,'Jan 2026'!$I$29:$I$528,"Expense")+SUMIFS('Feb 2026'!$J$29:$J$528,'Feb 2026'!$E$29:$E$528,$A23,'Feb 2026'!$I$29:$I$528,"Expense")+SUMIFS('Mar 2026'!$J$29:$J$528,'Mar 2026'!$E$29:$E$528,$A23,'Mar 2026'!$I$29:$I$528,"Expense")+SUMIFS('Apr 2026'!$J$29:$J$528,'Apr 2026'!$E$29:$E$528,$A23,'Apr 2026'!$I$29:$I$528,"Expense")+SUMIFS('May 2026'!$J$29:$J$528,'May 2026'!$E$29:$E$528,$A23,'May 2026'!$I$29:$I$528,"Expense")+SUMIFS('Jun 2026'!$J$29:$J$528,'Jun 2026'!$E$29:$E$528,$A23,'Jun 2026'!$I$29:$I$528,"Expense")+SUMIFS('Jul 2026'!$J$29:$J$528,'Jul 2026'!$E$29:$E$528,$A23,'Jul 2026'!$I$29:$I$528,"Expense")+SUMIFS('Aug 2026'!$J$29:$J$528,'Aug 2026'!$E$29:$E$528,$A23,'Aug 2026'!$I$29:$I$528,"Expense")+SUMIFS('Sep 2026'!$J$29:$J$528,'Sep 2026'!$E$29:$E$528,$A23,'Sep 2026'!$I$29:$I$528,"Expense")+SUMIFS('Oct 2026'!$J$29:$J$528,'Oct 2026'!$E$29:$E$528,$A23,'Oct 2026'!$I$29:$I$528,"Expense")+SUMIFS('Nov 2026'!$J$29:$J$528,'Nov 2026'!$E$29:$E$528,$A23,'Nov 2026'!$I$29:$I$528,"Expense")+SUMIFS('Dec 2026'!$J$29:$J$528,'Dec 2026'!$E$29:$E$528,$A23,'Dec 2026'!$I$29:$I$528,"Expense") -> 117.91 | C23: =SUMIFS('Jan 2026'!$J$29:$J$528,'Jan 2026'!$E$29:$E$528,$A23,'Jan 2026'!$I$29:$I$528,"Income")+SUMIFS('Feb 2026'!$J$29:$J$528,'Feb 2026'!$E$29:$E$528,$A23,'Feb 2026'!$I$29:$I$528,"Income")+SUMIFS('Mar 2026'!$J$29:$J$528,'Mar 2026'!$E$29:$E$528,$A23,'Mar 2026'!$I$29:$I$528,"Income")+SUMIFS('Apr 2026'!$J$29:$J$528,'Apr 2026'!$E$29:$E$528,$A23,'Apr 2026'!$I$29:$I$528,"Income")+SUMIFS('May 2026'!$J$29:$J$528,'May 2026'!$E$29:$E$528,$A23,'May 2026'!$I$29:$I$528,"Income")+SUMIFS('Jun 2026'!$J$29:$J$528,'Jun 2026'!$E$29:$E$528,$A23,'Jun 2026'!$I$29:$I$528,"Income")+SUMIFS('Jul 2026'!$J$29:$J$528,'Jul 2026'!$E$29:$E$528,$A23,'Jul 2026'!$I$29:$I$528,"Income")+SUMIFS('Aug 2026'!$J$29:$J$528,'Aug 2026'!$E$29:$E$528,$A23,'Aug 2026'!$I$29:$I$528,"Income")+SUMIFS('Sep 2026'!$J$29:$J$528,'Sep 2026'!$E$29:$E$528,$A23,'Sep 2026'!$I$29:$I$528,"Income")+SUMIFS('Oct 2026'!$J$29:$J$528,'Oct 2026'!$E$29:$E$528,$A23,'Oct 2026'!$I$29:$I$528,"Income")+SUMIFS('Nov 2026'!$J$29:$J$528,'Nov 2026'!$E$29:$E$528,$A23,'Nov 2026'!$I$29:$I$528,"Income")+SUMIFS('Dec 2026'!$J$29:$J$528,'Dec 2026'!$E$29:$E$528,$A23,'Dec 2026'!$I$29:$I$528,"Income") -> 0 | D23: =SUMIFS('Jan 2026'!$J$29:$J$528,'Jan 2026'!$E$29:$E$528,$A23,'Jan 2026'!$I$29:$I$528,"Opening Balance")+SUMIFS('Feb 2026'!$J$29:$J$528,'Feb 2026'!$E$29:$E$528,$A23,'Feb 2026'!$I$29:$I$528,"Opening Balance")+SUMIFS('Mar 2026'!$J$29:$J$528,'Mar 2026'!$E$29:$E$528,$A23,'Mar 2026'!$I$29:$I$528,"Opening Balance")+SUMIFS('Apr 2026'!$J$29:$J$528,'Apr 2026'!$E$29:$E$528,$A23,'Apr 2026'!$I$29:$I$528,"Opening Balance")+SUMIFS('May 2026'!$J$29:$J$528,'May 2026'!$E$29:$E$528,$A23,'May 2026'!$I$29:$I$528,"Opening Balance")+SUMIFS('Jun 2026'!$J$29:$J$528,'Jun 2026'!$E$29:$E$528,$A23,'Jun 2026'!$I$29:$I$528,"Opening Balance")+SUMIFS('Jul 2026'!$J$29:$J$528,'Jul 2026'!$E$29:$E$528,$A23,'Jul 2026'!$I$29:$I$528,"Opening Balance")+SUMIFS('Aug 2026'!$J$29:$J$528,'Aug 2026'!$E$29:$E$528,$A23,'Aug 2026'!$I$29:$I$528,"Opening Balance")+SUMIFS('Sep 2026'!$J$29:$J$528,'Sep 2026'!$E$29:$E$528,$A23,'Sep 2026'!$I$29:$I$528,"Opening Balance")+SUMIFS('Oct 2026'!$J$29:$J$528,'Oct 2026'!$E$29:$E$528,$A23,'Oct 2026'!$I$29:$I$528,"Opening Balance")+SUMIFS('Nov 2026'!$J$29:$J$528,'Nov 2026'!$E$29:$E$528,$A23,'Nov 2026'!$I$29:$I$528,"Opening Balance")+SUMIFS('Dec 2026'!$J$29:$J$528,'Dec 2026'!$E$29:$E$528,$A23,'Dec 2026'!$I$29:$I$528,"Opening Balance") -> 0 | E23: =C23+D23-B23 -> -117.91
A24: Groceries | B24: =SUMIFS('Jan 2026'!$J$29:$J$528,'Jan 2026'!$E$29:$E$528,$A24,'Jan 2026'!$I$29:$I$528,"Expense")+SUMIFS('Feb 2026'!$J$29:$J$528,'Feb 2026'!$E$29:$E$528,$A24,'Feb 2026'!$I$29:$I$528,"Expense")+SUMIFS('Mar 2026'!$J$29:$J$528,'Mar 2026'!$E$29:$E$528,$A24,'Mar 2026'!$I$29:$I$528,"Expense")+SUMIFS('Apr 2026'!$J$29:$J$528,'Apr 2026'!$E$29:$E$528,$A24,'Apr 2026'!$I$29:$I$528,"Expense")+SUMIFS('May 2026'!$J$29:$J$528,'May 2026'!$E$29:$E$528,$A24,'May 2026'!$I$29:$I$528,"Expense")+SUMIFS('Jun 2026'!$J$29:$J$528,'Jun 2026'!$E$29:$E$528,$A24,'Jun 2026'!$I$29:$I$528,"Expense")+SUMIFS('Jul 2026'!$J$29:$J$528,'Jul 2026'!$E$29:$E$528,$A24,'Jul 2026'!$I$29:$I$528,"Expense")+SUMIFS('Aug 2026'!$J$29:$J$528,'Aug 2026'!$E$29:$E$528,$A24,'Aug 2026'!$I$29:$I$528,"Expense")+SUMIFS('Sep 2026'!$J$29:$J$528,'Sep 2026'!$E$29:$E$528,$A24,'Sep 2026'!$I$29:$I$528,"Expense")+SUMIFS('Oct 2026'!$J$29:$J$528,'Oct 2026'!$E$29:$E$528,$A24,'Oct 2026'!$I$29:$I$528,"Expense")+SUMIFS('Nov 2026'!$J$29:$J$528,'Nov 2026'!$E$29:$E$528,$A24,'Nov 2026'!$I$29:$I$528,"Expense")+SUMIFS('Dec 2026'!$J$29:$J$528,'Dec 2026'!$E$29:$E$528,$A24,'Dec 2026'!$I$29:$I$528,"Expense") -> 757.58 | C24: =SUMIFS('Jan 2026'!$J$29:$J$528,'Jan 2026'!$E$29:$E$528,$A24,'Jan 2026'!$I$29:$I$528,"Income")+SUMIFS('Feb 2026'!$J$29:$J$528,'Feb 2026'!$E$29:$E$528,$A24,'Feb 2026'!$I$29:$I$528,"Income")+SUMIFS('Mar 2026'!$J$29:$J$528,'Mar 2026'!$E$29:$E$528,$A24,'Mar 2026'!$I$29:$I$528,"Income")+SUMIFS('Apr 2026'!$J$29:$J$528,'Apr 2026'!$E$29:$E$528,$A24,'Apr 2026'!$I$29:$I$528,"Income")+SUMIFS('May 2026'!$J$29:$J$528,'May 2026'!$E$29:$E$528,$A24,'May 2026'!$I$29:$I$528,"Income")+SUMIFS('Jun 2026'!$J$29:$J$528,'Jun 2026'!$E$29:$E$528,$A24,'Jun 2026'!$I$29:$I$528,"Income")+SUMIFS('Jul 2026'!$J$29:$J$528,'Jul 2026'!$E$29:$E$528,$A24,'Jul 2026'!$I$29:$I$528,"Income")+SUMIFS('Aug 2026'!$J$29:$J$528,'Aug 2026'!$E$29:$E$528,$A24,'Aug 2026'!$I$29:$I$528,"Income")+SUMIFS('Sep 2026'!$J$29:$J$528,'Sep 2026'!$E$29:$E$528,$A24,'Sep 2026'!$I$29:$I$528,"Income")+SUMIFS('Oct 2026'!$J$29:$J$528,'Oct 2026'!$E$29:$E$528,$A24,'Oct 2026'!$I$29:$I$528,"Income")+SUMIFS('Nov 2026'!$J$29:$J$528,'Nov 2026'!$E$29:$E$528,$A24,'Nov 2026'!$I$29:$I$528,"Income")+SUMIFS('Dec 2026'!$J$29:$J$528,'Dec 2026'!$E$29:$E$528,$A24,'Dec 2026'!$I$29:$I$528,"Income") -> 0 | D24: =SUMIFS('Jan 2026'!$J$29:$J$528,'Jan 2026'!$E$29:$E$528,$A24,'Jan 2026'!$I$29:$I$528,"Opening Balance")+SUMIFS('Feb 2026'!$J$29:$J$528,'Feb 2026'!$E$29:$E$528,$A24,'Feb 2026'!$I$29:$I$528,"Opening Balance")+SUMIFS('Mar 2026'!$J$29:$J$528,'Mar 2026'!$E$29:$E$528,$A24,'Mar 2026'!$I$29:$I$528,"Opening Balance")+SUMIFS('Apr 2026'!$J$29:$J$528,'Apr 2026'!$E$29:$E$528,$A24,'Apr 2026'!$I$29:$I$528,"Opening Balance")+SUMIFS('May 2026'!$J$29:$J$528,'May 2026'!$E$29:$E$528,$A24,'May 2026'!$I$29:$I$528,"Opening Balance")+SUMIFS('Jun 2026'!$J$29:$J$528,'Jun 2026'!$E$29:$E$528,$A24,'Jun 2026'!$I$29:$I$528,"Opening Balance")+SUMIFS('Jul 2026'!$J$29:$J$528,'Jul 2026'!$E$29:$E$528,$A24,'Jul 2026'!$I$29:$I$528,"Opening Balance")+SUMIFS('Aug 2026'!$J$29:$J$528,'Aug 2026'!$E$29:$E$528,$A24,'Aug 2026'!$I$29:$I$528,"Opening Balance")+SUMIFS('Sep 2026'!$J$29:$J$528,'Sep 2026'!$E$29:$E$528,$A24,'Sep 2026'!$I$29:$I$528,"Opening Balance")+SUMIFS('Oct 2026'!$J$29:$J$528,'Oct 2026'!$E$29:$E$528,$A24,'Oct 2026'!$I$29:$I$528,"Opening Balance")+SUMIFS('Nov 2026'!$J$29:$J$528,'Nov 2026'!$E$29:$E$528,$A24,'Nov 2026'!$I$29:$I$528,"Opening Balance")+SUMIFS('Dec 2026'!$J$29:$J$528,'Dec 2026'!$E$29:$E$528,$A24,'Dec 2026'!$I$29:$I$528,"Opening Balance") -> 0 | E24: =C24+D24-B24 -> -757.58
A25: Dining | B25: =SUMIFS('Jan 2026'!$J$29:$J$528,'Jan 2026'!$E$29:$E$528,$A25,'Jan 2026'!$I$29:$I$528,"Expense")+SUMIFS('Feb 2026'!$J$29:$J$528,'Feb 2026'!$E$29:$E$528,$A25,'Feb 2026'!$I$29:$I$528,"Expense")+SUMIFS('Mar 2026'!$J$29:$J$528,'Mar 2026'!$E$29:$E$528,$A25,'Mar 2026'!$I$29:$I$528,"Expense")+SUMIFS('Apr 2026'!$J$29:$J$528,'Apr 2026'!$E$29:$E$528,$A25,'Apr 2026'!$I$29:$I$528,"Expense")+SUMIFS('May 2026'!$J$29:$J$528,'May 2026'!$E$29:$E$528,$A25,'May 2026'!$I$29:$I$528,"Expense")+SUMIFS('Jun 2026'!$J$29:$J$528,'Jun 2026'!$E$29:$E$528,$A25,'Jun 2026'!$I$29:$I$528,"Expense")+SUMIFS('Jul 2026'!$J$29:$J$528,'Jul 2026'!$E$29:$E$528,$A25,'Jul 2026'!$I$29:$I$528,"Expense")+SUMIFS('Aug 2026'!$J$29:$J$528,'Aug 2026'!$E$29:$E$528,$A25,'Aug 2026'!$I$29:$I$528,"Expense")+SUMIFS('Sep 2026'!$J$29:$J$528,'Sep 2026'!$E$29:$E$528,$A25,'Sep 2026'!$I$29:$I$528,"Expense")+SUMIFS('Oct 2026'!$J$29:$J$528,'Oct 2026'!$E$29:$E$528,$A25,'Oct 2026'!$I$29:$I$528,"Expense")+SUMIFS('Nov 2026'!$J$29:$J$528,'Nov 2026'!$E$29:$E$528,$A25,'Nov 2026'!$I$29:$I$528,"Expense")+SUMIFS('Dec 2026'!$J$29:$J$528,'Dec 2026'!$E$29:$E$528,$A25,'Dec 2026'!$I$29:$I$528,"Expense") -> 1053.29 | C25: =SUMIFS('Jan 2026'!$J$29:$J$528,'Jan 2026'!$E$29:$E$528,$A25,'Jan 2026'!$I$29:$I$528,"Income")+SUMIFS('Feb 2026'!$J$29:$J$528,'Feb 2026'!$E$29:$E$528,$A25,'Feb 2026'!$I$29:$I$528,"Income")+SUMIFS('Mar 2026'!$J$29:$J$528,'Mar 2026'!$E$29:$E$528,$A25,'Mar 2026'!$I$29:$I$528,"Income")+SUMIFS('Apr 2026'!$J$29:$J$528,'Apr 2026'!$E$29:$E$528,$A25,'Apr 2026'!$I$29:$I$528,"Income")+SUMIFS('May 2026'!$J$29:$J$528,'May 2026'!$E$29:$E$528,$A25,'May 2026'!$I$29:$I$528,"Income")+SUMIFS('Jun 2026'!$J$29:$J$528,'Jun 2026'!$E$29:$E$528,$A25,'Jun 2026'!$I$29:$I$528,"Income")+SUMIFS('Jul 2026'!$J$29:$J$528,'Jul 2026'!$E$29:$E$528,$A25,'Jul 2026'!$I$29:$I$528,"Income")+SUMIFS('Aug 2026'!$J$29:$J$528,'Aug 2026'!$E$29:$E$528,$A25,'Aug 2026'!$I$29:$I$528,"Income")+SUMIFS('Sep 2026'!$J$29:$J$528,'Sep 2026'!$E$29:$E$528,$A25,'Sep 2026'!$I$29:$I$528,"Income")+SUMIFS('Oct 2026'!$J$29:$J$528,'Oct 2026'!$E$29:$E$528,$A25,'Oct 2026'!$I$29:$I$528,"Income")+SUMIFS('Nov 2026'!$J$29:$J$528,'Nov 2026'!$E$29:$E$528,$A25,'Nov 2026'!$I$29:$I$528,"Income")+SUMIFS('Dec 2026'!$J$29:$J$528,'Dec 2026'!$E$29:$E$528,$A25,'Dec 2026'!$I$29:$I$528,"Income") -> 0 | D25: =SUMIFS('Jan 2026'!$J$29:$J$528,'Jan 2026'!$E$29:$E$528,$A25,'Jan 2026'!$I$29:$I$528,"Opening Balance")+SUMIFS('Feb 2026'!$J$29:$J$528,'Feb 2026'!$E$29:$E$528,$A25,'Feb 2026'!$I$29:$I$528,"Opening Balance")+SUMIFS('Mar 2026'!$J$29:$J$528,'Mar 2026'!$E$29:$E$528,$A25,'Mar 2026'!$I$29:$I$528,"Opening Balance")+SUMIFS('Apr 2026'!$J$29:$J$528,'Apr 2026'!$E$29:$E$528,$A25,'Apr 2026'!$I$29:$I$528,"Opening Balance")+SUMIFS('May 2026'!$J$29:$J$528,'May 2026'!$E$29:$E$528,$A25,'May 2026'!$I$29:$I$528,"Opening Balance")+SUMIFS('Jun 2026'!$J$29:$J$528,'Jun 2026'!$E$29:$E$528,$A25,'Jun 2026'!$I$29:$I$528,"Opening Balance")+SUMIFS('Jul 2026'!$J$29:$J$528,'Jul 2026'!$E$29:$E$528,$A25,'Jul 2026'!$I$29:$I$528,"Opening Balance")+SUMIFS('Aug 2026'!$J$29:$J$528,'Aug 2026'!$E$29:$E$528,$A25,'Aug 2026'!$I$29:$I$528,"Opening Balance")+SUMIFS('Sep 2026'!$J$29:$J$528,'Sep 2026'!$E$29:$E$528,$A25,'Sep 2026'!$I$29:$I$528,"Opening Balance")+SUMIFS('Oct 2026'!$J$29:$J$528,'Oct 2026'!$E$29:$E$528,$A25,'Oct 2026'!$I$29:$I$528,"Opening Balance")+SUMIFS('Nov 2026'!$J$29:$J$528,'Nov 2026'!$E$29:$E$528,$A25,'Nov 2026'!$I$29:$I$528,"Opening Balance")+SUMIFS('Dec 2026'!$J$29:$J$528,'Dec 2026'!$E$29:$E$528,$A25,'Dec 2026'!$I$29:$I$528,"Opening Balance") -> 0 | E25: =C25+D25-B25 -> -1053.29
A26: Transportation | B26: =SUMIFS('Jan 2026'!$J$29:$J$528,'Jan 2026'!$E$29:$E$528,$A26,'Jan 2026'!$I$29:$I$528,"Expense")+SUMIFS('Feb 2026'!$J$29:$J$528,'Feb 2026'!$E$29:$E$528,$A26,'Feb 2026'!$I$29:$I$528,"Expense")+SUMIFS('Mar 2026'!$J$29:$J$528,'Mar 2026'!$E$29:$E$528,$A26,'Mar 2026'!$I$29:$I$528,"Expense")+SUMIFS('Apr 2026'!$J$29:$J$528,'Apr 2026'!$E$29:$E$528,$A26,'Apr 2026'!$I$29:$I$528,"Expense")+SUMIFS('May 2026'!$J$29:$J$528,'May 2026'!$E$29:$E$528,$A26,'May 2026'!$I$29:$I$528,"Expense")+SUMIFS('Jun 2026'!$J$29:$J$528,'Jun 2026'!$E$29:$E$528,$A26,'Jun 2026'!$I$29:$I$528,"Expense")+SUMIFS('Jul 2026'!$J$29:$J$528,'Jul 2026'!$E$29:$E$528,$A26,'Jul 2026'!$I$29:$I$528,"Expense")+SUMIFS('Aug 2026'!$J$29:$J$528,'Aug 2026'!$E$29:$E$528,$A26,'Aug 2026'!$I$29:$I$528,"Expense")+SUMIFS('Sep 2026'!$J$29:$J$528,'Sep 2026'!$E$29:$E$528,$A26,'Sep 2026'!$I$29:$I$528,"Expense")+SUMIFS('Oct 2026'!$J$29:$J$528,'Oct 2026'!$E$29:$E$528,$A26,'Oct 2026'!$I$29:$I$528,"Expense")+SUMIFS('Nov 2026'!$J$29:$J$528,'Nov 2026'!$E$29:$E$528,$A26,'Nov 2026'!$I$29:$I$528,"Expense")+SUMIFS('Dec 2026'!$J$29:$J$528,'Dec 2026'!$E$29:$E$528,$A26,'Dec 2026'!$I$29:$I$528,"Expense") -> 298.1 | C26: =SUMIFS('Jan 2026'!$J$29:$J$528,'Jan 2026'!$E$29:$E$528,$A26,'Jan 2026'!$I$29:$I$528,"Income")+SUMIFS('Feb 2026'!$J$29:$J$528,'Feb 2026'!$E$29:$E$528,$A26,'Feb 2026'!$I$29:$I$528,"Income")+SUMIFS('Mar 2026'!$J$29:$J$528,'Mar 2026'!$E$29:$E$528,$A26,'Mar 2026'!$I$29:$I$528,"Income")+SUMIFS('Apr 2026'!$J$29:$J$528,'Apr 2026'!$E$29:$E$528,$A26,'Apr 2026'!$I$29:$I$528,"Income")+SUMIFS('May 2026'!$J$29:$J$528,'May 2026'!$E$29:$E$528,$A26,'May 2026'!$I$29:$I$528,"Income")+SUMIFS('Jun 2026'!$J$29:$J$528,'Jun 2026'!$E$29:$E$528,$A26,'Jun 2026'!$I$29:$I$528,"Income")+SUMIFS('Jul 2026'!$J$29:$J$528,'Jul 2026'!$E$29:$E$528,$A26,'Jul 2026'!$I$29:$I$528,"Income")+SUMIFS('Aug 2026'!$J$29:$J$528,'Aug 2026'!$E$29:$E$528,$A26,'Aug 2026'!$I$29:$I$528,"Income")+SUMIFS('Sep 2026'!$J$29:$J$528,'Sep 2026'!$E$29:$E$528,$A26,'Sep 2026'!$I$29:$I$528,"Income")+SUMIFS('Oct 2026'!$J$29:$J$528,'Oct 2026'!$E$29:$E$528,$A26,'Oct 2026'!$I$29:$I$528,"Income")+SUMIFS('Nov 2026'!$J$29:$J$528,'Nov 2026'!$E$29:$E$528,$A26,'Nov 2026'!$I$29:$I$528,"Income")+SUMIFS('Dec 2026'!$J$29:$J$528,'Dec 2026'!$E$29:$E$528,$A26,'Dec 2026'!$I$29:$I$528,"Income") -> 0 | D26: =SUMIFS('Jan 2026'!$J$29:$J$528,'Jan 2026'!$E$29:$E$528,$A26,'Jan 2026'!$I$29:$I$528,"Opening Balance")+SUMIFS('Feb 2026'!$J$29:$J$528,'Feb 2026'!$E$29:$E$528,$A26,'Feb 2026'!$I$29:$I$528,"Opening Balance")+SUMIFS('Mar 2026'!$J$29:$J$528,'Mar 2026'!$E$29:$E$528,$A26,'Mar 2026'!$I$29:$I$528,"Opening Balance")+SUMIFS('Apr 2026'!$J$29:$J$528,'Apr 2026'!$E$29:$E$528,$A26,'Apr 2026'!$I$29:$I$528,"Opening Balance")+SUMIFS('May 2026'!$J$29:$J$528,'May 2026'!$E$29:$E$528,$A26,'May 2026'!$I$29:$I$528,"Opening Balance")+SUMIFS('Jun 2026'!$J$29:$J$528,'Jun 2026'!$E$29:$E$528,$A26,'Jun 2026'!$I$29:$I$528,"Opening Balance")+SUMIFS('Jul 2026'!$J$29:$J$528,'Jul 2026'!$E$29:$E$528,$A26,'Jul 2026'!$I$29:$I$528,"Opening Balance")+SUMIFS('Aug 2026'!$J$29:$J$528,'Aug 2026'!$E$29:$E$528,$A26,'Aug 2026'!$I$29:$I$528,"Opening Balance")+SUMIFS('Sep 2026'!$J$29:$J$528,'Sep 2026'!$E$29:$E$528,$A26,'Sep 2026'!$I$29:$I$528,"Opening Balance")+SUMIFS('Oct 2026'!$J$29:$J$528,'Oct 2026'!$E$29:$E$528,$A26,'Oct 2026'!$I$29:$I$528,"Opening Balance")+SUMIFS('Nov 2026'!$J$29:$J$528,'Nov 2026'!$E$29:$E$528,$A26,'Nov 2026'!$I$29:$I$528,"Opening Balance")+SUMIFS('Dec 2026'!$J$29:$J$528,'Dec 2026'!$E$29:$E$528,$A26,'Dec 2026'!$I$29:$I$528,"Opening Balance") -> 0 | E26: =C26+D26-B26 -> -298.1
A27: Health & Medical | B27: =SUMIFS('Jan 2026'!$J$29:$J$528,'Jan 2026'!$E$29:$E$528,$A27,'Jan 2026'!$I$29:$I$528,"Expense")+SUMIFS('Feb 2026'!$J$29:$J$528,'Feb 2026'!$E$29:$E$528,$A27,'Feb 2026'!$I$29:$I$528,"Expense")+SUMIFS('Mar 2026'!$J$29:$J$528,'Mar 2026'!$E$29:$E$528,$A27,'Mar 2026'!$I$29:$I$528,"Expense")+SUMIFS('Apr 2026'!$J$29:$J$528,'Apr 2026'!$E$29:$E$528,$A27,'Apr 2026'!$I$29:$I$528,"Expense")+SUMIFS('May 2026'!$J$29:$J$528,'May 2026'!$E$29:$E$528,$A27,'May 2026'!$I$29:$I$528,"Expense")+SUMIFS('Jun 2026'!$J$29:$J$528,'Jun 2026'!$E$29:$E$528,$A27,'Jun 2026'!$I$29:$I$528,"Expense")+SUMIFS('Jul 2026'!$J$29:$J$528,'Jul 2026'!$E$29:$E$528,$A27,'Jul 2026'!$I$29:$I$528,"Expense")+SUMIFS('Aug 2026'!$J$29:$J$528,'Aug 2026'!$E$29:$E$528,$A27,'Aug 2026'!$I$29:$I$528,"Expense")+SUMIFS('Sep 2026'!$J$29:$J$528,'Sep 2026'!$E$29:$E$528,$A27,'Sep 2026'!$I$29:$I$528,"Expense")+SUMIFS('Oct 2026'!$J$29:$J$528,'Oct 2026'!$E$29:$E$528,$A27,'Oct 2026'!$I$29:$I$528,"Expense")+SUMIFS('Nov 2026'!$J$29:$J$528,'Nov 2026'!$E$29:$E$528,$A27,'Nov 2026'!$I$29:$I$528,"Expense")+SUMIFS('Dec 2026'!$J$29:$J$528,'Dec 2026'!$E$29:$E$528,$A27,'Dec 2026'!$I$29:$I$528,"Expense") -> 0 | C27: =SUMIFS('Jan 2026'!$J$29:$J$528,'Jan 2026'!$E$29:$E$528,$A27,'Jan 2026'!$I$29:$I$528,"Income")+SUMIFS('Feb 2026'!$J$29:$J$528,'Feb 2026'!$E$29:$E$528,$A27,'Feb 2026'!$I$29:$I$528,"Income")+SUMIFS('Mar 2026'!$J$29:$J$528,'Mar 2026'!$E$29:$E$528,$A27,'Mar 2026'!$I$29:$I$528,"Income")+SUMIFS('Apr 2026'!$J$29:$J$528,'Apr 2026'!$E$29:$E$528,$A27,'Apr 2026'!$I$29:$I$528,"Income")+SUMIFS('May 2026'!$J$29:$J$528,'May 2026'!$E$29:$E$528,$A27,'May 2026'!$I$29:$I$528,"Income")+SUMIFS('Jun 2026'!$J$29:$J$528,'Jun 2026'!$E$29:$E$528,$A27,'Jun 2026'!$I$29:$I$528,"Income")+SUMIFS('Jul 2026'!$J$29:$J$528,'Jul 2026'!$E$29:$E$528,$A27,'Jul 2026'!$I$29:$I$528,"Income")+SUMIFS('Aug 2026'!$J$29:$J$528,'Aug 2026'!$E$29:$E$528,$A27,'Aug 2026'!$I$29:$I$528,"Income")+SUMIFS('Sep 2026'!$J$29:$J$528,'Sep 2026'!$E$29:$E$528,$A27,'Sep 2026'!$I$29:$I$528,"Income")+SUMIFS('Oct 2026'!$J$29:$J$528,'Oct 2026'!$E$29:$E$528,$A27,'Oct 2026'!$I$29:$I$528,"Income")+SUMIFS('Nov 2026'!$J$29:$J$528,'Nov 2026'!$E$29:$E$528,$A27,'Nov 2026'!$I$29:$I$528,"Income")+SUMIFS('Dec 2026'!$J$29:$J$528,'Dec 2026'!$E$29:$E$528,$A27,'Dec 2026'!$I$29:$I$528,"Income") -> 0 | D27: =SUMIFS('Jan 2026'!$J$29:$J$528,'Jan 2026'!$E$29:$E$528,$A27,'Jan 2026'!$I$29:$I$528,"Opening Balance")+SUMIFS('Feb 2026'!$J$29:$J$528,'Feb 2026'!$E$29:$E$528,$A27,'Feb 2026'!$I$29:$I$528,"Opening Balance")+SUMIFS('Mar 2026'!$J$29:$J$528,'Mar 2026'!$E$29:$E$528,$A27,'Mar 2026'!$I$29:$I$528,"Opening Balance")+SUMIFS('Apr 2026'!$J$29:$J$528,'Apr 2026'!$E$29:$E$528,$A27,'Apr 2026'!$I$29:$I$528,"Opening Balance")+SUMIFS('May 2026'!$J$29:$J$528,'May 2026'!$E$29:$E$528,$A27,'May 2026'!$I$29:$I$528,"Opening Balance")+SUMIFS('Jun 2026'!$J$29:$J$528,'Jun 2026'!$E$29:$E$528,$A27,'Jun 2026'!$I$29:$I$528,"Opening Balance")+SUMIFS('Jul 2026'!$J$29:$J$528,'Jul 2026'!$E$29:$E$528,$A27,'Jul 2026'!$I$29:$I$528,"Opening Balance")+SUMIFS('Aug 2026'!$J$29:$J$528,'Aug 2026'!$E$29:$E$528,$A27,'Aug 2026'!$I$29:$I$528,"Opening Balance")+SUMIFS('Sep 2026'!$J$29:$J$528,'Sep 2026'!$E$29:$E$528,$A27,'Sep 2026'!$I$29:$I$528,"Opening Balance")+SUMIFS('Oct 2026'!$J$29:$J$528,'Oct 2026'!$E$29:$E$528,$A27,'Oct 2026'!$I$29:$I$528,"Opening Balance")+SUMIFS('Nov 2026'!$J$29:$J$528,'Nov 2026'!$E$29:$E$528,$A27,'Nov 2026'!$I$29:$I$528,"Opening Balance")+SUMIFS('Dec 2026'!$J$29:$J$528,'Dec 2026'!$E$29:$E$528,$A27,'Dec 2026'!$I$29:$I$528,"Opening Balance") -> 0 | E27: =C27+D27-B27 -> 0
A28: Insurance | B28: =SUMIFS('Jan 2026'!$J$29:$J$528,'Jan 2026'!$E$29:$E$528,$A28,'Jan 2026'!$I$29:$I$528,"Expense")+SUMIFS('Feb 2026'!$J$29:$J$528,'Feb 2026'!$E$29:$E$528,$A28,'Feb 2026'!$I$29:$I$528,"Expense")+SUMIFS('Mar 2026'!$J$29:$J$528,'Mar 2026'!$E$29:$E$528,$A28,'Mar 2026'!$I$29:$I$528,"Expense")+SUMIFS('Apr 2026'!$J$29:$J$528,'Apr 2026'!$E$29:$E$528,$A28,'Apr 2026'!$I$29:$I$528,"Expense")+SUMIFS('May 2026'!$J$29:$J$528,'May 2026'!$E$29:$E$528,$A28,'May 2026'!$I$29:$I$528,"Expense")+SUMIFS('Jun 2026'!$J$29:$J$528,'Jun 2026'!$E$29:$E$528,$A28,'Jun 2026'!$I$29:$I$528,"Expense")+SUMIFS('Jul 2026'!$J$29:$J$528,'Jul 2026'!$E$29:$E$528,$A28,'Jul 2026'!$I$29:$I$528,"Expense")+SUMIFS('Aug 2026'!$J$29:$J$528,'Aug 2026'!$E$29:$E$528,$A28,'Aug 2026'!$I$29:$I$528,"Expense")+SUMIFS('Sep 2026'!$J$29:$J$528,'Sep 2026'!$E$29:$E$528,$A28,'Sep 2026'!$I$29:$I$528,"Expense")+SUMIFS('Oct 2026'!$J$29:$J$528,'Oct 2026'!$E$29:$E$528,$A28,'Oct 2026'!$I$29:$I$528,"Expense")+SUMIFS('Nov 2026'!$J$29:$J$528,'Nov 2026'!$E$29:$E$528,$A28,'Nov 2026'!$I$29:$I$528,"Expense")+SUMIFS('Dec 2026'!$J$29:$J$528,'Dec 2026'!$E$29:$E$528,$A28,'Dec 2026'!$I$29:$I$528,"Expense") -> 0 | C28: =SUMIFS('Jan 2026'!$J$29:$J$528,'Jan 2026'!$E$29:$E$528,$A28,'Jan 2026'!$I$29:$I$528,"Income")+SUMIFS('Feb 2026'!$J$29:$J$528,'Feb 2026'!$E$29:$E$528,$A28,'Feb 2026'!$I$29:$I$528,"Income")+SUMIFS('Mar 2026'!$J$29:$J$528,'Mar 2026'!$E$29:$E$528,$A28,'Mar 2026'!$I$29:$I$528,"Income")+SUMIFS('Apr 2026'!$J$29:$J$528,'Apr 2026'!$E$29:$E$528,$A28,'Apr 2026'!$I$29:$I$528,"Income")+SUMIFS('May 2026'!$J$29:$J$528,'May 2026'!$E$29:$E$528,$A28,'May 2026'!$I$29:$I$528,"Income")+SUMIFS('Jun 2026'!$J$29:$J$528,'Jun 2026'!$E$29:$E$528,$A28,'Jun 2026'!$I$29:$I$528,"Income")+SUMIFS('Jul 2026'!$J$29:$J$528,'Jul 2026'!$E$29:$E$528,$A28,'Jul 2026'!$I$29:$I$528,"Income")+SUMIFS('Aug 2026'!$J$29:$J$528,'Aug 2026'!$E$29:$E$528,$A28,'Aug 2026'!$I$29:$I$528,"Income")+SUMIFS('Sep 2026'!$J$29:$J$528,'Sep 2026'!$E$29:$E$528,$A28,'Sep 2026'!$I$29:$I$528,"Income")+SUMIFS('Oct 2026'!$J$29:$J$528,'Oct 2026'!$E$29:$E$528,$A28,'Oct 2026'!$I$29:$I$528,"Income")+SUMIFS('Nov 2026'!$J$29:$J$528,'Nov 2026'!$E$29:$E$528,$A28,'Nov 2026'!$I$29:$I$528,"Income")+SUMIFS('Dec 2026'!$J$29:$J$528,'Dec 2026'!$E$29:$E$528,$A28,'Dec 2026'!$I$29:$I$528,"Income") -> 0 | D28: =SUMIFS('Jan 2026'!$J$29:$J$528,'Jan 2026'!$E$29:$E$528,$A28,'Jan 2026'!$I$29:$I$528,"Opening Balance")+SUMIFS('Feb 2026'!$J$29:$J$528,'Feb 2026'!$E$29:$E$528,$A28,'Feb 2026'!$I$29:$I$528,"Opening Balance")+SUMIFS('Mar 2026'!$J$29:$J$528,'Mar 2026'!$E$29:$E$528,$A28,'Mar 2026'!$I$29:$I$528,"Opening Balance")+SUMIFS('Apr 2026'!$J$29:$J$528,'Apr 2026'!$E$29:$E$528,$A28,'Apr 2026'!$I$29:$I$528,"Opening Balance")+SUMIFS('May 2026'!$J$29:$J$528,'May 2026'!$E$29:$E$528,$A28,'May 2026'!$I$29:$I$528,"Opening Balance")+SUMIFS('Jun 2026'!$J$29:$J$528,'Jun 2026'!$E$29:$E$528,$A28,'Jun 2026'!$I$29:$I$528,"Opening Balance")+SUMIFS('Jul 2026'!$J$29:$J$528,'Jul 2026'!$E$29:$E$528,$A28,'Jul 2026'!$I$29:$I$528,"Opening Balance")+SUMIFS('Aug 2026'!$J$29:$J$528,'Aug 2026'!$E$29:$E$528,$A28,'Aug 2026'!$I$29:$I$528,"Opening Balance")+SUMIFS('Sep 2026'!$J$29:$J$528,'Sep 2026'!$E$29:$E$528,$A28,'Sep 2026'!$I$29:$I$528,"Opening Balance")+SUMIFS('Oct 2026'!$J$29:$J$528,'Oct 2026'!$E$29:$E$528,$A28,'Oct 2026'!$I$29:$I$528,"Opening Balance")+SUMIFS('Nov 2026'!$J$29:$J$528,'Nov 2026'!$E$29:$E$528,$A28,'Nov 2026'!$I$29:$I$528,"Opening Balance")+SUMIFS('Dec 2026'!$J$29:$J$528,'Dec 2026'!$E$29:$E$528,$A28,'Dec 2026'!$I$29:$I$528,"Opening Balance") -> 0 | E28: =C28+D28-B28 -> 0
A29: Debt Payments | B29: =SUMIFS('Jan 2026'!$J$29:$J$528,'Jan 2026'!$E$29:$E$528,$A29,'Jan 2026'!$I$29:$I$528,"Expense")+SUMIFS('Feb 2026'!$J$29:$J$528,'Feb 2026'!$E$29:$E$528,$A29,'Feb 2026'!$I$29:$I$528,"Expense")+SUMIFS('Mar 2026'!$J$29:$J$528,'Mar 2026'!$E$29:$E$528,$A29,'Mar 2026'!$I$29:$I$528,"Expense")+SUMIFS('Apr 2026'!$J$29:$J$528,'Apr 2026'!$E$29:$E$528,$A29,'Apr 2026'!$I$29:$I$528,"Expense")+SUMIFS('May 2026'!$J$29:$J$528,'May 2026'!$E$29:$E$528,$A29,'May 2026'!$I$29:$I$528,"Expense")+SUMIFS('Jun 2026'!$J$29:$J$528,'Jun 2026'!$E$29:$E$528,$A29,'Jun 2026'!$I$29:$I$528,"Expense")+SUMIFS('Jul 2026'!$J$29:$J$528,'Jul 2026'!$E$29:$E$528,$A29,'Jul 2026'!$I$29:$I$528,"Expense")+SUMIFS('Aug 2026'!$J$29:$J$528,'Aug 2026'!$E$29:$E$528,$A29,'Aug 2026'!$I$29:$I$528,"Expense")+SUMIFS('Sep 2026'!$J$29:$J$528,'Sep 2026'!$E$29:$E$528,$A29,'Sep 2026'!$I$29:$I$528,"Expense")+SUMIFS('Oct 2026'!$J$29:$J$528,'Oct 2026'!$E$29:$E$528,$A29,'Oct 2026'!$I$29:$I$528,"Expense")+SUMIFS('Nov 2026'!$J$29:$J$528,'Nov 2026'!$E$29:$E$528,$A29,'Nov 2026'!$I$29:$I$528,"Expense")+SUMIFS('Dec 2026'!$J$29:$J$528,'Dec 2026'!$E$29:$E$528,$A29,'Dec 2026'!$I$29:$I$528,"Expense") -> 0 | C29: =SUMIFS('Jan 2026'!$J$29:$J$528,'Jan 2026'!$E$29:$E$528,$A29,'Jan 2026'!$I$29:$I$528,"Income")+SUMIFS('Feb 2026'!$J$29:$J$528,'Feb 2026'!$E$29:$E$528,$A29,'Feb 2026'!$I$29:$I$528,"Income")+SUMIFS('Mar 2026'!$J$29:$J$528,'Mar 2026'!$E$29:$E$528,$A29,'Mar 2026'!$I$29:$I$528,"Income")+SUMIFS('Apr 2026'!$J$29:$J$528,'Apr 2026'!$E$29:$E$528,$A29,'Apr 2026'!$I$29:$I$528,"Income")+SUMIFS('May 2026'!$J$29:$J$528,'May 2026'!$E$29:$E$528,$A29,'May 2026'!$I$29:$I$528,"Income")+SUMIFS('Jun 2026'!$J$29:$J$528,'Jun 2026'!$E$29:$E$528,$A29,'Jun 2026'!$I$29:$I$528,"Income")+SUMIFS('Jul 2026'!$J$29:$J$528,'Jul 2026'!$E$29:$E$528,$A29,'Jul 2026'!$I$29:$I$528,"Income")+SUMIFS('Aug 2026'!$J$29:$J$528,'Aug 2026'!$E$29:$E$528,$A29,'Aug 2026'!$I$29:$I$528,"Income")+SUMIFS('Sep 2026'!$J$29:$J$528,'Sep 2026'!$E$29:$E$528,$A29,'Sep 2026'!$I$29:$I$528,"Income")+SUMIFS('Oct 2026'!$J$29:$J$528,'Oct 2026'!$E$29:$E$528,$A29,'Oct 2026'!$I$29:$I$528,"Income")+SUMIFS('Nov 2026'!$J$29:$J$528,'Nov 2026'!$E$29:$E$528,$A29,'Nov 2026'!$I$29:$I$528,"Income")+SUMIFS('Dec 2026'!$J$29:$J$528,'Dec 2026'!$E$29:$E$528,$A29,'Dec 2026'!$I$29:$I$528,"Income") -> 0 | D29: =SUMIFS('Jan 2026'!$J$29:$J$528,'Jan 2026'!$E$29:$E$528,$A29,'Jan 2026'!$I$29:$I$528,"Opening Balance")+SUMIFS('Feb 2026'!$J$29:$J$528,'Feb 2026'!$E$29:$E$528,$A29,'Feb 2026'!$I$29:$I$528,"Opening Balance")+SUMIFS('Mar 2026'!$J$29:$J$528,'Mar 2026'!$E$29:$E$528,$A29,'Mar 2026'!$I$29:$I$528,"Opening Balance")+SUMIFS('Apr 2026'!$J$29:$J$528,'Apr 2026'!$E$29:$E$528,$A29,'Apr 2026'!$I$29:$I$528,"Opening Balance")+SUMIFS('May 2026'!$J$29:$J$528,'May 2026'!$E$29:$E$528,$A29,'May 2026'!$I$29:$I$528,"Opening Balance")+SUMIFS('Jun 2026'!$J$29:$J$528,'Jun 2026'!$E$29:$E$528,$A29,'Jun 2026'!$I$29:$I$528,"Opening Balance")+SUMIFS('Jul 2026'!$J$29:$J$528,'Jul 2026'!$E$29:$E$528,$A29,'Jul 2026'!$I$29:$I$528,"Opening Balance")+SUMIFS('Aug 2026'!$J$29:$J$528,'Aug 2026'!$E$29:$E$528,$A29,'Aug 2026'!$I$29:$I$528,"Opening Balance")+SUMIFS('Sep 2026'!$J$29:$J$528,'Sep 2026'!$E$29:$E$528,$A29,'Sep 2026'!$I$29:$I$528,"Opening Balance")+SUMIFS('Oct 2026'!$J$29:$J$528,'Oct 2026'!$E$29:$E$528,$A29,'Oct 2026'!$I$29:$I$528,"Opening Balance")+SUMIFS('Nov 2026'!$J$29:$J$528,'Nov 2026'!$E$29:$E$528,$A29,'Nov 2026'!$I$29:$I$528,"Opening Balance")+SUMIFS('Dec 2026'!$J$29:$J$528,'Dec 2026'!$E$29:$E$528,$A29,'Dec 2026'!$I$29:$I$528,"Opening Balance") -> 0 | E29: =C29+D29-B29 -> 0
A30: Savings & Investments | B30: =SUMIFS('Jan 2026'!$J$29:$J$528,'Jan 2026'!$E$29:$E$528,$A30,'Jan 2026'!$I$29:$I$528,"Expense")+SUMIFS('Feb 2026'!$J$29:$J$528,'Feb 2026'!$E$29:$E$528,$A30,'Feb 2026'!$I$29:$I$528,"Expense")+SUMIFS('Mar 2026'!$J$29:$J$528,'Mar 2026'!$E$29:$E$528,$A30,'Mar 2026'!$I$29:$I$528,"Expense")+SUMIFS('Apr 2026'!$J$29:$J$528,'Apr 2026'!$E$29:$E$528,$A30,'Apr 2026'!$I$29:$I$528,"Expense")+SUMIFS('May 2026'!$J$29:$J$528,'May 2026'!$E$29:$E$528,$A30,'May 2026'!$I$29:$I$528,"Expense")+SUMIFS('Jun 2026'!$J$29:$J$528,'Jun 2026'!$E$29:$E$528,$A30,'Jun 2026'!$I$29:$I$528,"Expense")+SUMIFS('Jul 2026'!$J$29:$J$528,'Jul 2026'!$E$29:$E$528,$A30,'Jul 2026'!$I$29:$I$528,"Expense")+SUMIFS('Aug 2026'!$J$29:$J$528,'Aug 2026'!$E$29:$E$528,$A30,'Aug 2026'!$I$29:$I$528,"Expense")+SUMIFS('Sep 2026'!$J$29:$J$528,'Sep 2026'!$E$29:$E$528,$A30,'Sep 2026'!$I$29:$I$528,"Expense")+SUMIFS('Oct 2026'!$J$29:$J$528,'Oct 2026'!$E$29:$E$528,$A30,'Oct 2026'!$I$29:$I$528,"Expense")+SUMIFS('Nov 2026'!$J$29:$J$528,'Nov 2026'!$E$29:$E$528,$A30,'Nov 2026'!$I$29:$I$528,"Expense")+SUMIFS('Dec 2026'!$J$29:$J$528,'Dec 2026'!$E$29:$E$528,$A30,'Dec 2026'!$I$29:$I$528,"Expense") -> 0 | C30: =SUMIFS('Jan 2026'!$J$29:$J$528,'Jan 2026'!$E$29:$E$528,$A30,'Jan 2026'!$I$29:$I$528,"Income")+SUMIFS('Feb 2026'!$J$29:$J$528,'Feb 2026'!$E$29:$E$528,$A30,'Feb 2026'!$I$29:$I$528,"Income")+SUMIFS('Mar 2026'!$J$29:$J$528,'Mar 2026'!$E$29:$E$528,$A30,'Mar 2026'!$I$29:$I$528,"Income")+SUMIFS('Apr 2026'!$J$29:$J$528,'Apr 2026'!$E$29:$E$528,$A30,'Apr 2026'!$I$29:$I$528,"Income")+SUMIFS('May 2026'!$J$29:$J$528,'May 2026'!$E$29:$E$528,$A30,'May 2026'!$I$29:$I$528,"Income")+SUMIFS('Jun 2026'!$J$29:$J$528,'Jun 2026'!$E$29:$E$528,$A30,'Jun 2026'!$I$29:$I$528,"Income")+SUMIFS('Jul 2026'!$J$29:$J$528,'Jul 2026'!$E$29:$E$528,$A30,'Jul 2026'!$I$29:$I$528,"Income")+SUMIFS('Aug 2026'!$J$29:$J$528,'Aug 2026'!$E$29:$E$528,$A30,'Aug 2026'!$I$29:$I$528,"Income")+SUMIFS('Sep 2026'!$J$29:$J$528,'Sep 2026'!$E$29:$E$528,$A30,'Sep 2026'!$I$29:$I$528,"Income")+SUMIFS('Oct 2026'!$J$29:$J$528,'Oct 2026'!$E$29:$E$528,$A30,'Oct 2026'!$I$29:$I$528,"Income")+SUMIFS('Nov 2026'!$J$29:$J$528,'Nov 2026'!$E$29:$E$528,$A30,'Nov 2026'!$I$29:$I$528,"Income")+SUMIFS('Dec 2026'!$J$29:$J$528,'Dec 2026'!$E$29:$E$528,$A30,'Dec 2026'!$I$29:$I$528,"Income") -> 0 | D30: =SUMIFS('Jan 2026'!$J$29:$J$528,'Jan 2026'!$E$29:$E$528,$A30,'Jan 2026'!$I$29:$I$528,"Opening Balance")+SUMIFS('Feb 2026'!$J$29:$J$528,'Feb 2026'!$E$29:$E$528,$A30,'Feb 2026'!$I$29:$I$528,"Opening Balance")+SUMIFS('Mar 2026'!$J$29:$J$528,'Mar 2026'!$E$29:$E$528,$A30,'Mar 2026'!$I$29:$I$528,"Opening Balance")+SUMIFS('Apr 2026'!$J$29:$J$528,'Apr 2026'!$E$29:$E$528,$A30,'Apr 2026'!$I$29:$I$528,"Opening Balance")+SUMIFS('May 2026'!$J$29:$J$528,'May 2026'!$E$29:$E$528,$A30,'May 2026'!$I$29:$I$528,"Opening Balance")+SUMIFS('Jun 2026'!$J$29:$J$528,'Jun 2026'!$E$29:$E$528,$A30,'Jun 2026'!$I$29:$I$528,"Opening Balance")+SUMIFS('Jul 2026'!$J$29:$J$528,'Jul 2026'!$E$29:$E$528,$A30,'Jul 2026'!$I$29:$I$528,"Opening Balance")+SUMIFS('Aug 2026'!$J$29:$J$528,'Aug 2026'!$E$29:$E$528,$A30,'Aug 2026'!$I$29:$I$528,"Opening Balance")+SUMIFS('Sep 2026'!$J$29:$J$528,'Sep 2026'!$E$29:$E$528,$A30,'Sep 2026'!$I$29:$I$528,"Opening Balance")+SUMIFS('Oct 2026'!$J$29:$J$528,'Oct 2026'!$E$29:$E$528,$A30,'Oct 2026'!$I$29:$I$528,"Opening Balance")+SUMIFS('Nov 2026'!$J$29:$J$528,'Nov 2026'!$E$29:$E$528,$A30,'Nov 2026'!$I$29:$I$528,"Opening Balance")+SUMIFS('Dec 2026'!$J$29:$J$528,'Dec 2026'!$E$29:$E$528,$A30,'Dec 2026'!$I$29:$I$528,"Opening Balance") -> 0 | E30: =C30+D30-B30 -> 0
A31: Personal Care | B31: =SUMIFS('Jan 2026'!$J$29:$J$528,'Jan 2026'!$E$29:$E$528,$A31,'Jan 2026'!$I$29:$I$528,"Expense")+SUMIFS('Feb 2026'!$J$29:$J$528,'Feb 2026'!$E$29:$E$528,$A31,'Feb 2026'!$I$29:$I$528,"Expense")+SUMIFS('Mar 2026'!$J$29:$J$528,'Mar 2026'!$E$29:$E$528,$A31,'Mar 2026'!$I$29:$I$528,"Expense")+SUMIFS('Apr 2026'!$J$29:$J$528,'Apr 2026'!$E$29:$E$528,$A31,'Apr 2026'!$I$29:$I$528,"Expense")+SUMIFS('May 2026'!$J$29:$J$528,'May 2026'!$E$29:$E$528,$A31,'May 2026'!$I$29:$I$528,"Expense")+SUMIFS('Jun 2026'!$J$29:$J$528,'Jun 2026'!$E$29:$E$528,$A31,'Jun 2026'!$I$29:$I$528,"Expense")+SUMIFS('Jul 2026'!$J$29:$J$528,'Jul 2026'!$E$29:$E$528,$A31,'Jul 2026'!$I$29:$I$528,"Expense")+SUMIFS('Aug 2026'!$J$29:$J$528,'Aug 2026'!$E$29:$E$528,$A31,'Aug 2026'!$I$29:$I$528,"Expense")+SUMIFS('Sep 2026'!$J$29:$J$528,'Sep 2026'!$E$29:$E$528,$A31,'Sep 2026'!$I$29:$I$528,"Expense")+SUMIFS('Oct 2026'!$J$29:$J$528,'Oct 2026'!$E$29:$E$528,$A31,'Oct 2026'!$I$29:$I$528,"Expense")+SUMIFS('Nov 2026'!$J$29:$J$528,'Nov 2026'!$E$29:$E$528,$A31,'Nov 2026'!$I$29:$I$528,"Expense")+SUMIFS('Dec 2026'!$J$29:$J$528,'Dec 2026'!$E$29:$E$528,$A31,'Dec 2026'!$I$29:$I$528,"Expense") -> 0 | C31: =SUMIFS('Jan 2026'!$J$29:$J$528,'Jan 2026'!$E$29:$E$528,$A31,'Jan 2026'!$I$29:$I$528,"Income")+SUMIFS('Feb 2026'!$J$29:$J$528,'Feb 2026'!$E$29:$E$528,$A31,'Feb 2026'!$I$29:$I$528,"Income")+SUMIFS('Mar 2026'!$J$29:$J$528,'Mar 2026'!$E$29:$E$528,$A31,'Mar 2026'!$I$29:$I$528,"Income")+SUMIFS('Apr 2026'!$J$29:$J$528,'Apr 2026'!$E$29:$E$528,$A31,'Apr 2026'!$I$29:$I$528,"Income")+SUMIFS('May 2026'!$J$29:$J$528,'May 2026'!$E$29:$E$528,$A31,'May 2026'!$I$29:$I$528,"Income")+SUMIFS('Jun 2026'!$J$29:$J$528,'Jun 2026'!$E$29:$E$528,$A31,'Jun 2026'!$I$29:$I$528,"Income")+SUMIFS('Jul 2026'!$J$29:$J$528,'Jul 2026'!$E$29:$E$528,$A31,'Jul 2026'!$I$29:$I$528,"Income")+SUMIFS('Aug 2026'!$J$29:$J$528,'Aug 2026'!$E$29:$E$528,$A31,'Aug 2026'!$I$29:$I$528,"Income")+SUMIFS('Sep 2026'!$J$29:$J$528,'Sep 2026'!$E$29:$E$528,$A31,'Sep 2026'!$I$29:$I$528,"Income")+SUMIFS('Oct 2026'!$J$29:$J$528,'Oct 2026'!$E$29:$E$528,$A31,'Oct 2026'!$I$29:$I$528,"Income")+SUMIFS('Nov 2026'!$J$29:$J$528,'Nov 2026'!$E$29:$E$528,$A31,'Nov 2026'!$I$29:$I$528,"Income")+SUMIFS('Dec 2026'!$J$29:$J$528,'Dec 2026'!$E$29:$E$528,$A31,'Dec 2026'!$I$29:$I$528,"Income") -> 0 | D31: =SUMIFS('Jan 2026'!$J$29:$J$528,'Jan 2026'!$E$29:$E$528,$A31,'Jan 2026'!$I$29:$I$528,"Opening Balance")+SUMIFS('Feb 2026'!$J$29:$J$528,'Feb 2026'!$E$29:$E$528,$A31,'Feb 2026'!$I$29:$I$528,"Opening Balance")+SUMIFS('Mar 2026'!$J$29:$J$528,'Mar 2026'!$E$29:$E$528,$A31,'Mar 2026'!$I$29:$I$528,"Opening Balance")+SUMIFS('Apr 2026'!$J$29:$J$528,'Apr 2026'!$E$29:$E$528,$A31,'Apr 2026'!$I$29:$I$528,"Opening Balance")+SUMIFS('May 2026'!$J$29:$J$528,'May 2026'!$E$29:$E$528,$A31,'May 2026'!$I$29:$I$528,"Opening Balance")+SUMIFS('Jun 2026'!$J$29:$J$528,'Jun 2026'!$E$29:$E$528,$A31,'Jun 2026'!$I$29:$I$528,"Opening Balance")+SUMIFS('Jul 2026'!$J$29:$J$528,'Jul 2026'!$E$29:$E$528,$A31,'Jul 2026'!$I$29:$I$528,"Opening Balance")+SUMIFS('Aug 2026'!$J$29:$J$528,'Aug 2026'!$E$29:$E$528,$A31,'Aug 2026'!$I$29:$I$528,"Opening Balance")+SUMIFS('Sep 2026'!$J$29:$J$528,'Sep 2026'!$E$29:$E$528,$A31,'Sep 2026'!$I$29:$I$528,"Opening Balance")+SUMIFS('Oct 2026'!$J$29:$J$528,'Oct 2026'!$E$29:$E$528,$A31,'Oct 2026'!$I$29:$I$528,"Opening Balance")+SUMIFS('Nov 2026'!$J$29:$J$528,'Nov 2026'!$E$29:$E$528,$A31,'Nov 2026'!$I$29:$I$528,"Opening Balance")+SUMIFS('Dec 2026'!$J$29:$J$528,'Dec 2026'!$E$29:$E$528,$A31,'Dec 2026'!$I$29:$I$528,"Opening Balance") -> 0 | E31: =C31+D31-B31 -> 0
A32: Shopping | B32: =SUMIFS('Jan 2026'!$J$29:$J$528,'Jan 2026'!$E$29:$E$528,$A32,'Jan 2026'!$I$29:$I$528,"Expense")+SUMIFS('Feb 2026'!$J$29:$J$528,'Feb 2026'!$E$29:$E$528,$A32,'Feb 2026'!$I$29:$I$528,"Expense")+SUMIFS('Mar 2026'!$J$29:$J$528,'Mar 2026'!$E$29:$E$528,$A32,'Mar 2026'!$I$29:$I$528,"Expense")+SUMIFS('Apr 2026'!$J$29:$J$528,'Apr 2026'!$E$29:$E$528,$A32,'Apr 2026'!$I$29:$I$528,"Expense")+SUMIFS('May 2026'!$J$29:$J$528,'May 2026'!$E$29:$E$528,$A32,'May 2026'!$I$29:$I$528,"Expense")+SUMIFS('Jun 2026'!$J$29:$J$528,'Jun 2026'!$E$29:$E$528,$A32,'Jun 2026'!$I$29:$I$528,"Expense")+SUMIFS('Jul 2026'!$J$29:$J$528,'Jul 2026'!$E$29:$E$528,$A32,'Jul 2026'!$I$29:$I$528,"Expense")+SUMIFS('Aug 2026'!$J$29:$J$528,'Aug 2026'!$E$29:$E$528,$A32,'Aug 2026'!$I$29:$I$528,"Expense")+SUMIFS('Sep 2026'!$J$29:$J$528,'Sep 2026'!$E$29:$E$528,$A32,'Sep 2026'!$I$29:$I$528,"Expense")+SUMIFS('Oct 2026'!$J$29:$J$528,'Oct 2026'!$E$29:$E$528,$A32,'Oct 2026'!$I$29:$I$528,"Expense")+SUMIFS('Nov 2026'!$J$29:$J$528,'Nov 2026'!$E$29:$E$528,$A32,'Nov 2026'!$I$29:$I$528,"Expense")+SUMIFS('Dec 2026'!$J$29:$J$528,'Dec 2026'!$E$29:$E$528,$A32,'Dec 2026'!$I$29:$I$528,"Expense") -> 521.78 | C32: =SUMIFS('Jan 2026'!$J$29:$J$528,'Jan 2026'!$E$29:$E$528,$A32,'Jan 2026'!$I$29:$I$528,"Income")+SUMIFS('Feb 2026'!$J$29:$J$528,'Feb 2026'!$E$29:$E$528,$A32,'Feb 2026'!$I$29:$I$528,"Income")+SUMIFS('Mar 2026'!$J$29:$J$528,'Mar 2026'!$E$29:$E$528,$A32,'Mar 2026'!$I$29:$I$528,"Income")+SUMIFS('Apr 2026'!$J$29:$J$528,'Apr 2026'!$E$29:$E$528,$A32,'Apr 2026'!$I$29:$I$528,"Income")+SUMIFS('May 2026'!$J$29:$J$528,'May 2026'!$E$29:$E$528,$A32,'May 2026'!$I$29:$I$528,"Income")+SUMIFS('Jun 2026'!$J$29:$J$528,'Jun 2026'!$E$29:$E$528,$A32,'Jun 2026'!$I$29:$I$528,"Income")+SUMIFS('Jul 2026'!$J$29:$J$528,'Jul 2026'!$E$29:$E$528,$A32,'Jul 2026'!$I$29:$I$528,"Income")+SUMIFS('Aug 2026'!$J$29:$J$528,'Aug 2026'!$E$29:$E$528,$A32,'Aug 2026'!$I$29:$I$528,"Income")+SUMIFS('Sep 2026'!$J$29:$J$528,'Sep 2026'!$E$29:$E$528,$A32,'Sep 2026'!$I$29:$I$528,"Income")+SUMIFS('Oct 2026'!$J$29:$J$528,'Oct 2026'!$E$29:$E$528,$A32,'Oct 2026'!$I$29:$I$528,"Income")+SUMIFS('Nov 2026'!$J$29:$J$528,'Nov 2026'!$E$29:$E$528,$A32,'Nov 2026'!$I$29:$I$528,"Income")+SUMIFS('Dec 2026'!$J$29:$J$528,'Dec 2026'!$E$29:$E$528,$A32,'Dec 2026'!$I$29:$I$528,"Income") -> 0 | D32: =SUMIFS('Jan 2026'!$J$29:$J$528,'Jan 2026'!$E$29:$E$528,$A32,'Jan 2026'!$I$29:$I$528,"Opening Balance")+SUMIFS('Feb 2026'!$J$29:$J$528,'Feb 2026'!$E$29:$E$528,$A32,'Feb 2026'!$I$29:$I$528,"Opening Balance")+SUMIFS('Mar 2026'!$J$29:$J$528,'Mar 2026'!$E$29:$E$528,$A32,'Mar 2026'!$I$29:$I$528,"Opening Balance")+SUMIFS('Apr 2026'!$J$29:$J$528,'Apr 2026'!$E$29:$E$528,$A32,'Apr 2026'!$I$29:$I$528,"Opening Balance")+SUMIFS('May 2026'!$J$29:$J$528,'May 2026'!$E$29:$E$528,$A32,'May 2026'!$I$29:$I$528,"Opening Balance")+SUMIFS('Jun 2026'!$J$29:$J$528,'Jun 2026'!$E$29:$E$528,$A32,'Jun 2026'!$I$29:$I$528,"Opening Balance")+SUMIFS('Jul 2026'!$J$29:$J$528,'Jul 2026'!$E$29:$E$528,$A32,'Jul 2026'!$I$29:$I$528,"Opening Balance")+SUMIFS('Aug 2026'!$J$29:$J$528,'Aug 2026'!$E$29:$E$528,$A32,'Aug 2026'!$I$29:$I$528,"Opening Balance")+SUMIFS('Sep 2026'!$J$29:$J$528,'Sep 2026'!$E$29:$E$528,$A32,'Sep 2026'!$I$29:$I$528,"Opening Balance")+SUMIFS('Oct 2026'!$J$29:$J$528,'Oct 2026'!$E$29:$E$528,$A32,'Oct 2026'!$I$29:$I$528,"Opening Balance")+SUMIFS('Nov 2026'!$J$29:$J$528,'Nov 2026'!$E$29:$E$528,$A32,'Nov 2026'!$I$29:$I$528,"Opening Balance")+SUMIFS('Dec 2026'!$J$29:$J$528,'Dec 2026'!$E$29:$E$528,$A32,'Dec 2026'!$I$29:$I$528,"Opening Balance") -> 0 | E32: =C32+D32-B32 -> -521.78
A33: Entertainment | B33: =SUMIFS('Jan 2026'!$J$29:$J$528,'Jan 2026'!$E$29:$E$528,$A33,'Jan 2026'!$I$29:$I$528,"Expense")+SUMIFS('Feb 2026'!$J$29:$J$528,'Feb 2026'!$E$29:$E$528,$A33,'Feb 2026'!$I$29:$I$528,"Expense")+SUMIFS('Mar 2026'!$J$29:$J$528,'Mar 2026'!$E$29:$E$528,$A33,'Mar 2026'!$I$29:$I$528,"Expense")+SUMIFS('Apr 2026'!$J$29:$J$528,'Apr 2026'!$E$29:$E$528,$A33,'Apr 2026'!$I$29:$I$528,"Expense")+SUMIFS('May 2026'!$J$29:$J$528,'May 2026'!$E$29:$E$528,$A33,'May 2026'!$I$29:$I$528,"Expense")+SUMIFS('Jun 2026'!$J$29:$J$528,'Jun 2026'!$E$29:$E$528,$A33,'Jun 2026'!$I$29:$I$528,"Expense")+SUMIFS('Jul 2026'!$J$29:$J$528,'Jul 2026'!$E$29:$E$528,$A33,'Jul 2026'!$I$29:$I$528,"Expense")+SUMIFS('Aug 2026'!$J$29:$J$528,'Aug 2026'!$E$29:$E$528,$A33,'Aug 2026'!$I$29:$I$528,"Expense")+SUMIFS('Sep 2026'!$J$29:$J$528,'Sep 2026'!$E$29:$E$528,$A33,'Sep 2026'!$I$29:$I$528,"Expense")+SUMIFS('Oct 2026'!$J$29:$J$528,'Oct 2026'!$E$29:$E$528,$A33,'Oct 2026'!$I$29:$I$528,"Expense")+SUMIFS('Nov 2026'!$J$29:$J$528,'Nov 2026'!$E$29:$E$528,$A33,'Nov 2026'!$I$29:$I$528,"Expense")+SUMIFS('Dec 2026'!$J$29:$J$528,'Dec 2026'!$E$29:$E$528,$A33,'Dec 2026'!$I$29:$I$528,"Expense") -> 543.59 | C33: =SUMIFS('Jan 2026'!$J$29:$J$528,'Jan 2026'!$E$29:$E$528,$A33,'Jan 2026'!$I$29:$I$528,"Income")+SUMIFS('Feb 2026'!$J$29:$J$528,'Feb 2026'!$E$29:$E$528,$A33,'Feb 2026'!$I$29:$I$528,"Income")+SUMIFS('Mar 2026'!$J$29:$J$528,'Mar 2026'!$E$29:$E$528,$A33,'Mar 2026'!$I$29:$I$528,"Income")+SUMIFS('Apr 2026'!$J$29:$J$528,'Apr 2026'!$E$29:$E$528,$A33,'Apr 2026'!$I$29:$I$528,"Income")+SUMIFS('May 2026'!$J$29:$J$528,'May 2026'!$E$29:$E$528,$A33,'May 2026'!$I$29:$I$528,"Income")+SUMIFS('Jun 2026'!$J$29:$J$528,'Jun 2026'!$E$29:$E$528,$A33,'Jun 2026'!$I$29:$I$528,"Income")+SUMIFS('Jul 2026'!$J$29:$J$528,'Jul 2026'!$E$29:$E$528,$A33,'Jul 2026'!$I$29:$I$528,"Income")+SUMIFS('Aug 2026'!$J$29:$J$528,'Aug 2026'!$E$29:$E$528,$A33,'Aug 2026'!$I$29:$I$528,"Income")+SUMIFS('Sep 2026'!$J$29:$J$528,'Sep 2026'!$E$29:$E$528,$A33,'Sep 2026'!$I$29:$I$528,"Income")+SUMIFS('Oct 2026'!$J$29:$J$528,'Oct 2026'!$E$29:$E$528,$A33,'Oct 2026'!$I$29:$I$528,"Income")+SUMIFS('Nov 2026'!$J$29:$J$528,'Nov 2026'!$E$29:$E$528,$A33,'Nov 2026'!$I$29:$I$528,"Income")+SUMIFS('Dec 2026'!$J$29:$J$528,'Dec 2026'!$E$29:$E$528,$A33,'Dec 2026'!$I$29:$I$528,"Income") -> 0 | D33: =SUMIFS('Jan 2026'!$J$29:$J$528,'Jan 2026'!$E$29:$E$528,$A33,'Jan 2026'!$I$29:$I$528,"Opening Balance")+SUMIFS('Feb 2026'!$J$29:$J$528,'Feb 2026'!$E$29:$E$528,$A33,'Feb 2026'!$I$29:$I$528,"Opening Balance")+SUMIFS('Mar 2026'!$J$29:$J$528,'Mar 2026'!$E$29:$E$528,$A33,'Mar 2026'!$I$29:$I$528,"Opening Balance")+SUMIFS('Apr 2026'!$J$29:$J$528,'Apr 2026'!$E$29:$E$528,$A33,'Apr 2026'!$I$29:$I$528,"Opening Balance")+SUMIFS('May 2026'!$J$29:$J$528,'May 2026'!$E$29:$E$528,$A33,'May 2026'!$I$29:$I$528,"Opening Balance")+SUMIFS('Jun 2026'!$J$29:$J$528,'Jun 2026'!$E$29:$E$528,$A33,'Jun 2026'!$I$29:$I$528,"Opening Balance")+SUMIFS('Jul 2026'!$J$29:$J$528,'Jul 2026'!$E$29:$E$528,$A33,'Jul 2026'!$I$29:$I$528,"Opening Balance")+SUMIFS('Aug 2026'!$J$29:$J$528,'Aug 2026'!$E$29:$E$528,$A33,'Aug 2026'!$I$29:$I$528,"Opening Balance")+SUMIFS('Sep 2026'!$J$29:$J$528,'Sep 2026'!$E$29:$E$528,$A33,'Sep 2026'!$I$29:$I$528,"Opening Balance")+SUMIFS('Oct 2026'!$J$29:$J$528,'Oct 2026'!$E$29:$E$528,$A33,'Oct 2026'!$I$29:$I$528,"Opening Balance")+SUMIFS('Nov 2026'!$J$29:$J$528,'Nov 2026'!$E$29:$E$528,$A33,'Nov 2026'!$I$29:$I$528,"Opening Balance")+SUMIFS('Dec 2026'!$J$29:$J$528,'Dec 2026'!$E$29:$E$528,$A33,'Dec 2026'!$I$29:$I$528,"Opening Balance") -> 0 | E33: =C33+D33-B33 -> -543.59
... A42: Other | B42: =SUMIFS('Jan 2026'!$J$29:$J$528,'Jan 2026'!$E$29:$E$528,$A42,'Jan 2026'!$I$29:$I$528,"Expense")+SUMIFS('Feb 2026'!$J$29:$J$528,'Feb 2026'!$E$29:$E$528,$A42,'Feb 2026'!$I$29:$I$528,"Expense")+SUMIFS('Mar 2026'!$J$29:$J$528,'Mar 2026'!$E$29:$E$528,$A42,'Mar 2026'!$I$29:$I$528,"Expense")+SUMIFS('Apr 2026'!$J$29:$J$528,'Apr 2026'!$E$29:$E$528,$A42,'Apr 2026'!$I$29:$I$528,"Expense")+SUMIFS('May 2026'!$J$29:$J$528,'May 2026'!$E$29:$E$528,$A42,'May 2026'!$I$29:$I$528,"Expense")+SUMIFS('Jun 2026'!$J$29:$J$528,'Jun 2026'!$E$29:$E$528,$A42,'Jun 2026'!$I$29:$I$528,"Expense")+SUMIFS('Jul 2026'!$J$29:$J$528,'Jul 2026'!$E$29:$E$528,$A42,'Jul 2026'!$I$29:$I$528,"Expense")+SUMIFS('Aug 2026'!$J$29:$J$528,'Aug 2026'!$E$29:$E$528,$A42,'Aug 2026'!$I$29:$I$528,"Expense")+SUMIFS('Sep 2026'!$J$29:$J$528,'Sep 2026'!$E$29:$E$528,$A42,'Sep 2026'!$I$29:$I$528,"Expense")+SUMIFS('Oct 2026'!$J$29:$J$528,'Oct 2026'!$E$29:$E$528,$A42,'Oct 2026'!$I$29:$I$528,"Expense")+SUMIFS('Nov 2026'!$J$29:$J$528,'Nov 2026'!$E$29:$E$528,$A42,'Nov 2026'!$I$29:$I$528,"Expense")+SUMIFS('Dec 2026'!$J$29:$J$528,'Dec 2026'!$E$29:$E$528,$A42,'Dec 2026'!$I$29:$I$528,"Expense") -> 0 | C42: =SUMIFS('Jan 2026'!$J$29:$J$528,'Jan 2026'!$E$29:$E$528,$A42,'Jan 2026'!$I$29:$I$528,"Income")+SUMIFS('Feb 2026'!$J$29:$J$528,'Feb 2026'!$E$29:$E$528,$A42,'Feb 2026'!$I$29:$I$528,"Income")+SUMIFS('Mar 2026'!$J$29:$J$528,'Mar 2026'!$E$29:$E$528,$A42,'Mar 2026'!$I$29:$I$528,"Income")+SUMIFS('Apr 2026'!$J$29:$J$528,'Apr 2026'!$E$29:$E$528,$A42,'Apr 2026'!$I$29:$I$528,"Income")+SUMIFS('May 2026'!$J$29:$J$528,'May 2026'!$E$29:$E$528,$A42,'May 2026'!$I$29:$I$528,"Income")+SUMIFS('Jun 2026'!$J$29:$J$528,'Jun 2026'!$E$29:$E$528,$A42,'Jun 2026'!$I$29:$I$528,"Income")+SUMIFS('Jul 2026'!$J$29:$J$528,'Jul 2026'!$E$29:$E$528,$A42,'Jul 2026'!$I$29:$I$528,"Income")+SUMIFS('Aug 2026'!$J$29:$J$528,'Aug 2026'!$E$29:$E$528,$A42,'Aug 2026'!$I$29:$I$528,"Income")+SUMIFS('Sep 2026'!$J$29:$J$528,'Sep 2026'!$E$29:$E$528,$A42,'Sep 2026'!$I$29:$I$528,"Income")+SUMIFS('Oct 2026'!$J$29:$J$528,'Oct 2026'!$E$29:$E$528,$A42,'Oct 2026'!$I$29:$I$528,"Income")+SUMIFS('Nov 2026'!$J$29:$J$528,'Nov 2026'!$E$29:$E$528,$A42,'Nov 2026'!$I$29:$I$528,"Income")+SUMIFS('Dec 2026'!$J$29:$J$528,'Dec 2026'!$E$29:$E$528,$A42,'Dec 2026'!$I$29:$I$528,"Income") -> 0 | D42: =SUMIFS('Jan 2026'!$J$29:$J$528,'Jan 2026'!$E$29:$E$528,$A42,'Jan 2026'!$I$29:$I$528,"Opening Balance")+SUMIFS('Feb 2026'!$J$29:$J$528,'Feb 2026'!$E$29:$E$528,$A42,'Feb 2026'!$I$29:$I$528,"Opening Balance")+SUMIFS('Mar 2026'!$J$29:$J$528,'Mar 2026'!$E$29:$E$528,$A42,'Mar 2026'!$I$29:$I$528,"Opening Balance")+SUMIFS('Apr 2026'!$J$29:$J$528,'Apr 2026'!$E$29:$E$528,$A42,'Apr 2026'!$I$29:$I$528,"Opening Balance")+SUMIFS('May 2026'!$J$29:$J$528,'May 2026'!$E$29:$E$528,$A42,'May 2026'!$I$29:$I$528,"Opening Balance")+SUMIFS('Jun 2026'!$J$29:$J$528,'Jun 2026'!$E$29:$E$528,$A42,'Jun 2026'!$I$29:$I$528,"Opening Balance")+SUMIFS('Jul 2026'!$J$29:$J$528,'Jul 2026'!$E$29:$E$528,$A42,'Jul 2026'!$I$29:$I$528,"Opening Balance")+SUMIFS('Aug 2026'!$J$29:$J$528,'Aug 2026'!$E$29:$E$528,$A42,'Aug 2026'!$I$29:$I$528,"Opening Balance")+SUMIFS('Sep 2026'!$J$29:$J$528,'Sep 2026'!$E$29:$E$528,$A42,'Sep 2026'!$I$29:$I$528,"Opening Balance")+SUMIFS('Oct 2026'!$J$29:$J$528,'Oct 2026'!$E$29:$E$528,$A42,'Oct 2026'!$I$29:$I$528,"Opening Balance")+SUMIFS('Nov 2026'!$J$29:$J$528,'Nov 2026'!$E$29:$E$528,$A42,'Nov 2026'!$I$29:$I$528,"Opening Balance")+SUMIFS('Dec 2026'!$J$29:$J$528,'Dec 2026'!$E$29:$E$528,$A42,'Dec 2026'!$I$29:$I$528,"Opening Balance") -> 0 | E42: =C42+D42-B42 -> 0

Sheet Jan 2026
A1: January 2026 Ledger
A2: Use positive amounts. Choose Type to classify each transaction.
A4: Month Summary | D4: Category Summary | H4: Weekly Summary
A5: Total Income | B5: =SUMIFS($J$29:$J$528,$I$29:$I$528,"Income") | D5: Category | E5: Expenses | F5: Income | G5: Existing Savings | H5: Week | I5: Expenses | J5: Income | K5: Net
A6: Total Expenses | B6: =SUMIFS($J$29:$J$528,$I$29:$I$528,"Expense") | D6: Housing | E6: =SUMIFS($J$29:$J$528,$E$29:$E$528,$D6,$I$29:$I$528,"Expense") | F6: =SUMIFS($J$29:$J$528,$E$29:$E$528,$D6,$I$29:$I$528,"Income") | G6: =SUMIFS($J$29:$J$528,$E$29:$E$528,$D6,$I$29:$I$528,"Opening Balance") | H6: Week 1 | I6: =SUMIFS($J$29:$J$528,$B$29:$B$528,1,$I$29:$I$528,"Expense",$F$29:$F$528,"<>Rent") | J6: =SUMIFS($J$29:$J$528,$B$29:$B$528,1,$I$29:$I$528,"Income") | K6: =J6-I6
A7: Existing Savings | B7: =SUMIFS($J$29:$J$528,$I$29:$I$528,"Opening Balance") | D7: Utilities | E7: =SUMIFS($J$29:$J$528,$E$29:$E$528,$D7,$I$29:$I$528,"Expense") | F7: =SUMIFS($J$29:$J$528,$E$29:$E$528,$D7,$I$29:$I$528,"Income") | G7: =SUMIFS($J$29:$J$528,$E$29:$E$528,$D7,$I$29:$I$528,"Opening Balance") | H7: Week 2 | I7: =SUMIFS($J$29:$J$528,$B$29:$B$528,2,$I$29:$I$528,"Expense",$F$29:$F$528,"<>Rent") | J7: =SUMIFS($J$29:$J$528,$B$29:$B$528,2,$I$29:$I$528,"Income") | K7: =J7-I7
A8: Transfers | B8: =SUMIFS($J$29:$J$528,$I$29:$I$528,"Transfer") | D8: Groceries | E8: =SUMIFS($J$29:$J$528,$E$29:$E$528,$D8,$I$29:$I$528,"Expense") | F8: =SUMIFS($J$29:$J$528,$E$29:$E$528,$D8,$I$29:$I$528,"Income") | G8: =SUMIFS($J$29:$J$528,$E$29:$E$528,$D8,$I$29:$I$528,"Opening Balance") | H8: Week 3 | I8: =SUMIFS($J$29:$J$528,$B$29:$B$528,3,$I$29:$I$528,"Expense",$F$29:$F$528,"<>Rent") | J8: =SUMIFS($J$29:$J$528,$B$29:$B$528,3,$I$29:$I$528,"Income") | K8: =J8-I8
A9: Net Cash Flow | B9: =B5-B6 | D9: Dining | E9: =SUMIFS($J$29:$J$528,$E$29:$E$528,$D9,$I$29:$I$528,"Expense") | F9: =SUMIFS($J$29:$J$528,$E$29:$E$528,$D9,$I$29:$I$528,"Income") | G9: =SUMIFS($J$29:$J$528,$E$29:$E$528,$D9,$I$29:$I$528,"Opening Balance") | H9: Week 4 | I9: =SUMIFS($J$29:$J$528,$B$29:$B$528,4,$I$29:$I$528,"Expense",$F$29:$F$528,"<>Rent") | J9: =SUMIFS($J$29:$J$528,$B$29:$B$528,4,$I$29:$I$528,"Income") | K9: =J9-I9
D10: Transportation | E10: =SUMIFS($J$29:$J$528,$E$29:$E$528,$D10,$I$29:$I$528,"Expense") | F10: =SUMIFS($J$29:$J$528,$E$29:$E$528,$D10,$I$29:$I$528,"Income") | G10: =SUMIFS($J$29:$J$528,$E$29:$E$528,$D10,$I$29:$I$528,"Opening Balance") | H10: Week 5 | I10: =SUMIFS($J$29:$J$528,$B$29:$B$528,5,$I$29:$I$528,"Expense",$F$29:$F$528,"<>Rent") | J10: =SUMIFS($J$29:$J$528,$B$29:$B$528,5,$I$29:$I$528,"Income") | K10: =J10-I10
D11: Health & Medical | E11: =SUMIFS($J$29:$J$528,$E$29:$E$528,$D11,$I$29:$I$528,"Expense") | F11: =SUMIFS($J$29:$J$528,$E$29:$E$528,$D11,$I$29:$I$528,"Income") | G11: =SUMIFS($J$29:$J$528,$E$29:$E$528,$D11,$I$29:$I$528,"Opening Balance")
D12: Insurance | E12: =SUMIFS($J$29:$J$528,$E$29:$E$528,$D12,$I$29:$I$528,"Expense") | F12: =SUMIFS($J$29:$J$528,$E$29:$E$528,$D12,$I$29:$I$528,"Income") | G12: =SUMIFS($J$29:$J$528,$E$29:$E$528,$D12,$I$29:$I$528,"Opening Balance")
D13: Debt Payments | E13: =SUMIFS($J$29:$J$528,$E$29:$E$528,$D13,$I$29:$I$528,"Expense") | F13: =SUMIFS($J$29:$J$528,$E$29:$E$528,$D13,$I$29:$I$528,"Income") | G13: =SUMIFS($J$29:$J$528,$E$29:$E$528,$D13,$I$29:$I$528,"Opening Balance")
D14: Savings & Investments | E14: =SUMIFS($J$29:$J$528,$E$29:$E$528,$D14,$I$29:$I$528,"Expense") | F14: =SUMIFS($J$29:$J$528,$E$29:$E$528,$D14,$I$29:$I$528,"Income") | G14: =SUMIFS($J$29:$J$528,$E$29:$E$528,$D14,$I$29:$I$528,"Opening Balance")
D15: Personal Care | E15: =SUMIFS($J$29:$J$528,$E$29:$E$528,$D15,$I$29:$I$528,"Expense") | F15: =SUMIFS($J$29:$J$528,$E$29:$E$528,$D15,$I$29:$I$528,"Income") | G15: =SUMIFS($J$29:$J$528,$E$29:$E$528,$D15,$I$29:$I$528,"Opening Balance")
D16: Shopping | E16: =SUMIFS($J$29:$J$528,$E$29:$E$528,$D16,$I$29:$I$528,"Expense") | F16: =SUMIFS($J$29:$J$528,$E$29:$E$528,$D16,$I$29:$I$528,"Income") | G16: =SUMIFS($J$29:$J$528,$E$29:$E$528,$D16,$I$29:$I$528,"Opening Balance")
D17: Entertainment | E17: =SUMIFS($J$29:$J$528,$E$29:$E$528,$D17,$I$29:$I$528,"Expense") | F17: =SUMIFS($J$29:$J$528,$E$29:$E$528,$D17,$I$29:$I$528,"Income") | G17: =SUMIFS($J$29:$J$528,$E$29:$E$528,$D17,$I$29:$I$528,"Opening Balance")
D18: Travel | E18: =SUMIFS($J$29:$J$528,$E$29:$E$528,$D18,$I$29:$I$528,"Expense") | F18: =SUMIFS($J$29:$J$528,$E$29:$E$528,$D18,$I$29:$I$528,"Income") | G18: =SUMIFS($J$29:$J$528,$E$29:$E$528,$D18,$I$29:$I$528,"Opening Balance")
D19: Education | E19: =SUMIFS($J$29:$J$528,$E$29:$E$528,$D19,$I$29:$I$528,"Expense") | F19: =SUMIFS($J$29:$J$528,$E$29:$E$528,$D19,$I$29:$I$528,"Income") | G19: =SUMIFS($J$29:$J$528,$E$29:$E$528,$D19,$I$29:$I$528,"Opening Balance")
D20: Gifts & Donations | E20: =SUMIFS($J$29:$J$528,$E$29:$E$528,$D20,$I$29:$I$528,"Expense") | F20: =SUMIFS($J$29:$J$528,$E$29:$E$528,$D20,$I$29:$I$528,"Income") | G20: =SUMIFS($J$29:$J$528,$E$29:$E$528,$D20,$I$29:$I$528,"Opening Balance")
D21: Taxes | E21: =SUMIFS($J$29:$J$528,$E$29:$E$528,$D21,$I$29:$I$528,"Expense") | F21: =SUMIFS($J$29:$J$528,$E$29:$E$528,$D21,$I$29:$I$528,"Income") | G21: =SUMIFS($J$29:$J$528,$E$29:$E$528,$D21,$I$29:$I$528,"Opening Balance")
D22: Shipping | E22: =SUMIFS($J$29:$J$528,$E$29:$E$528,$D22,$I$29:$I$528,"Expense") | F22: =SUMIFS($J$29:$J$528,$E$29:$E$528,$D22,$I$29:$I$528,"Income") | G22: =SUMIFS($J$29:$J$528,$E$29:$E$528,$D22,$I$29:$I$528,"Opening Balance")
... D26: Essentials | E26: =SUMIFS($J$29:$J$528,$E$29:$E$528,$D26,$I$29:$I$528,"Expense") | F26: =SUMIFS($J$29:$J$528,$E$29:$E$528,$D26,$I$29:$I$528,"Income") | G26: =SUMIFS($J$29:$J$528,$E$29:$E$528,$D26,$I$29:$I$528,"Opening Balance")
A27: Transactions
A28: Date | B28: Week | C28: Description | D28: Merchant | E28: Category | F28: Subcategory | G28: Account | H28: Payment Method | I28: Type | J28: Amount | K28: Notes
B29: =IF(A29="","",INT((DAY(A29)-1)/7)+1)
B30: =IF(A30="","",INT((DAY(A30)-1)/7)+1)
B31: =IF(A31="","",INT((DAY(A31)-1)/7)+1)
B32: =IF(A32="","",INT((DAY(A32)-1)/7)+1)
B33: =IF(A33="","",INT((DAY(A33)-1)/7)+1)
B34: =IF(A34="","",INT((DAY(A34)-1)/7)+1)
B35: =IF(A35="","",INT((DAY(A35)-1)/7)+1)
B36: =IF(A36="","",INT((DAY(A36)-1)/7)+1)
B37: =IF(A37="","",INT((DAY(A37)-1)/7)+1)
B38: =IF(A38="","",INT((DAY(A38)-1)/7)+1)
B39: =IF(A39="","",INT((DAY(A39)-1)/7)+1)
B40: =IF(A40="","",INT((DAY(A40)-1)/7)+1)
... B528: =IF(A528="","",INT((DAY(A528)-1)/7)+1)

Sheet Feb 2026
A1: February 2026 Ledger
A2: Use positive amounts. Choose Type to classify each transaction.
A4: Month Summary | D4: Category Summary | H4: Weekly Summary
A5: Total Income | B5: =SUMIFS($J$29:$J$528,$I$29:$I$528,"Income") | D5: Category | E5: Expenses | F5: Income | G5: Existing Savings | H5: Week | I5: Expenses | J5: Income | K5: Net
A6: Total Expenses | B6: =SUMIFS($J$29:$J$528,$I$29:$I$528,"Expense") | D6: Housing | E6: =SUMIFS($J$29:$J$528,$E$29:$E$528,$D6,$I$29:$I$528,"Expense") | F6: =SUMIFS($J$29:$J$528,$E$29:$E$528,$D6,$I$29:$I$528,"Income") | G6: =SUMIFS($J$29:$J$528,$E$29:$E$528,$D6,$I$29:$I$528,"Opening Balance") | H6: Week 1 | I6: =SUMIFS($J$29:$J$528,$B$29:$B$528,1,$I$29:$I$528,"Expense",$F$29:$F$528,"<>Rent") | J6: =SUMIFS($J$29:$J$528,$B$29:$B$528,1,$I$29:$I$528,"Income") | K6: =J6-I6
A7: Existing Savings | B7: =SUMIFS($J$29:$J$528,$I$29:$I$528,"Opening Balance") | D7: Utilities | E7: =SUMIFS($J$29:$J$528,$E$29:$E$528,$D7,$I$29:$I$528,"Expense") | F7: =SUMIFS($J$29:$J$528,$E$29:$E$528,$D7,$I$29:$I$528,"Income") | G7: =SUMIFS($J$29:$J$528,$E$29:$E$528,$D7,$I$29:$I$528,"Opening Balance") | H7: Week 2 | I7: =SUMIFS($J$29:$J$528,$B$29:$B$528,2,$I$29:$I$528,"Expense",$F$29:$F$528,"<>Rent") | J7: =SUMIFS($J$29:$J$528,$B$29:$B$528,2,$I$29:$I$528,"Income") | K7: =J7-I7
A8: Transfers | B8: =SUMIFS($J$29:$J$528,$I$29:$I$528,"Transfer") | D8: Groceries | E8: =SUMIFS($J$29:$J$528,$E$29:$E$528,$D8,$I$29:$I$528,"Expense") | F8: =SUMIFS($J$29:$J$528,$E$29:$E$528,$D8,$I$29:$I$528,"Income") | G8: =SUMIFS($J$29:$J$528,$E$29:$E$528,$D8,$I$29:$I$528,"Opening Balance") | H8: Week 3 | I8: =SUMIFS($J$29:$J$528,$B$29:$B$528,3,$I$29:$I$528,"Expense",$F$29:$F$528,"<>Rent") | J8: =SUMIFS($J$29:$J$528,$B$29:$B$528,3,$I$29:$I$528,"Income") | K8: =J8-I8
A9: Net Cash Flow | B9: =B5-B6 | D9: Dining | E9: =SUMIFS($J$29:$J$528,$E$29:$E$528,$D9,$I$29:$I$528,"Expense") | F9: =SUMIFS($J$29:$J$528,$E$29:$E$528,$D9,$I$29:$I$528,"Income") | G9: =SUMIFS($J$29:$J$528,$E$29:$E$528,$D9,$I$29:$I$528,"Opening Balance") | H9: Week 4 | I9: =SUMIFS($J$29:$J$528,$B$29:$B$528,4,$I$29:$I$528,"Expense",$F$29:$F$528,"<>Rent") | J9: =SUMIFS($J$29:$J$528,$B$29:$B$528,4,$I$29:$I$528,"Income") | K9: =J9-I9
D10: Transportation | E10: =SUMIFS($J$29:$J$528,$E$29:$E$528,$D10,$I$29:$I$528,"Expense") | F10: =SUMIFS($J$29:$J$528,$E$29:$E$528,$D10,$I$29:$I$528,"Income") | G10: =SUMIFS($J$29:$J$528,$E$29:$E$528,$D10,$I$29:$I$528,"Opening Balance") | H10: Week 5 | I10: =SUMIFS($J$29:$J$528,$B$29:$B$528,5,$I$29:$I$528,"Expense",$F$29:$F$528,"<>Rent") | J10: =SUMIFS($J$29:$J$528,$B$29:$B$528,5,$I$29:$I$528,"Income") | K10: =J10-I10
D11: Health & Medical | E11: =SUMIFS($J$29:$J$528,$E$29:$E$528,$D11,$I$29:$I$528,"Expense") | F11: =SUMIFS($J$29:$J$528,$E$29:$E$528,$D11,$I$29:$I$528,"Income") | G11: =SUMIFS($J$29:$J$528,$E$29:$E$528,$D11,$I$29:$I$528,"Opening Balance")
D12: Insurance | E12: =SUMIFS($J$29:$J$528,$E$29:$E$528,$D12,$I$29:$I$528,"Expense") | F12: =SUMIFS($J$29:$J$528,$E$29:$E$528,$D12,$I$29:$I$528,"Income") | G12: =SUMIFS($J$29:$J$528,$E$29:$E$528,$D12,$I$29:$I$528,"Opening Balance")
D13: Debt Payments | E13: =SUMIFS($J$29:$J$528,$E$29:$E$528,$D13,$I$29:$I$528,"Expense") | F13: =SUMIFS($J$29:$J$528,$E$29:$E$528,$D13,$I$29:$I$528,"Income") | G13: =SUMIFS($J$29:$J$528,$E$29:$E$528,$D13,$I$29:$I$528,"Opening Balance")
D14: Savings & Investments | E14: =SUMIFS($J$29:$J$528,$E$29:$E$528,$D14,$I$29:$I$528,"Expense") | F14: =SUMIFS($J$29:$J$528,$E$29:$E$528,$D14,$I$29:$I$528,"Income") | G14: =SUMIFS($J$29:$J$528,$E$29:$E$528,$D14,$I$29:$I$528,"Opening Balance")
D15: Personal Care | E15: =SUMIFS($J$29:$J$528,$E$29:$E$528,$D15,$I$29:$I$528,"Expense") | F15: =SUMIFS($J$29:$J$528,$E$29:$E$528,$D15,$I$29:$I$528,"Income") | G15: =SUMIFS($J$29:$J$528,$E$29:$E$528,$D15,$I$29:$I$528,"Opening Balance")
D16: Shopping | E16: =SUMIFS($J$29:$J$528,$E$29:$E$528,$D16,$I$29:$I$528,"Expense") | F16: =SUMIFS($J$29:$J$528,$E$29:$E$528,$D16,$I$29:$I$528,"Income") | G16: =SUMIFS($J$29:$J$528,$E$29:$E$528,$D16,$I$29:$I$528,"Opening Balance")
D17: Entertainment | E17: =SUMIFS($J$29:$J$528,$E$29:$E$528,$D17,$I$29:$I$528,"Expense") | F17: =SUMIFS($J$29:$J$528,$E$29:$E$528,$D17,$I$29:$I$528,"Income") | G17: =SUMIFS($J$29:$J$528,$E$29:$E$528,$D17,$I$29:$I$528,"Opening Balance")
D18: Travel | E18: =SUMIFS($J$29:$J$528,$E$29:$E$528,$D18,$I$29:$I$528,"Expense") | F18: =SUMIFS($J$29:$J$528,$E$29:$E$528,$D18,$I$29:$I$528,"Income") | G18: =SUMIFS($J$29:$J$528,$E$29:$E$528,$D18,$I$29:$I$528,"Opening Balance")
D19: Education | E19: =SUMIFS($J$29:$J$528,$E$29:$E$528,$D19,$I$29:$I$528,"Expense") | F19: =SUMIFS($J$29:$J$528,$E$29:$E$528,$D19,$I$29:$I$528,"Income") | G19: =SUMIFS($J$29:$J$528,$E$29:$E$528,$D19,$I$29:$I$528,"Opening Balance")
D20: Gifts & Donations | E20: =SUMIFS($J$29:$J$528,$E$29:$E$528,$D20,$I$29:$I$528,"Expense") | F20: =SUMIFS($J$29:$J$528,$E$29:$E$528,$D20,$I$29:$I$528,"Income") | G20: =SUMIFS($J$29:$J$528,$E$29:$E$528,$D20,$I$29:$I$528,"Opening Balance")
D21: Taxes | E21: =SUMIFS($J$29:$J$528,$E$29:$E$528,$D21,$I$29:$I$528,"Expense") | F21: =SUMIFS($J$29:$J$528,$E$29:$E$528,$D21,$I$29:$I$528,"Income") | G21: =SUMIFS($J$29:$J$528,$E$29:$E$528,$D21,$I$29:$I$528,"Opening Balance")
D22: Shipping | E22: =SUMIFS($J$29:$J$528,$E$29:$E$528,$D22,$I$29:$I$528,"Expense") | F22: =SUMIFS($J$29:$J$528,$E$29:$E$528,$D22,$I$29:$I$528,"Income") | G22: =SUMIFS($J$29:$J$528,$E$29:$E$528,$D22,$I$29:$I$528,"Opening Balance")
... D26: Essentials | E26: =SUMIFS($J$29:$J$528,$E$29:$E$528,$D26,$I$29:$I$528,"Expense") | F26: =SUMIFS($J$29:$J$528,$E$29:$E$528,$D26,$I$29:$I$528,"Income") | G26: =SUMIFS($J$29:$J$528,$E$29:$E$528,$D26,$I$29:$I$528,"Opening Balance")
A27: Transactions
A28: Date | B28: Week | C28: Description | D28: Merchant | E28: Category | F28: Subcategory | G28: Account | H28: Payment Method | I28: Type | J28: Amount | K28: Notes
B29: =IF(A29="","",INT((DAY(A29)-1)/7)+1)
B30: =IF(A30="","",INT((DAY(A30)-1)/7)+1)
B31: =IF(A31="","",INT((DAY(A31)-1)/7)+1)
B32: =IF(A32="","",INT((DAY(A32)-1)/7)+1)
B33: =IF(A33="","",INT((DAY(A33)-1)/7)+1)
B34: =IF(A34="","",INT((DAY(A34)-1)/7)+1)
B35: =IF(A35="","",INT((DAY(A35)-1)/7)+1)
B36: =IF(A36="","",INT((DAY(A36)-1)/7)+1)
B37: =IF(A37="","",INT((DAY(A37)-1)/7)+1)
B38: =IF(A38="","",INT((DAY(A38)-1)/7)+1)
B39: =IF(A39="","",INT((DAY(A39)-1)/7)+1)
B40: =IF(A40="","",INT((DAY(A40)-1)/7)+1)
... B528: =IF(A528="","",INT((DAY(A528)-1)/7)+1)

Sheet Mar 2026
A1: March 2026 Ledger
A2: Use positive amounts. Choose Type to classify each transaction.
A4: Month Summary | D4: Category Summary | H4: Weekly Summary
A5: Total Income | B5: =SUMIFS($J$29:$J$528,$I$29:$I$528,"Income") | D5: Category | E5: Expenses | F5: Income | G5: Existing Savings | H5: Week | I5: Expenses | J5: Income | K5: Net
A6: Total Expenses | B6: =SUMIFS($J$29:$J$528,$I$29:$I$528,"Expense") | D6: Housing | E6: =SUMIFS($J$29:$J$528,$E$29:$E$528,$D6,$I$29:$I$528,"Expense") | F6: =SUMIFS($J$29:$J$528,$E$29:$E$528,$D6,$I$29:$I$528,"Income") | G6: =SUMIFS($J$29:$J$528,$E$29:$E$528,$D6,$I$29:$I$528,"Opening Balance") | H6: Week 1 | I6: =SUMIFS($J$29:$J$528,$B$29:$B$528,1,$I$29:$I$528,"Expense",$F$29:$F$528,"<>Rent") | J6: =SUMIFS($J$29:$J$528,$B$29:$B$528,1,$I$29:$I$528,"Income") | K6: =J6-I6
A7: Existing Savings | B7: =SUMIFS($J$29:$J$528,$I$29:$I$528,"Opening Balance") | D7: Utilities | E7: =SUMIFS($J$29:$J$528,$E$29:$E$528,$D7,$I$29:$I$528,"Expense") | F7: =SUMIFS($J$29:$J$528,$E$29:$E$528,$D7,$I$29:$I$528,"Income") | G7: =SUMIFS($J$29:$J$528,$E$29:$E$528,$D7,$I$29:$I$528,"Opening Balance") | H7: Week 2 | I7: =SUMIFS($J$29:$J$528,$B$29:$B$528,2,$I$29:$I$528,"Expense",$F$29:$F$528,"<>Rent") | J7: =SUMIFS($J$29:$J$528,$B$29:$B$528,2,$I$29:$I$528,"Income") | K7: =J7-I7
A8: Transfers | B8: =SUMIFS($J$29:$J$528,$I$29:$I$528,"Transfer") | D8: Groceries | E8: =SUMIFS($J$29:$J$528,$E$29:$E$528,$D8,$I$29:$I$528,"Expense") | F8: =SUMIFS($J$29:$J$528,$E$29:$E$528,$D8,$I$29:$I$528,"Income") | G8: =SUMIFS($J$29:$J$528,$E$29:$E$528,$D8,$I$29:$I$528,"Opening Balance") | H8: Week 3 | I8: =SUMIFS($J$29:$J$528,$B$29:$B$528,3,$I$29:$I$528,"Expense",$F$29:$F$528,"<>Rent") | J8: =SUMIFS($J$29:$J$528,$B$29:$B$528,3,$I$29:$I$528,"Income") | K8: =J8-I8
A9: Net Cash Flow | B9: =B5-B6 | D9: Dining | E9: =SUMIFS($J$29:$J$528,$E$29:$E$528,$D9,$I$29:$I$528,"Expense") | F9: =SUMIFS($J$29:$J$528,$E$29:$E$528,$D9,$I$29:$I$528,"Income") | G9: =SUMIFS($J$29:$J$528,$E$29:$E$528,$D9,$I$29:$I$528,"Opening Balance") | H9: Week 4 | I9: =SUMIFS($J$29:$J$528,$B$29:$B$528,4,$I$29:$I$528,"Expense",$F$29:$F$528,"<>Rent") | J9: =SUMIFS($J$29:$J$528,$B$29:$B$528,4,$I$29:$I$528,"Income") | K9: =J9-I9
D10: Transportation | E10: =SUMIFS($J$29:$J$528,$E$29:$E$528,$D10,$I$29:$I$528,"Expense") | F10: =SUMIFS($J$29:$J$528,$E$29:$E$528,$D10,$I$29:$I$528,"Income") | G10: =SUMIFS($J$29:$J$528,$E$29:$E$528,$D10,$I$29:$I$528,"Opening Balance") | H10: Week 5 | I10: =SUMIFS($J$29:$J$528,$B$29:$B$528,5,$I$29:$I$528,"Expense",$F$29:$F$528,"<>Rent") | J10: =SUMIFS($J$29:$J$528,$B$29:$B$528,5,$I$29:$I$528,"Income") | K10: =J10-I10
D11: Health & Medical | E11: =SUMIFS($J$29:$J$528,$E$29:$E$528,$D11,$I$29:$I$528,"Expense") | F11: =SUMIFS($J$29:$J$528,$E$29:$E$528,$D11,$I$29:$I$528,"Income") | G11: =SUMIFS($J$29:$J$528,$E$29:$E$528,$D11,$I$29:$I$528,"Opening Balance")
D12: Insurance | E12: =SUMIFS($J$29:$J$528,$E$29:$E$528,$D12,$I$29:$I$528,"Expense") | F12: =SUMIFS($J$29:$J$528,$E$29:$E$528,$D12,$I$29:$I$528,"Income") | G12: =SUMIFS($J$29:$J$528,$E$29:$E$528,$D12,$I$29:$I$528,"Opening Balance")
D13: Debt Payments | E13: =SUMIFS($J$29:$J$528,$E$29:$E$528,$D13,$I$29:$I$528,"Expense") | F13: =SUMIFS($J$29:$J$528,$E$29:$E$528,$D13,$I$29:$I$528,"Income") | G13: =SUMIFS($J$29:$J$528,$E$29:$E$528,$D13,$I$29:$I$528,"Opening Balance")
D14: Savings & Investments | E14: =SUMIFS($J$29:$J$528,$E$29:$E$528,$D14,$I$29:$I$528,"Expense") | F14: =SUMIFS($J$29:$J$528,$E$29:$E$528,$D14,$I$29:$I$528,"Income") | G14: =SUMIFS($J$29:$J$528,$E$29:$E$528,$D14,$I$29:$I$528,"Opening Balance")
D15: Personal Care | E15: =SUMIFS($J$29:$J$528,$E$29:$E$528,$D15,$I$29:$I$528,"Expense") | F15: =SUMIFS($J$29:$J$528,$E$29:$E$528,$D15,$I$29:$I$528,"Income") | G15: =SUMIFS($J$29:$J$528,$E$29:$E$528,$D15,$I$29:$I$528,"Opening Balance")
D16: Shopping | E16: =SUMIFS($J$29:$J$528,$E$29:$E$528,$D16,$I$29:$I$528,"Expense") | F16: =SUMIFS($J$29:$J$528,$E$29:$E$528,$D16,$I$29:$I$528,"Income") | G16: =SUMIFS($J$29:$J$528,$E$29:$E$528,$D16,$I$29:$I$528,"Opening Balance")
D17: Entertainment | E17: =SUMIFS($J$29:$J$528,$E$29:$E$528,$D17,$I$29:$I$528,"Expense") | F17: =SUMIFS($J$29:$J$528,$E$29:$E$528,$D17,$I$29:$I$528,"Income") | G17: =SUMIFS($J$29:$J$528,$E$29:$E$528,$D17,$I$29:$I$528,"Opening Balance")
D18: Travel | E18: =SUMIFS($J$29:$J$528,$E$29:$E$528,$D18,$I$29:$I$528,"Expense") | F18: =SUMIFS($J$29:$J$528,$E$29:$E$528,$D18,$I$29:$I$528,"Income") | G18: =SUMIFS($J$29:$J$528,$E$29:$E$528,$D18,$I$29:$I$528,"Opening Balance")
D19: Education | E19: =SUMIFS($J$29:$J$528,$E$29:$E$528,$D19,$I$29:$I$528,"Expense") | F19: =SUMIFS($J$29:$J$528,$E$29:$E$528,$D19,$I$29:$I$528,"Income") | G19: =SUMIFS($J$29:$J$528,$E$29:$E$528,$D19,$I$29:$I$528,"Opening Balance")
D20: Gifts & Donations | E20: =SUMIFS($J$29:$J$528,$E$29:$E$528,$D20,$I$29:$I$528,"Expense") | F20: =SUMIFS($J$29:$J$528,$E$29:$E$528,$D20,$I$29:$I$528,"Income") | G20: =SUMIFS($J$29:$J$528,$E$29:$E$528,$D20,$I$29:$I$528,"Opening Balance")
D21: Taxes | E21: =SUMIFS($J$29:$J$528,$E$29:$E$528,$D21,$I$29:$I$528,"Expense") | F21: =SUMIFS($J$29:$J$528,$E$29:$E$528,$D21,$I$29:$I$528,"Income") | G21: =SUMIFS($J$29:$J$528,$E$29:$E$528,$D21,$I$29:$I$528,"Opening Balance")
D22: Shipping | E22: =SUMIFS($J$29:$J$528,$E$29:$E$528,$D22,$I$29:$I$528,"Expense") | F22: =SUMIFS($J$29:$J$528,$E$29:$E$528,$D22,$I$29:$I$528,"Income") | G22: =SUMIFS($J$29:$J$528,$E$29:$E$528,$D22,$I$29:$I$528,"Opening Balance")
... D26: Essentials | E26: =SUMIFS($J$29:$J$528,$E$29:$E$528,$D26,$I$29:$I$528,"Expense") | F26: =SUMIFS($J$29:$J$528,$E$29:$E$528,$D26,$I$29:$I$528,"Income") | G26: =SUMIFS($J$29:$J$528,$E$29:$E$528,$D26,$I$29:$I$528,"Opening Balance")
A27: Transactions
A28: Date | B28: Week | C28: Description | D28: Merchant | E28: Category | F28: Subcategory | G28: Account | H28: Payment Method | I28: Type | J28: Amount | K28: Notes
B29: =IF(A29="","",INT((DAY(A29)-1)/7)+1)
B30: =IF(A30="","",INT((DAY(A30)-1)/7)+1)
B31: =IF(A31="","",INT((DAY(A31)-1)/7)+1)
B32: =IF(A32="","",INT((DAY(A32)-1)/7)+1)
B33: =IF(A33="","",INT((DAY(A33)-1)/7)+1)
B34: =IF(A34="","",INT((DAY(A34)-1)/7)+1)
B35: =IF(A35="","",INT((DAY(A35)-1)/7)+1)
B36: =IF(A36="","",INT((DAY(A36)-1)/7)+1)
B37: =IF(A37="","",INT((DAY(A37)-1)/7)+1)
B38: =IF(A38="","",INT((DAY(A38)-1)/7)+1)
B39: =IF(A39="","",INT((DAY(A39)-1)/7)+1)
B40: =IF(A40="","",INT((DAY(A40)-1)/7)+1)
... B528: =IF(A528="","",INT((DAY(A528)-1)/7)+1)

Sheet Apr 2026
A1: April 2026 Ledger
A2: Use positive amounts. Choose Type to classify each transaction.
A4: Month Summary | D4: Category Summary | H4: Weekly Summary
A5: Total Income | B5: =SUMIFS($J$29:$J$528,$I$29:$I$528,"Income") | D5: Category | E5: Expenses | F5: Income | G5: Existing Savings | H5: Week | I5: Expenses | J5: Income | K5: Net
A6: Total Expenses | B6: =SUMIFS($J$29:$J$528,$I$29:$I$528,"Expense") | D6: Housing | E6: =SUMIFS($J$29:$J$528,$E$29:$E$528,$D6,$I$29:$I$528,"Expense") | F6: =SUMIFS($J$29:$J$528,$E$29:$E$528,$D6,$I$29:$I$528,"Income") | G6: =SUMIFS($J$29:$J$528,$E$29:$E$528,$D6,$I$29:$I$528,"Opening Balance") | H6: Week 1 | I6: =SUMIFS($J$29:$J$528,$B$29:$B$528,1,$I$29:$I$528,"Expense",$F$29:$F$528,"<>Rent") | J6: =SUMIFS($J$29:$J$528,$B$29:$B$528,1,$I$29:$I$528,"Income") | K6: =J6-I6
A7: Existing Savings | B7: =SUMIFS($J$29:$J$528,$I$29:$I$528,"Opening Balance") | D7: Utilities | E7: =SUMIFS($J$29:$J$528,$E$29:$E$528,$D7,$I$29:$I$528,"Expense") | F7: =SUMIFS($J$29:$J$528,$E$29:$E$528,$D7,$I$29:$I$528,"Income") | G7: =SUMIFS($J$29:$J$528,$E$29:$E$528,$D7,$I$29:$I$528,"Opening Balance") | H7: Week 2 | I7: =SUMIFS($J$29:$J$528,$B$29:$B$528,2,$I$29:$I$528,"Expense",$F$29:$F$528,"<>Rent") | J7: =SUMIFS($J$29:$J$528,$B$29:$B$528,2,$I$29:$I$528,"Income") | K7: =J7-I7
A8: Transfers | B8: =SUMIFS($J$29:$J$528,$I$29:$I$528,"Transfer") | D8: Groceries | E8: =SUMIFS($J$29:$J$528,$E$29:$E$528,$D8,$I$29:$I$528,"Expense") | F8: =SUMIFS($J$29:$J$528,$E$29:$E$528,$D8,$I$29:$I$528,"Income") | G8: =SUMIFS($J$29:$J$528,$E$29:$E$528,$D8,$I$29:$I$528,"Opening Balance") | H8: Week 3 | I8: =SUMIFS($J$29:$J$528,$B$29:$B$528,3,$I$29:$I$528,"Expense",$F$29:$F$528,"<>Rent") | J8: =SUMIFS($J$29:$J$528,$B$29:$B$528,3,$I$29:$I$528,"Income") | K8: =J8-I8
A9: Net Cash Flow | B9: =B5-B6 | D9: Dining | E9: =SUMIFS($J$29:$J$528,$E$29:$E$528,$D9,$I$29:$I$528,"Expense") | F9: =SUMIFS($J$29:$J$528,$E$29:$E$528,$D9,$I$29:$I$528,"Income") | G9: =SUMIFS($J$29:$J$528,$E$29:$E$528,$D9,$I$29:$I$528,"Opening Balance") | H9: Week 4 | I9: =SUMIFS($J$29:$J$528,$B$29:$B$528,4,$I$29:$I$528,"Expense",$F$29:$F$528,"<>Rent") | J9: =SUMIFS($J$29:$J$528,$B$29:$B$528,4,$I$29:$I$528,"Income") | K9: =J9-I9
D10: Transportation | E10: =SUMIFS($J$29:$J$528,$E$29:$E$528,$D10,$I$29:$I$528,"Expense") | F10: =SUMIFS($J$29:$J$528,$E$29:$E$528,$D10,$I$29:$I$528,"Income") | G10: =SUMIFS($J$29:$J$528,$E$29:$E$528,$D10,$I$29:$I$528,"Opening Balance") | H10: Week 5 | I10: =SUMIFS($J$29:$J$528,$B$29:$B$528,5,$I$29:$I$528,"Expense",$F$29:$F$528,"<>Rent") | J10: =SUMIFS($J$29:$J$528,$B$29:$B$528,5,$I$29:$I$528,"Income") | K10: =J10-I10
D11: Health & Medical | E11: =SUMIFS($J$29:$J$528,$E$29:$E$528,$D11,$I$29:$I$528,"Expense") | F11: =SUMIFS($J$29:$J$528,$E$29:$E$528,$D11,$I$29:$I$528,"Income") | G11: =SUMIFS($J$29:$J$528,$E$29:$E$528,$D11,$I$29:$I$528,"Opening Balance")
D12: Insurance | E12: =SUMIFS($J$29:$J$528,$E$29:$E$528,$D12,$I$29:$I$528,"Expense") | F12: =SUMIFS($J$29:$J$528,$E$29:$E$528,$D12,$I$29:$I$528,"Income") | G12: =SUMIFS($J$29:$J$528,$E$29:$E$528,$D12,$I$29:$I$528,"Opening Balance")
D13: Debt Payments | E13: =SUMIFS($J$29:$J$528,$E$29:$E$528,$D13,$I$29:$I$528,"Expense") | F13: =SUMIFS($J$29:$J$528,$E$29:$E$528,$D13,$I$29:$I$528,"Income") | G13: =SUMIFS($J$29:$J$528,$E$29:$E$528,$D13,$I$29:$I$528,"Opening Balance")
D14: Savings & Investments | E14: =SUMIFS($J$29:$J$528,$E$29:$E$528,$D14,$I$29:$I$528,"Expense") | F14: =SUMIFS($J$29:$J$528,$E$29:$E$528,$D14,$I$29:$I$528,"Income") | G14: =SUMIFS($J$29:$J$528,$E$29:$E$528,$D14,$I$29:$I$528,"Opening Balance")
D15: Personal Care | E15: =SUMIFS($J$29:$J$528,$E$29:$E$528,$D15,$I$29:$I$528,"Expense") | F15: =SUMIFS($J$29:$J$528,$E$29:$E$528,$D15,$I$29:$I$528,"Income") | G15: =SUMIFS($J$29:$J$528,$E$29:$E$528,$D15,$I$29:$I$528,"Opening Balance")
D16: Shopping | E16: =SUMIFS($J$29:$J$528,$E$29:$E$528,$D16,$I$29:$I$528,"Expense") | F16: =SUMIFS($J$29:$J$528,$E$29:$E$528,$D16,$I$29:$I$528,"Income") | G16: =SUMIFS($J$29:$J$528,$E$29:$E$528,$D16,$I$29:$I$528,"Opening Balance")
D17: Entertainment | E17: =SUMIFS($J$29:$J$528,$E$29:$E$528,$D17,$I$29:$I$528,"Expense") | F17: =SUMIFS($J$29:$J$528,$E$29:$E$528,$D17,$I$29:$I$528,"Income") | G17: =SUMIFS($J$29:$J$528,$E$29:$E$528,$D17,$I$29:$I$528,"Opening Balance")
D18: Travel | E18: =SUMIFS($J$29:$J$528,$E$29:$E$528,$D18,$I$29:$I$528,"Expense") | F18: =SUMIFS($J$29:$J$528,$E$29:$E$528,$D18,$I$29:$I$528,"Income") | G18: =SUMIFS($J$29:$J$528,$E$29:$E$528,$D18,$I$29:$I$528,"Opening Balance")
D19: Education | E19: =SUMIFS($J$29:$J$528,$E$29:$E$528,$D19,$I$29:$I$528,"Expense") | F19: =SUMIFS($J$29:$J$528,$E$29:$E$528,$D19,$I$29:$I$528,"Income") | G19: =SUMIFS($J$29:$J$528,$E$29:$E$528,$D19,$I$29:$I$528,"Opening Balance")
D20: Gifts & Donations | E20: =SUMIFS($J$29:$J$528,$E$29:$E$528,$D20,$I$29:$I$528,"Expense") | F20: =SUMIFS($J$29:$J$528,$E$29:$E$528,$D20,$I$29:$I$528,"Income") | G20: =SUMIFS($J$29:$J$528,$E$29:$E$528,$D20,$I$29:$I$528,"Opening Balance")
D21: Taxes | E21: =SUMIFS($J$29:$J$528,$E$29:$E$528,$D21,$I$29:$I$528,"Expense") | F21: =SUMIFS($J$29:$J$528,$E$29:$E$528,$D21,$I$29:$I$528,"Income") | G21: =SUMIFS($J$29:$J$528,$E$29:$E$528,$D21,$I$29:$I$528,"Opening Balance")
D22: Shipping | E22: =SUMIFS($J$29:$J$528,$E$29:$E$528,$D22,$I$29:$I$528,"Expense") | F22: =SUMIFS($J$29:$J$528,$E$29:$E$528,$D22,$I$29:$I$528,"Income") | G22: =SUMIFS($J$29:$J$528,$E$29:$E$528,$D22,$I$29:$I$528,"Opening Balance")
... D26: Essentials | E26: =SUMIFS($J$29:$J$528,$E$29:$E$528,$D26,$I$29:$I$528,"Expense") | F26: =SUMIFS($J$29:$J$528,$E$29:$E$528,$D26,$I$29:$I$528,"Income") | G26: =SUMIFS($J$29:$J$528,$E$29:$E$528,$D26,$I$29:$I$528,"Opening Balance")
A27: Transactions
A28: Date | B28: Week | C28: Description | D28: Merchant | E28: Category | F28: Subcategory | G28: Account | H28: Payment Method | I28: Type | J28: Amount | K28: Notes
B29: =IF(A29="","",INT((DAY(A29)-1)/7)+1)
B30: =IF(A30="","",INT((DAY(A30)-1)/7)+1)
B31: =IF(A31="","",INT((DAY(A31)-1)/7)+1)
B32: =IF(A32="","",INT((DAY(A32)-1)/7)+1)
B33: =IF(A33="","",INT((DAY(A33)-1)/7)+1)
B34: =IF(A34="","",INT((DAY(A34)-1)/7)+1)
B35: =IF(A35="","",INT((DAY(A35)-1)/7)+1)
B36: =IF(A36="","",INT((DAY(A36)-1)/7)+1)
B37: =IF(A37="","",INT((DAY(A37)-1)/7)+1)
B38: =IF(A38="","",INT((DAY(A38)-1)/7)+1)
B39: =IF(A39="","",INT((DAY(A39)-1)/7)+1)
B40: =IF(A40="","",INT((DAY(A40)-1)/7)+1)
... B528: =IF(A528="","",INT((DAY(A528)-1)/7)+1)

Sheet May 2026
A1: May 2026 Ledger
A2: Use positive amounts. Choose Type to classify each transaction.
A4: Month Summary | D4: Category Summary | H4: Weekly Summary
A5: Total Income | B5: =SUMIFS($J$29:$J$528,$I$29:$I$528,"Income") | D5: Category | E5: Expenses | F5: Income | G5: Existing Savings | H5: Week | I5: Expenses | J5: Income | K5: Net
A6: Total Expenses | B6: =SUMIFS($J$29:$J$528,$I$29:$I$528,"Expense") | D6: Housing | E6: =SUMIFS($J$29:$J$528,$E$29:$E$528,$D6,$I$29:$I$528,"Expense") | F6: =SUMIFS($J$29:$J$528,$E$29:$E$528,$D6,$I$29:$I$528,"Income") | G6: =SUMIFS($J$29:$J$528,$E$29:$E$528,$D6,$I$29:$I$528,"Opening Balance") | H6: Week 1 | I6: =SUMIFS($J$29:$J$528,$B$29:$B$528,1,$I$29:$I$528,"Expense",$F$29:$F$528,"<>Rent") | J6: =SUMIFS($J$29:$J$528,$B$29:$B$528,1,$I$29:$I$528,"Income") | K6: =J6-I6
A7: Existing Savings | B7: =SUMIFS($J$29:$J$528,$I$29:$I$528,"Opening Balance") | D7: Utilities | E7: =SUMIFS($J$29:$J$528,$E$29:$E$528,$D7,$I$29:$I$528,"Expense") | F7: =SUMIFS($J$29:$J$528,$E$29:$E$528,$D7,$I$29:$I$528,"Income") | G7: =SUMIFS($J$29:$J$528,$E$29:$E$528,$D7,$I$29:$I$528,"Opening Balance") | H7: Week 2 | I7: =SUMIFS($J$29:$J$528,$B$29:$B$528,2,$I$29:$I$528,"Expense",$F$29:$F$528,"<>Rent") | J7: =SUMIFS($J$29:$J$528,$B$29:$B$528,2,$I$29:$I$528,"Income") | K7: =J7-I7
A8: Transfers | B8: =SUMIFS($J$29:$J$528,$I$29:$I$528,"Transfer") | D8: Groceries | E8: =SUMIFS($J$29:$J$528,$E$29:$E$528,$D8,$I$29:$I$528,"Expense") | F8: =SUMIFS($J$29:$J$528,$E$29:$E$528,$D8,$I$29:$I$528,"Income") | G8: =SUMIFS($J$29:$J$528,$E$29:$E$528,$D8,$I$29:$I$528,"Opening Balance") | H8: Week 3 | I8: =SUMIFS($J$29:$J$528,$B$29:$B$528,3,$I$29:$I$528,"Expense",$F$29:$F$528,"<>Rent") | J8: =SUMIFS($J$29:$J$528,$B$29:$B$528,3,$I$29:$I$528,"Income") | K8: =J8-I8
A9: Net Cash Flow | B9: =B5-B6 | D9: Dining | E9: =SUMIFS($J$29:$J$528,$E$29:$E$528,$D9,$I$29:$I$528,"Expense") | F9: =SUMIFS($J$29:$J$528,$E$29:$E$528,$D9,$I$29:$I$528,"Income") | G9: =SUMIFS($J$29:$J$528,$E$29:$E$528,$D9,$I$29:$I$528,"Opening Balance") | H9: Week 4 | I9: =SUMIFS($J$29:$J$528,$B$29:$B$528,4,$I$29:$I$528,"Expense",$F$29:$F$528,"<>Rent") | J9: =SUMIFS($J$29:$J$528,$B$29:$B$528,4,$I$29:$I$528,"Income") | K9: =J9-I9
D10: Transportation | E10: =SUMIFS($J$29:$J$528,$E$29:$E$528,$D10,$I$29:$I$528,"Expense") | F10: =SUMIFS($J$29:$J$528,$E$29:$E$528,$D10,$I$29:$I$528,"Income") | G10: =SUMIFS($J$29:$J$528,$E$29:$E$528,$D10,$I$29:$I$528,"Opening Balance") | H10: Week 5 | I10: =SUMIFS($J$29:$J$528,$B$29:$B$528,5,$I$29:$I$528,"Expense",$F$29:$F$528,"<>Rent") | J10: =SUMIFS($J$29:$J$528,$B$29:$B$528,5,$I$29:$I$528,"Income") | K10: =J10-I10
D11: Health & Medical | E11: =SUMIFS($J$29:$J$528,$E$29:$E$528,$D11,$I$29:$I$528,"Expense") | F11: =SUMIFS($J$29:$J$528,$E$29:$E$528,$D11,$I$29:$I$528,"Income") | G11: =SUMIFS($J$29:$J$528,$E$29:$E$528,$D11,$I$29:$I$528,"Opening Balance")
D12: Insurance | E12: =SUMIFS($J$29:$J$528,$E$29:$E$528,$D12,$I$29:$I$528,"Expense") | F12: =SUMIFS($J$29:$J$528,$E$29:$E$528,$D12,$I$29:$I$528,"Income") | G12: =SUMIFS($J$29:$J$528,$E$29:$E$528,$D12,$I$29:$I$528,"Opening Balance")
D13: Debt Payments | E13: =SUMIFS($J$29:$J$528,$E$29:$E$528,$D13,$I$29:$I$528,"Expense") | F13: =SUMIFS($J$29:$J$528,$E$29:$E$528,$D13,$I$29:$I$528,"Income") | G13: =SUMIFS($J$29:$J$528,$E$29:$E$528,$D13,$I$29:$I$528,"Opening Balance")
D14: Savings & Investments | E14: =SUMIFS($J$29:$J$528,$E$29:$E$528,$D14,$I$29:$I$528,"Expense") | F14: =SUMIFS($J$29:$J$528,$E$29:$E$528,$D14,$I$29:$I$528,"Income") | G14: =SUMIFS($J$29:$J$528,$E$29:$E$528,$D14,$I$29:$I$528,"Opening Balance")
D15: Personal Care | E15: =SUMIFS($J$29:$J$528,$E$29:$E$528,$D15,$I$29:$I$528,"Expense") | F15: =SUMIFS($J$29:$J$528,$E$29:$E$528,$D15,$I$29:$I$528,"Income") | G15: =SUMIFS($J$29:$J$528,$E$29:$E$528,$D15,$I$29:$I$528,"Opening Balance")
D16: Shopping | E16: =SUMIFS($J$29:$J$528,$E$29:$E$528,$D16,$I$29:$I$528,"Expense") | F16: =SUMIFS($J$29:$J$528,$E$29:$E$528,$D16,$I$29:$I$528,"Income") | G16: =SUMIFS($J$29:$J$528,$E$29:$E$528,$D16,$I$29:$I$528,"Opening Balance")
D17: Entertainment | E17: =SUMIFS($J$29:$J$528,$E$29:$E$528,$D17,$I$29:$I$528,"Expense") | F17: =SUMIFS($J$29:$J$528,$E$29:$E$528,$D17,$I$29:$I$528,"Income") | G17: =SUMIFS($J$29:$J$528,$E$29:$E$528,$D17,$I$29:$I$528,"Opening Balance")
D18: Travel | E18: =SUMIFS($J$29:$J$528,$E$29:$E$528,$D18,$I$29:$I$528,"Expense") | F18: =SUMIFS($J$29:$J$528,$E$29:$E$528,$D18,$I$29:$I$528,"Income") | G18: =SUMIFS($J$29:$J$528,$E$29:$E$528,$D18,$I$29:$I$528,"Opening Balance")
D19: Education | E19: =SUMIFS($J$29:$J$528,$E$29:$E$528,$D19,$I$29:$I$528,"Expense") | F19: =SUMIFS($J$29:$J$528,$E$29:$E$528,$D19,$I$29:$I$528,"Income") | G19: =SUMIFS($J$29:$J$528,$E$29:$E$528,$D19,$I$29:$I$528,"Opening Balance")
D20: Gifts & Donations | E20: =SUMIFS($J$29:$J$528,$E$29:$E$528,$D20,$I$29:$I$528,"Expense") | F20: =SUMIFS($J$29:$J$528,$E$29:$E$528,$D20,$I$29:$I$528,"Income") | G20: =SUMIFS($J$29:$J$528,$E$29:$E$528,$D20,$I$29:$I$528,"Opening Balance")
D21: Taxes | E21: =SUMIFS($J$29:$J$528,$E$29:$E$528,$D21,$I$29:$I$528,"Expense") | F21: =SUMIFS($J$29:$J$528,$E$29:$E$528,$D21,$I$29:$I$528,"Income") | G21: =SUMIFS($J$29:$J$528,$E$29:$E$528,$D21,$I$29:$I$528,"Opening Balance")
D22: Shipping | E22: =SUMIFS($J$29:$J$528,$E$29:$E$528,$D22,$I$29:$I$528,"Expense") | F22: =SUMIFS($J$29:$J$528,$E$29:$E$528,$D22,$I$29:$I$528,"Income") | G22: =SUMIFS($J$29:$J$528,$E$29:$E$528,$D22,$I$29:$I$528,"Opening Balance")
... D26: Essentials | E26: =SUMIFS($J$29:$J$528,$E$29:$E$528,$D26,$I$29:$I$528,"Expense") | F26: =SUMIFS($J$29:$J$528,$E$29:$E$528,$D26,$I$29:$I$528,"Income") | G26: =SUMIFS($J$29:$J$528,$E$29:$E$528,$D26,$I$29:$I$528,"Opening Balance")
A27: Transactions
A28: Date | B28: Week | C28: Description | D28: Merchant | E28: Category | F28: Subcategory | G28: Account | H28: Payment Method | I28: Type | J28: Amount | K28: Notes
B29: =IF(A29="","",INT((DAY(A29)-1)/7)+1)
B30: =IF(A30="","",INT((DAY(A30)-1)/7)+1)
B31: =IF(A31="","",INT((DAY(A31)-1)/7)+1)
B32: =IF(A32="","",INT((DAY(A32)-1)/7)+1)
B33: =IF(A33="","",INT((DAY(A33)-1)/7)+1)
B34: =IF(A34="","",INT((DAY(A34)-1)/7)+1)
B35: =IF(A35="","",INT((DAY(A35)-1)/7)+1)
B36: =IF(A36="","",INT((DAY(A36)-1)/7)+1)
B37: =IF(A37="","",INT((DAY(A37)-1)/7)+1)
B38: =IF(A38="","",INT((DAY(A38)-1)/7)+1)
B39: =IF(A39="","",INT((DAY(A39)-1)/7)+1)
B40: =IF(A40="","",INT((DAY(A40)-1)/7)+1)
... B528: =IF(A528="","",INT((DAY(A528)-1)/7)+1)

Sheet Jun 2026
A1: June 2026 Ledger
A2: Use positive amounts. Choose Type to classify each transaction.
A4: Month Summary | D4: Category Summary | H4: Weekly Summary
A5: Total Income | B5: =SUMIFS($J$29:$J$528,$I$29:$I$528,"Income") | D5: Category | E5: Expenses | F5: Income | G5: Existing Savings | H5: Week | I5: Expenses | J5: Income | K5: Net
A6: Total Expenses | B6: =SUMIFS($J$29:$J$528,$I$29:$I$528,"Expense") | D6: Housing | E6: =SUMIFS($J$29:$J$528,$E$29:$E$528,$D6,$I$29:$I$528,"Expense") | F6: =SUMIFS($J$29:$J$528,$E$29:$E$528,$D6,$I$29:$I$528,"Income") | G6: =SUMIFS($J$29:$J$528,$E$29:$E$528,$D6,$I$29:$I$528,"Opening Balance") | H6: Week 1 | I6: =SUMIFS($J$29:$J$528,$B$29:$B$528,1,$I$29:$I$528,"Expense",$F$29:$F$528,"<>Rent") | J6: =SUMIFS($J$29:$J$528,$B$29:$B$528,1,$I$29:$I$528,"Income") | K6: =J6-I6
A7: Existing Savings | B7: =SUMIFS($J$29:$J$528,$I$29:$I$528,"Opening Balance") | D7: Utilities | E7: =SUMIFS($J$29:$J$528,$E$29:$E$528,$D7,$I$29:$I$528,"Expense") | F7: =SUMIFS($J$29:$J$528,$E$29:$E$528,$D7,$I$29:$I$528,"Income") | G7: =SUMIFS($J$29:$J$528,$E$29:$E$528,$D7,$I$29:$I$528,"Opening Balance") | H7: Week 2 | I7: =SUMIFS($J$29:$J$528,$B$29:$B$528,2,$I$29:$I$528,"Expense",$F$29:$F$528,"<>Rent") | J7: =SUMIFS($J$29:$J$528,$B$29:$B$528,2,$I$29:$I$528,"Income") | K7: =J7-I7
A8: Transfers | B8: =SUMIFS($J$29:$J$528,$I$29:$I$528,"Transfer") | D8: Groceries | E8: =SUMIFS($J$29:$J$528,$E$29:$E$528,$D8,$I$29:$I$528,"Expense") | F8: =SUMIFS($J$29:$J$528,$E$29:$E$528,$D8,$I$29:$I$528,"Income") | G8: =SUMIFS($J$29:$J$528,$E$29:$E$528,$D8,$I$29:$I$528,"Opening Balance") | H8: Week 3 | I8: =SUMIFS($J$29:$J$528,$B$29:$B$528,3,$I$29:$I$528,"Expense",$F$29:$F$528,"<>Rent") | J8: =SUMIFS($J$29:$J$528,$B$29:$B$528,3,$I$29:$I$528,"Income") | K8: =J8-I8
A9: Net Cash Flow | B9: =B5-B6 | D9: Dining | E9: =SUMIFS($J$29:$J$528,$E$29:$E$528,$D9,$I$29:$I$528,"Expense") | F9: =SUMIFS($J$29:$J$528,$E$29:$E$528,$D9,$I$29:$I$528,"Income") | G9: =SUMIFS($J$29:$J$528,$E$29:$E$528,$D9,$I$29:$I$528,"Opening Balance") | H9: Week 4 | I9: =SUMIFS($J$29:$J$528,$B$29:$B$528,4,$I$29:$I$528,"Expense",$F$29:$F$528,"<>Rent") | J9: =SUMIFS($J$29:$J$528,$B$29:$B$528,4,$I$29:$I$528,"Income") | K9: =J9-I9
D10: Transportation | E10: =SUMIFS($J$29:$J$528,$E$29:$E$528,$D10,$I$29:$I$528,"Expense") | F10: =SUMIFS($J$29:$J$528,$E$29:$E$528,$D10,$I$29:$I$528,"Income") | G10: =SUMIFS($J$29:$J$528,$E$29:$E$528,$D10,$I$29:$I$528,"Opening Balance") | H10: Week 5 | I10: =SUMIFS($J$29:$J$528,$B$29:$B$528,5,$I$29:$I$528,"Expense",$F$29:$F$528,"<>Rent") | J10: =SUMIFS($J$29:$J$528,$B$29:$B$528,5,$I$29:$I$528,"Income") | K10: =J10-I10
D11: Health & Medical | E11: =SUMIFS($J$29:$J$528,$E$29:$E$528,$D11,$I$29:$I$528,"Expense") | F11: =SUMIFS($J$29:$J$528,$E$29:$E$528,$D11,$I$29:$I$528,"Income") | G11: =SUMIFS($J$29:$J$528,$E$29:$E$528,$D11,$I$29:$I$528,"Opening Balance")
D12: Insurance | E12: =SUMIFS($J$29:$J$528,$E$29:$E$528,$D12,$I$29:$I$528,"Expense") | F12: =SUMIFS($J$29:$J$528,$E$29:$E$528,$D12,$I$29:$I$528,"Income") | G12: =SUMIFS($J$29:$J$528,$E$29:$E$528,$D12,$I$29:$I$528,"Opening Balance")
D13: Debt Payments | E13: =SUMIFS($J$29:$J$528,$E$29:$E$528,$D13,$I$29:$I$528,"Expense") | F13: =SUMIFS($J$29:$J$528,$E$29:$E$528,$D13,$I$29:$I$528,"Income") | G13: =SUMIFS($J$29:$J$528,$E$29:$E$528,$D13,$I$29:$I$528,"Opening Balance")
D14: Savings & Investments | E14: =SUMIFS($J$29:$J$528,$E$29:$E$528,$D14,$I$29:$I$528,"Expense") | F14: =SUMIFS($J$29:$J$528,$E$29:$E$528,$D14,$I$29:$I$528,"Income") | G14: =SUMIFS($J$29:$J$528,$E$29:$E$528,$D14,$I$29:$I$528,"Opening Balance")
D15: Personal Care | E15: =SUMIFS($J$29:$J$528,$E$29:$E$528,$D15,$I$29:$I$528,"Expense") | F15: =SUMIFS($J$29:$J$528,$E$29:$E$528,$D15,$I$29:$I$528,"Income") | G15: =SUMIFS($J$29:$J$528,$E$29:$E$528,$D15,$I$29:$I$528,"Opening Balance")
D16: Shopping | E16: =SUMIFS($J$29:$J$528,$E$29:$E$528,$D16,$I$29:$I$528,"Expense") | F16: =SUMIFS($J$29:$J$528,$E$29:$E$528,$D16,$I$29:$I$528,"Income") | G16: =SUMIFS($J$29:$J$528,$E$29:$E$528,$D16,$I$29:$I$528,"Opening Balance")
D17: Entertainment | E17: =SUMIFS($J$29:$J$528,$E$29:$E$528,$D17,$I$29:$I$528,"Expense") | F17: =SUMIFS($J$29:$J$528,$E$29:$E$528,$D17,$I$29:$I$528,"Income") | G17: =SUMIFS($J$29:$J$528,$E$29:$E$528,$D17,$I$29:$I$528,"Opening Balance")
D18: Travel | E18: =SUMIFS($J$29:$J$528,$E$29:$E$528,$D18,$I$29:$I$528,"Expense") | F18: =SUMIFS($J$29:$J$528,$E$29:$E$528,$D18,$I$29:$I$528,"Income") | G18: =SUMIFS($J$29:$J$528,$E$29:$E$528,$D18,$I$29:$I$528,"Opening Balance")
D19: Education | E19: =SUMIFS($J$29:$J$528,$E$29:$E$528,$D19,$I$29:$I$528,"Expense") | F19: =SUMIFS($J$29:$J$528,$E$29:$E$528,$D19,$I$29:$I$528,"Income") | G19: =SUMIFS($J$29:$J$528,$E$29:$E$528,$D19,$I$29:$I$528,"Opening Balance")
D20: Gifts & Donations | E20: =SUMIFS($J$29:$J$528,$E$29:$E$528,$D20,$I$29:$I$528,"Expense") | F20: =SUMIFS($J$29:$J$528,$E$29:$E$528,$D20,$I$29:$I$528,"Income") | G20: =SUMIFS($J$29:$J$528,$E$29:$E$528,$D20,$I$29:$I$528,"Opening Balance")
D21: Taxes | E21: =SUMIFS($J$29:$J$528,$E$29:$E$528,$D21,$I$29:$I$528,"Expense") | F21: =SUMIFS($J$29:$J$528,$E$29:$E$528,$D21,$I$29:$I$528,"Income") | G21: =SUMIFS($J$29:$J$528,$E$29:$E$528,$D21,$I$29:$I$528,"Opening Balance")
D22: Shipping | E22: =SUMIFS($J$29:$J$528,$E$29:$E$528,$D22,$I$29:$I$528,"Expense") | F22: =SUMIFS($J$29:$J$528,$E$29:$E$528,$D22,$I$29:$I$528,"Income") | G22: =SUMIFS($J$29:$J$528,$E$29:$E$528,$D22,$I$29:$I$528,"Opening Balance")
... D26: Essentials | E26: =SUMIFS($J$29:$J$528,$E$29:$E$528,$D26,$I$29:$I$528,"Expense") | F26: =SUMIFS($J$29:$J$528,$E$29:$E$528,$D26,$I$29:$I$528,"Income") | G26: =SUMIFS($J$29:$J$528,$E$29:$E$528,$D26,$I$29:$I$528,"Opening Balance")
A27: Transactions
A28: Date | B28: Week | C28: Description | D28: Merchant | E28: Category | F28: Subcategory | G28: Account | H28: Payment Method | I28: Type | J28: Amount | K28: Notes
B29: =IF(A29="","",INT((DAY(A29)-1)/7)+1)
B30: =IF(A30="","",INT((DAY(A30)-1)/7)+1)
B31: =IF(A31="","",INT((DAY(A31)-1)/7)+1)
B32: =IF(A32="","",INT((DAY(A32)-1)/7)+1)
B33: =IF(A33="","",INT((DAY(A33)-1)/7)+1)
B34: =IF(A34="","",INT((DAY(A34)-1)/7)+1)
B35: =IF(A35="","",INT((DAY(A35)-1)/7)+1)
B36: =IF(A36="","",INT((DAY(A36)-1)/7)+1)
B37: =IF(A37="","",INT((DAY(A37)-1)/7)+1)
B38: =IF(A38="","",INT((DAY(A38)-1)/7)+1)
B39: =IF(A39="","",INT((DAY(A39)-1)/7)+1)
B40: =IF(A40="","",INT((DAY(A40)-1)/7)+1)
... B528: =IF(A528="","",INT((DAY(A528)-1)/7)+1)

Sheet Jul 2026
A1: July 2026 Ledger
A2: Use positive amounts. Choose Type to classify each transaction.
A4: Month Summary | D4: Category Summary | H4: Weekly Summary
A5: Total Income | B5: =SUMIFS($J$29:$J$528,$I$29:$I$528,"Income") | D5: Category | E5: Expenses | F5: Income | G5: Existing Savings | H5: Week | I5: Expenses | J5: Income | K5: Net
A6: Total Expenses | B6: =SUMIFS($J$29:$J$528,$I$29:$I$528,"Expense") | D6: Housing | E6: =SUMIFS($J$29:$J$528,$E$29:$E$528,$D6,$I$29:$I$528,"Expense") | F6: =SUMIFS($J$29:$J$528,$E$29:$E$528,$D6,$I$29:$I$528,"Income") | G6: =SUMIFS($J$29:$J$528,$E$29:$E$528,$D6,$I$29:$I$528,"Opening Balance") | H6: Week 1 | I6: =SUMIFS($J$29:$J$528,$B$29:$B$528,1,$I$29:$I$528,"Expense",$F$29:$F$528,"<>Rent") | J6: =SUMIFS($J$29:$J$528,$B$29:$B$528,1,$I$29:$I$528,"Income") | K6: =J6-I6
A7: Existing Savings | B7: =SUMIFS($J$29:$J$528,$I$29:$I$528,"Opening Balance") | D7: Utilities | E7: =SUMIFS($J$29:$J$528,$E$29:$E$528,$D7,$I$29:$I$528,"Expense") | F7: =SUMIFS($J$29:$J$528,$E$29:$E$528,$D7,$I$29:$I$528,"Income") | G7: =SUMIFS($J$29:$J$528,$E$29:$E$528,$D7,$I$29:$I$528,"Opening Balance") | H7: Week 2 | I7: =SUMIFS($J$29:$J$528,$B$29:$B$528,2,$I$29:$I$528,"Expense",$F$29:$F$528,"<>Rent") | J7: =SUMIFS($J$29:$J$528,$B$29:$B$528,2,$I$29:$I$528,"Income") | K7: =J7-I7
A8: Transfers | B8: =SUMIFS($J$29:$J$528,$I$29:$I$528,"Transfer") | D8: Groceries | E8: =SUMIFS($J$29:$J$528,$E$29:$E$528,$D8,$I$29:$I$528,"Expense") | F8: =SUMIFS($J$29:$J$528,$E$29:$E$528,$D8,$I$29:$I$528,"Income") | G8: =SUMIFS($J$29:$J$528,$E$29:$E$528,$D8,$I$29:$I$528,"Opening Balance") | H8: Week 3 | I8: =SUMIFS($J$29:$J$528,$B$29:$B$528,3,$I$29:$I$528,"Expense",$F$29:$F$528,"<>Rent") | J8: =SUMIFS($J$29:$J$528,$B$29:$B$528,3,$I$29:$I$528,"Income") | K8: =J8-I8
A9: Net Cash Flow | B9: =B5-B6 | D9: Dining | E9: =SUMIFS($J$29:$J$528,$E$29:$E$528,$D9,$I$29:$I$528,"Expense") | F9: =SUMIFS($J$29:$J$528,$E$29:$E$528,$D9,$I$29:$I$528,"Income") | G9: =SUMIFS($J$29:$J$528,$E$29:$E$528,$D9,$I$29:$I$528,"Opening Balance") | H9: Week 4 | I9: =SUMIFS($J$29:$J$528,$B$29:$B$528,4,$I$29:$I$528,"Expense",$F$29:$F$528,"<>Rent") | J9: =SUMIFS($J$29:$J$528,$B$29:$B$528,4,$I$29:$I$528,"Income") | K9: =J9-I9
D10: Transportation | E10: =SUMIFS($J$29:$J$528,$E$29:$E$528,$D10,$I$29:$I$528,"Expense") | F10: =SUMIFS($J$29:$J$528,$E$29:$E$528,$D10,$I$29:$I$528,"Income") | G10: =SUMIFS($J$29:$J$528,$E$29:$E$528,$D10,$I$29:$I$528,"Opening Balance") | H10: Week 5 | I10: =SUMIFS($J$29:$J$528,$B$29:$B$528,5,$I$29:$I$528,"Expense",$F$29:$F$528,"<>Rent") | J10: =SUMIFS($J$29:$J$528,$B$29:$B$528,5,$I$29:$I$528,"Income") | K10: =J10-I10
D11: Health & Medical | E11: =SUMIFS($J$29:$J$528,$E$29:$E$528,$D11,$I$29:$I$528,"Expense") | F11: =SUMIFS($J$29:$J$528,$E$29:$E$528,$D11,$I$29:$I$528,"Income") | G11: =SUMIFS($J$29:$J$528,$E$29:$E$528,$D11,$I$29:$I$528,"Opening Balance")
D12: Insurance | E12: =SUMIFS($J$29:$J$528,$E$29:$E$528,$D12,$I$29:$I$528,"Expense") | F12: =SUMIFS($J$29:$J$528,$E$29:$E$528,$D12,$I$29:$I$528,"Income") | G12: =SUMIFS($J$29:$J$528,$E$29:$E$528,$D12,$I$29:$I$528,"Opening Balance")
D13: Debt Payments | E13: =SUMIFS($J$29:$J$528,$E$29:$E$528,$D13,$I$29:$I$528,"Expense") | F13: =SUMIFS($J$29:$J$528,$E$29:$E$528,$D13,$I$29:$I$528,"Income") | G13: =SUMIFS($J$29:$J$528,$E$29:$E$528,$D13,$I$29:$I$528,"Opening Balance")
D14: Savings & Investments | E14: =SUMIFS($J$29:$J$528,$E$29:$E$528,$D14,$I$29:$I$528,"Expense") | F14: =SUMIFS($J$29:$J$528,$E$29:$E$528,$D14,$I$29:$I$528,"Income") | G14: =SUMIFS($J$29:$J$528,$E$29:$E$528,$D14,$I$29:$I$528,"Opening Balance")
D15: Personal Care | E15: =SUMIFS($J$29:$J$528,$E$29:$E$528,$D15,$I$29:$I$528,"Expense") | F15: =SUMIFS($J$29:$J$528,$E$29:$E$528,$D15,$I$29:$I$528,"Income") | G15: =SUMIFS($J$29:$J$528,$E$29:$E$528,$D15,$I$29:$I$528,"Opening Balance")
D16: Shopping | E16: =SUMIFS($J$29:$J$528,$E$29:$E$528,$D16,$I$29:$I$528,"Expense") | F16: =SUMIFS($J$29:$J$528,$E$29:$E$528,$D16,$I$29:$I$528,"Income") | G16: =SUMIFS($J$29:$J$528,$E$29:$E$528,$D16,$I$29:$I$528,"Opening Balance")
D17: Entertainment | E17: =SUMIFS($J$29:$J$528,$E$29:$E$528,$D17,$I$29:$I$528,"Expense") | F17: =SUMIFS($J$29:$J$528,$E$29:$E$528,$D17,$I$29:$I$528,"Income") | G17: =SUMIFS($J$29:$J$528,$E$29:$E$528,$D17,$I$29:$I$528,"Opening Balance")
D18: Travel | E18: =SUMIFS($J$29:$J$528,$E$29:$E$528,$D18,$I$29:$I$528,"Expense") | F18: =SUMIFS($J$29:$J$528,$E$29:$E$528,$D18,$I$29:$I$528,"Income") | G18: =SUMIFS($J$29:$J$528,$E$29:$E$528,$D18,$I$29:$I$528,"Opening Balance")
D19: Education | E19: =SUMIFS($J$29:$J$528,$E$29:$E$528,$D19,$I$29:$I$528,"Expense") | F19: =SUMIFS($J$29:$J$528,$E$29:$E$528,$D19,$I$29:$I$528,"Income") | G19: =SUMIFS($J$29:$J$528,$E$29:$E$528,$D19,$I$29:$I$528,"Opening Balance")
D20: Gifts & Donations | E20: =SUMIFS($J$29:$J$528,$E$29:$E$528,$D20,$I$29:$I$528,"Expense") | F20: =SUMIFS($J$29:$J$528,$E$29:$E$528,$D20,$I$29:$I$528,"Income") | G20: =SUMIFS($J$29:$J$528,$E$29:$E$528,$D20,$I$29:$I$528,"Opening Balance")
D21: Taxes | E21: =SUMIFS($J$29:$J$528,$E$29:$E$528,$D21,$I$29:$I$528,"Expense") | F21: =SUMIFS($J$29:$J$528,$E$29:$E$528,$D21,$I$29:$I$528,"Income") | G21: =SUMIFS($J$29:$J$528,$E$29:$E$528,$D21,$I$29:$I$528,"Opening Balance")
D22: Shipping | E22: =SUMIFS($J$29:$J$528,$E$29:$E$528,$D22,$I$29:$I$528,"Expense") | F22: =SUMIFS($J$29:$J$528,$E$29:$E$528,$D22,$I$29:$I$528,"Income") | G22: =SUMIFS($J$29:$J$528,$E$29:$E$528,$D22,$I$29:$I$528,"Opening Balance")
... D26: Essentials | E26: =SUMIFS($J$29:$J$528,$E$29:$E$528,$D26,$I$29:$I$528,"Expense") | F26: =SUMIFS($J$29:$J$528,$E$29:$E$528,$D26,$I$29:$I$528,"Income") | G26: =SUMIFS($J$29:$J$528,$E$29:$E$528,$D26,$I$29:$I$528,"Opening Balance")
A27: Transactions
A28: Date | B28: Week | C28: Description | D28: Merchant | E28: Category | F28: Subcategory | G28: Account | H28: Payment Method | I28: Type | J28: Amount | K28: Notes
B29: =IF(A29="","",INT((DAY(A29)-1)/7)+1)
B30: =IF(A30="","",INT((DAY(A30)-1)/7)+1)
B31: =IF(A31="","",INT((DAY(A31)-1)/7)+1)
B32: =IF(A32="","",INT((DAY(A32)-1)/7)+1)
B33: =IF(A33="","",INT((DAY(A33)-1)/7)+1)
B34: =IF(A34="","",INT((DAY(A34)-1)/7)+1)
B35: =IF(A35="","",INT((DAY(A35)-1)/7)+1)
B36: =IF(A36="","",INT((DAY(A36)-1)/7)+1)
B37: =IF(A37="","",INT((DAY(A37)-1)/7)+1)
B38: =IF(A38="","",INT((DAY(A38)-1)/7)+1)
B39: =IF(A39="","",INT((DAY(A39)-1)/7)+1)
B40: =IF(A40="","",INT((DAY(A40)-1)/7)+1)
... B528: =IF(A528="","",INT((DAY(A528)-1)/7)+1)

Sheet Aug 2026
A1: August 2026 Ledger
A2: Use positive amounts. Choose Type to classify each transaction.
A4: Month Summary | D4: Category Summary | H4: Weekly Summary
A5: Total Income | B5: =SUMIFS($J$29:$J$528,$I$29:$I$528,"Income") -> 4988 | D5: Category | E5: Expenses | F5: Income | G5: Existing Savings | H5: Week | I5: Expenses | J5: Income | K5: Net
A6: Total Expenses | B6: =SUMIFS($J$29:$J$528,$I$29:$I$528,"Expense") -> 2741.56 | D6: Housing | E6: =SUMIFS($J$29:$J$528,$E$29:$E$528,$D6,$I$29:$I$528,"Expense") -> 1100 | F6: =SUMIFS($J$29:$J$528,$E$29:$E$528,$D6,$I$29:$I$528,"Income") -> 0 | G6: =SUMIFS($J$29:$J$528,$E$29:$E$528,$D6,$I$29:$I$528,"Opening Balance") -> 0 | H6: Week 1 | I6: =SUMIFS($J$29:$J$528,$B$29:$B$528,1,$I$29:$I$528,"Expense",$F$29:$F$528,"<>Rent") -> 0 | J6: =SUMIFS($J$29:$J$528,$B$29:$B$528,1,$I$29:$I$528,"Income") -> 0 | K6: =J6-I6 -> 0
A7: Existing Savings | B7: =SUMIFS($J$29:$J$528,$I$29:$I$528,"Opening Balance") -> 7300 | D7: Utilities | E7: =SUMIFS($J$29:$J$528,$E$29:$E$528,$D7,$I$29:$I$528,"Expense") -> 67.72 | F7: =SUMIFS($J$29:$J$528,$E$29:$E$528,$D7,$I$29:$I$528,"Income") -> 0 | G7: =SUMIFS($J$29:$J$528,$E$29:$E$528,$D7,$I$29:$I$528,"Opening Balance") -> 0 | H7: Week 2 | I7: =SUMIFS($J$29:$J$528,$B$29:$B$528,2,$I$29:$I$528,"Expense",$F$29:$F$528,"<>Rent") -> 294.98 | J7: =SUMIFS($J$29:$J$528,$B$29:$B$528,2,$I$29:$I$528,"Income") -> 0 | K7: =J7-I7 -> -294.98
A8: Transfers | B8: =SUMIFS($J$29:$J$528,$I$29:$I$528,"Transfer") -> 1700 | D8: Groceries | E8: =SUMIFS($J$29:$J$528,$E$29:$E$528,$D8,$I$29:$I$528,"Expense") -> 394.07 | F8: =SUMIFS($J$29:$J$528,$E$29:$E$528,$D8,$I$29:$I$528,"Income") -> 0 | G8: =SUMIFS($J$29:$J$528,$E$29:$E$528,$D8,$I$29:$I$528,"Opening Balance") -> 0 | H8: Week 3 | I8: =SUMIFS($J$29:$J$528,$B$29:$B$528,3,$I$29:$I$528,"Expense",$F$29:$F$528,"<>Rent") -> 553.36 | J8: =SUMIFS($J$29:$J$528,$B$29:$B$528,3,$I$29:$I$528,"Income") -> 0 | K8: =J8-I8 -> -553.36
A9: Net Cash Flow | B9: =B5-B6 -> 2246.44 | D9: Dining | E9: =SUMIFS($J$29:$J$528,$E$29:$E$528,$D9,$I$29:$I$528,"Expense") -> 350.01 | F9: =SUMIFS($J$29:$J$528,$E$29:$E$528,$D9,$I$29:$I$528,"Income") -> 0 | G9: =SUMIFS($J$29:$J$528,$E$29:$E$528,$D9,$I$29:$I$528,"Opening Balance") -> 0 | H9: Week 4 | I9: =SUMIFS($J$29:$J$528,$B$29:$B$528,4,$I$29:$I$528,"Expense",$F$29:$F$528,"<>Rent") -> 546.17 | J9: =SUMIFS($J$29:$J$528,$B$29:$B$528,4,$I$29:$I$528,"Income") -> 0 | K9: =J9-I9 -> -546.17
A10: Current Balance | B10: 8242.24 | D10: Transportation | E10: =SUMIFS($J$29:$J$528,$E$29:$E$528,$D10,$I$29:$I$528,"Expense") -> 110.45 | F10: =SUMIFS($J$29:$J$528,$E$29:$E$528,$D10,$I$29:$I$528,"Income") -> 0 | G10: =SUMIFS($J$29:$J$528,$E$29:$E$528,$D10,$I$29:$I$528,"Opening Balance") -> 0 | H10: Week 5 | I10: =SUMIFS($J$29:$J$528,$B$29:$B$528,5,$I$29:$I$528,"Expense",$F$29:$F$528,"<>Rent") -> 247.05 | J10: =SUMIFS($J$29:$J$528,$B$29:$B$528,5,$I$29:$I$528,"Income") -> 4988 | K10: =J10-I10 -> 4740.95
D11: Health & Medical | E11: =SUMIFS($J$29:$J$528,$E$29:$E$528,$D11,$I$29:$I$528,"Expense") -> 0 | F11: =SUMIFS($J$29:$J$528,$E$29:$E$528,$D11,$I$29:$I$528,"Income") -> 0 | G11: =SUMIFS($J$29:$J$528,$E$29:$E$528,$D11,$I$29:$I$528,"Opening Balance") -> 0
D12: Insurance | E12: =SUMIFS($J$29:$J$528,$E$29:$E$528,$D12,$I$29:$I$528,"Expense") -> 0 | F12: =SUMIFS($J$29:$J$528,$E$29:$E$528,$D12,$I$29:$I$528,"Income") -> 0 | G12: =SUMIFS($J$29:$J$528,$E$29:$E$528,$D12,$I$29:$I$528,"Opening Balance") -> 0
D13: Debt Payments | E13: =SUMIFS($J$29:$J$528,$E$29:$E$528,$D13,$I$29:$I$528,"Expense") -> 0 | F13: =SUMIFS($J$29:$J$528,$E$29:$E$528,$D13,$I$29:$I$528,"Income") -> 0 | G13: =SUMIFS($J$29:$J$528,$E$29:$E$528,$D13,$I$29:$I$528,"Opening Balance") -> 0
D14: Savings & Investments | E14: =SUMIFS($J$29:$J$528,$E$29:$E$528,$D14,$I$29:$I$528,"Expense") -> 0 | F14: =SUMIFS($J$29:$J$528,$E$29:$E$528,$D14,$I$29:$I$528,"Income") -> 0 | G14: =SUMIFS($J$29:$J$528,$E$29:$E$528,$D14,$I$29:$I$528,"Opening Balance") -> 0
D15: Personal Care | E15: =SUMIFS($J$29:$J$528,$E$29:$E$528,$D15,$I$29:$I$528,"Expense") -> 0 | F15: =SUMIFS($J$29:$J$528,$E$29:$E$528,$D15,$I$29:$I$528,"Income") -> 0 | G15: =SUMIFS($J$29:$J$528,$E$29:$E$528,$D15,$I$29:$I$528,"Opening Balance") -> 0
D16: Shopping | E16: =SUMIFS($J$29:$J$528,$E$29:$E$528,$D16,$I$29:$I$528,"Expense") -> 78.32 | F16: =SUMIFS($J$29:$J$528,$E$29:$E$528,$D16,$I$29:$I$528,"Income") -> 0 | G16: =SUMIFS($J$29:$J$528,$E$29:$E$528,$D16,$I$29:$I$528,"Opening Balance") -> 0
D17: Entertainment | E17: =SUMIFS($J$29:$J$528,$E$29:$E$528,$D17,$I$29:$I$528,"Expense") -> 332.82 | F17: =SUMIFS($J$29:$J$528,$E$29:$E$528,$D17,$I$29:$I$528,"Income") -> 0 | G17: =SUMIFS($J$29:$J$528,$E$29:$E$528,$D17,$I$29:$I$528,"Opening Balance") -> 0
D18: Travel | E18: =SUMIFS($J$29:$J$528,$E$29:$E$528,$D18,$I$29:$I$528,"Expense") -> 0 | F18: =SUMIFS($J$29:$J$528,$E$29:$E$528,$D18,$I$29:$I$528,"Income") -> 0 | G18: =SUMIFS($J$29:$J$528,$E$29:$E$528,$D18,$I$29:$I$528,"Opening Balance") -> 0
D19: Education | E19: =SUMIFS($J$29:$J$528,$E$29:$E$528,$D19,$I$29:$I$528,"Expense") -> 0 | F19: =SUMIFS($J$29:$J$528,$E$29:$E$528,$D19,$I$29:$I$528,"Income") -> 0 | G19: =SUMIFS($J$29:$J$528,$E$29:$E$528,$D19,$I$29:$I$528,"Opening Balance") -> 0
D20: Gifts & Donations | E20: =SUMIFS($J$29:$J$528,$E$29:$E$528,$D20,$I$29:$I$528,"Expense") -> 0 | F20: =SUMIFS($J$29:$J$528,$E$29:$E$528,$D20,$I$29:$I$528,"Income") -> 0 | G20: =SUMIFS($J$29:$J$528,$E$29:$E$528,$D20,$I$29:$I$528,"Opening Balance") -> 0
D21: Taxes | E21: =SUMIFS($J$29:$J$528,$E$29:$E$528,$D21,$I$29:$I$528,"Expense") -> 0 | F21: =SUMIFS($J$29:$J$528,$E$29:$E$528,$D21,$I$29:$I$528,"Income") -> 0 | G21: =SUMIFS($J$29:$J$528,$E$29:$E$528,$D21,$I$29:$I$528,"Opening Balance") -> 0
D22: Shipping | E22: =SUMIFS($J$29:$J$528,$E$29:$E$528,$D22,$I$29:$I$528,"Expense") -> 165.75 | F22: =SUMIFS($J$29:$J$528,$E$29:$E$528,$D22,$I$29:$I$528,"Income") -> 0 | G22: =SUMIFS($J$29:$J$528,$E$29:$E$528,$D22,$I$29:$I$528,"Opening Balance") -> 0
... D26: Essentials | E26: =SUMIFS($J$29:$J$528,$E$29:$E$528,$D26,$I$29:$I$528,"Expense") -> 142.42 | F26: =SUMIFS($J$29:$J$528,$E$29:$E$528,$D26,$I$29:$I$528,"Income") -> 0 | G26: =SUMIFS($J$29:$J$528,$E$29:$E$528,$D26,$I$29:$I$528,"Opening Balance") -> 0
A27: Transactions
A28: Date | B28: Week | C28: Description | D28: Merchant | E28: Category | F28: Subcategory | G28: Account | H28: Payment Method | I28: Type | J28: Amount | K28: Notes
A29: 46244 | B29: =IF(A29="","",INT(DAY(A29)/7)+1) -> 2 | C29: DEPOSIT ID NUMBER 503240 | D29: Existing Savings | E29: Existing Savings | F29: Starting balance | G29: Savings | H29: Bank Transfer | I29: Opening Balance | J29: 3200 | K29: 8월 3주차; Chase Secure (...7259); Balance shown: $3,200.00; Reclassified from income to existing savings
A30: 46244 | B30: =IF(A30="","",INT(DAY(A30)/7)+1) -> 2 | C30: HOMEGOODS #0515 NEW YORK NY 028967 08/10 | D30: HomeGoods | E30: Essentials | F30: Home goods | G30: Checking | H30: Debit Card | I30: Expense | J30: 16.32 | K30: 8월 3주차; Chase Secure (...7259); Balance shown: $3,183.68
A31: 46244 | B31: =IF(A31="","",INT(DAY(A31)/7)+1) -> 2 | C31: T-MOBILE 2563 BROADWAY NEW YORK NY 566367 08/10 | D31: T-Mobile | E31: Utilities | F31: Mobile phone | G31: Checking | H31: Debit Card | I31: Expense | J31: 61.08 | K31: 8월 3주차; Chase Secure (...7259); Balance shown: $3,122.60
A32: 46244 | B32: =IF(A32="","",INT(DAY(A32)/7)+1) -> 2 | C32: MTA*NYCT PAYGO NEW YORK NY 08/10 | D32: MTA NYCT Paygo | E32: Transportation | F32: Public transit | G32: Checking | H32: Debit Card | I32: Expense | J32: 3 | K32: 8월 3주차; Chase Secure (...7259); Balance shown: $3,119.60
A33: 46244 | B33: =IF(A33="","",INT(DAY(A33)/7)+1) -> 2 | C33: MTA*NYCT PAYGO NEW YORK NY 08/10 | D33: MTA NYCT Paygo | E33: Transportation | F33: Public transit | G33: Checking | H33: Debit Card | I33: Expense | J33: 3 | K33: 8월 3주차; Chase Secure (...7259); Balance shown: $3,116.60
A34: 46245 | B34: =IF(A34="","",INT(DAY(A34)/7)+1) -> 2 | C34: TARGET STORE T-3 10 UN NEW YORK NY 593369 08/11 | D34: Target | E34: Essentials | F34: Retail | G34: Checking | H34: Debit Card | I34: Expense | J34: 32.72 | K34: 8월 3주차; Chase Secure (...7259); Balance shown: $3,083.88
A35: 46245 | B35: =IF(A35="","",INT(DAY(A35)/7)+1) -> 2 | C35: TRADER JOE S #54 142 E NEW YORK NY 031581 08/11 | D35: Trader Joe's | E35: Groceries | F35: Groceries | G35: Checking | H35: Debit Card | I35: Expense | J35: 2.99 | K35: 8월 3주차; Chase Secure (...7259); Balance shown: $3,080.89
A36: 46245 | B36: =IF(A36="","",INT(DAY(A36)/7)+1) -> 2 | C36: TRADER JOE S #54 142 E NEW YORK NY 736951 08/11 | D36: Trader Joe's | E36: Groceries | F36: Groceries | G36: Checking | H36: Debit Card | I36: Expense | J36: 18.99 | K36: 8월 3주차; Chase Secure (...7259); Balance shown: $3,061.90
A37: 46245 | B37: =IF(A37="","",INT(DAY(A37)/7)+1) -> 2 | C37: TST*BOS BAGELS - HARLEM NEW YORK NY 08/11 | D37: Bo's Bagels Harlem | E37: Dining | F37: Bakery/Cafe | G37: Checking | H37: Debit Card | I37: Expense | J37: 16.15 | K37: 8월 3주차; Chase Secure (...7259); Balance shown: $3,045.75
A38: 46245 | B38: =IF(A38="","",INT(DAY(A38)/7)+1) -> 2 | C38: MTA*NYCT PAYGO NEW YORK NY 08/11 | D38: MTA NYCT Paygo | E38: Transportation | F38: Public transit | G38: Checking | H38: Debit Card | I38: Expense | J38: 3 | K38: 8월 3주차; Chase Secure (...7259); Balance shown: $3,042.75
A39: 46245 | B39: =IF(A39="","",INT(DAY(A39)/7)+1) -> 2 | C39: MTA*NYCT PAYGO NEW YORK NY 08/11 | D39: MTA NYCT Paygo | E39: Transportation | F39: Public transit | G39: Checking | H39: Debit Card | I39: Expense | J39: 3 | K39: 8월 3주차; Chase Secure (...7259); Balance shown: $3,039.75
A40: 46245 | B40: =IF(A40="","",INT(DAY(A40)/7)+1) -> 2 | C40: MTA*NYCT PAYGO NEW YORK NY 08/11 | D40: MTA NYCT Paygo | E40: Transportation | F40: Public transit | G40: Checking | H40: Debit Card | I40: Expense | J40: 3 | K40: 8월 3주차; Chase Secure (...7259); Balance shown: $3,036.75
... A118: 46265 | B118: =IF(A118="","",INT(DAY(A118)/7)+1) -> 5 | C118: SOOSANGHAN POCHA NEW PALISADES PAR NJ 08/27 (...0119) | D118: Soosanghan Pocha | E118: Dining | F118: Restaurant | G118: Checking | H118: Debit Card | I118: Expense | J118: 72.04 | K118: 8월 5주차; Chase Secure (...0119); Balance shown: $8,386.60
B119: =IF(A119="","",IF(DAY(A119)<=2,1,IF(DAY(A119)<=9,2,IF(DAY(A119)<=16,3,IF(DAY(A119)<=23,4,5)))))
B120: =IF(A120="","",IF(DAY(A120)<=2,1,IF(DAY(A120)<=9,2,IF(DAY(A120)<=16,3,IF(DAY(A120)<=23,4,5)))))
B121: =IF(A121="","",IF(DAY(A121)<=2,1,IF(DAY(A121)<=9,2,IF(DAY(A121)<=16,3,IF(DAY(A121)<=23,4,5)))))
B122: =IF(A122="","",IF(DAY(A122)<=2,1,IF(DAY(A122)<=9,2,IF(DAY(A122)<=16,3,IF(DAY(A122)<=23,4,5)))))
B123: =IF(A123="","",IF(DAY(A123)<=2,1,IF(DAY(A123)<=9,2,IF(DAY(A123)<=16,3,IF(DAY(A123)<=23,4,5)))))
B124: =IF(A124="","",IF(DAY(A124)<=2,1,IF(DAY(A124)<=9,2,IF(DAY(A124)<=16,3,IF(DAY(A124)<=23,4,5)))))
B125: =IF(A125="","",IF(DAY(A125)<=2,1,IF(DAY(A125)<=9,2,IF(DAY(A125)<=16,3,IF(DAY(A125)<=23,4,5)))))
B126: =IF(A126="","",IF(DAY(A126)<=2,1,IF(DAY(A126)<=9,2,IF(DAY(A126)<=16,3,IF(DAY(A126)<=23,4,5)))))
B127: =IF(A127="","",IF(DAY(A127)<=2,1,IF(DAY(A127)<=9,2,IF(DAY(A127)<=16,3,IF(DAY(A127)<=23,4,5)))))
B128: =IF(A128="","",IF(DAY(A128)<=2,1,IF(DAY(A128)<=9,2,IF(DAY(A128)<=16,3,IF(DAY(A128)<=23,4,5)))))
B129: =IF(A129="","",IF(DAY(A129)<=2,1,IF(DAY(A129)<=9,2,IF(DAY(A129)<=16,3,IF(DAY(A129)<=23,4,5)))))
B130: =IF(A130="","",IF(DAY(A130)<=2,1,IF(DAY(A130)<=9,2,IF(DAY(A130)<=16,3,IF(DAY(A130)<=23,4,5)))))
... B528: =IF(A528="","",IF(DAY(A528)<=2,1,IF(DAY(A528)<=9,2,IF(DAY(A528)<=16,3,IF(DAY(A528)<=23,4,5)))))

Sheet Sep 2026
A1: September 2026 Ledger
A2: Use positive amounts; expense reimbursements use negative amounts to reduce the original category.
A4: Month Summary | D4: Category Summary | H4: Weekly Summary
A5: Total Income | B5: =SUMIFS($J$29:$J$528,$I$29:$I$528,"Income") -> 3126 | D5: Category | E5: Expenses | F5: Income | G5: Existing Savings | H5: Week | I5: Expenses | J5: Income | K5: Net
A6: Total Expenses | B6: =SUMIFS($J$29:$J$528,$I$29:$I$528,"Expense") -> 2841.18 | D6: Housing | E6: =SUMIFS($J$29:$J$528,$E$29:$E$528,$D6,$I$29:$I$528,"Expense") -> 1100 | F6: =SUMIFS($J$29:$J$528,$E$29:$E$528,$D6,$I$29:$I$528,"Income") -> 0 | G6: =SUMIFS($J$29:$J$528,$E$29:$E$528,$D6,$I$29:$I$528,"Opening Balance") -> 0 | H6: Week 1 | I6: =SUMIFS($J$29:$J$528,$B$29:$B$528,1,$I$29:$I$528,"Expense",$F$29:$F$528,"<>Rent") -> 449.85 | J6: =SUMIFS($J$29:$J$528,$B$29:$B$528,1,$I$29:$I$528,"Income") -> 0 | K6: =J6-I6 -> -449.85
A7: Existing Savings | B7: =SUMIFS($J$29:$J$528,$I$29:$I$528,"Opening Balance") -> 0 | D7: Utilities | E7: =SUMIFS($J$29:$J$528,$E$29:$E$528,$D7,$I$29:$I$528,"Expense") -> 50.19 | F7: =SUMIFS($J$29:$J$528,$E$29:$E$528,$D7,$I$29:$I$528,"Income") -> 0 | G7: =SUMIFS($J$29:$J$528,$E$29:$E$528,$D7,$I$29:$I$528,"Opening Balance") -> 0 | H7: Week 2 | I7: =SUMIFS($J$29:$J$528,$B$29:$B$528,2,$I$29:$I$528,"Expense",$F$29:$F$528,"<>Rent") -> 462.9 | J7: =SUMIFS($J$29:$J$528,$B$29:$B$528,2,$I$29:$I$528,"Income") -> 1548 | K7: =J7-I7 -> 1085.1
A8: Transfers | B8: =SUMIFS($J$29:$J$528,$I$29:$I$528,"Transfer") -> 106 | D8: Groceries | E8: =SUMIFS($J$29:$J$528,$E$29:$E$528,$D8,$I$29:$I$528,"Expense") -> 264.75 | F8: =SUMIFS($J$29:$J$528,$E$29:$E$528,$D8,$I$29:$I$528,"Income") -> 0 | G8: =SUMIFS($J$29:$J$528,$E$29:$E$528,$D8,$I$29:$I$528,"Opening Balance") -> 0 | H8: Week 3 | I8: =SUMIFS($J$29:$J$528,$B$29:$B$528,3,$I$29:$I$528,"Expense",$F$29:$F$528,"<>Rent") -> 122.99 | J8: =SUMIFS($J$29:$J$528,$B$29:$B$528,3,$I$29:$I$528,"Income") -> 30 | K8: =J8-I8 -> -92.99
A9: Net Cash Flow | B9: =B5-B6 -> 284.82 | D9: Dining | E9: =SUMIFS($J$29:$J$528,$E$29:$E$528,$D9,$I$29:$I$528,"Expense") -> 567.13 | F9: =SUMIFS($J$29:$J$528,$E$29:$E$528,$D9,$I$29:$I$528,"Income") -> 0 | G9: =SUMIFS($J$29:$J$528,$E$29:$E$528,$D9,$I$29:$I$528,"Opening Balance") -> 0 | H9: Week 4 | I9: =SUMIFS($J$29:$J$528,$B$29:$B$528,4,$I$29:$I$528,"Expense",$F$29:$F$528,"<>Rent") -> 396.47 | J9: =SUMIFS($J$29:$J$528,$B$29:$B$528,4,$I$29:$I$528,"Income") -> 0 | K9: =J9-I9 -> -396.47
A10: Current Balance | B10: 9127.06 | D10: Transportation | E10: =SUMIFS($J$29:$J$528,$E$29:$E$528,$D10,$I$29:$I$528,"Expense") -> 152.65 | F10: =SUMIFS($J$29:$J$528,$E$29:$E$528,$D10,$I$29:$I$528,"Income") -> 0 | G10: =SUMIFS($J$29:$J$528,$E$29:$E$528,$D10,$I$29:$I$528,"Opening Balance") -> 0 | H10: Week 5 | I10: =SUMIFS($J$29:$J$528,$B$29:$B$528,5,$I$29:$I$528,"Expense",$F$29:$F$528,"<>Rent") -> 308.97 | J10: =SUMIFS($J$29:$J$528,$B$29:$B$528,5,$I$29:$I$528,"Income") -> 1548 | K10: =J10-I10 -> 1239.03
D11: Health & Medical | E11: =SUMIFS($J$29:$J$528,$E$29:$E$528,$D11,$I$29:$I$528,"Expense") -> 0 | F11: =SUMIFS($J$29:$J$528,$E$29:$E$528,$D11,$I$29:$I$528,"Income") -> 0 | G11: =SUMIFS($J$29:$J$528,$E$29:$E$528,$D11,$I$29:$I$528,"Opening Balance") -> 0 | H11: Monthly Net | I11: =B6 -> 2841.18 | J11: =B5 -> 3126 | K11: =J11-I11 -> 284.82
D12: Insurance | E12: =SUMIFS($J$29:$J$528,$E$29:$E$528,$D12,$I$29:$I$528,"Expense") -> 0 | F12: =SUMIFS($J$29:$J$528,$E$29:$E$528,$D12,$I$29:$I$528,"Income") -> 0 | G12: =SUMIFS($J$29:$J$528,$E$29:$E$528,$D12,$I$29:$I$528,"Opening Balance") -> 0 | H12: Includes rent
A13: Venmo/Zelle Alcohol Settlement | D13: Debt Payments | E13: =SUMIFS($J$29:$J$528,$E$29:$E$528,$D13,$I$29:$I$528,"Expense") -> 0 | F13: =SUMIFS($J$29:$J$528,$E$29:$E$528,$D13,$I$29:$I$528,"Income") -> 0 | G13: =SUMIFS($J$29:$J$528,$E$29:$E$528,$D13,$I$29:$I$528,"Opening Balance") -> 0
A14: Paid (+ expense) | B14: =SUMIFS($J$29:$J$528,$F$29:$F$528,"Alcohol settlement",$I$29:$I$528,"Expense",$J$29:$J$528,">0") -> 46.36 | D14: Savings & Investments | E14: =SUMIFS($J$29:$J$528,$E$29:$E$528,$D14,$I$29:$I$528,"Expense") -> 0 | F14: =SUMIFS($J$29:$J$528,$E$29:$E$528,$D14,$I$29:$I$528,"Income") -> 0 | G14: =SUMIFS($J$29:$J$528,$E$29:$E$528,$D14,$I$29:$I$528,"Opening Balance") -> 0
A15: Received (- expense) | B15: =SUMIFS($J$29:$J$528,$F$29:$F$528,"Alcohol settlement",$I$29:$I$528,"Expense",$J$29:$J$528,"<0") -> -44 | D15: Personal Care | E15: =SUMIFS($J$29:$J$528,$E$29:$E$528,$D15,$I$29:$I$528,"Expense") -> 0 | F15: =SUMIFS($J$29:$J$528,$E$29:$E$528,$D15,$I$29:$I$528,"Income") -> 0 | G15: =SUMIFS($J$29:$J$528,$E$29:$E$528,$D15,$I$29:$I$528,"Opening Balance") -> 0
A16: Net Alcohol Expense | B16: =SUM(B14:B15) -> 2.36 | D16: Shopping | E16: =SUMIFS($J$29:$J$528,$E$29:$E$528,$D16,$I$29:$I$528,"Expense") -> 395.68 | F16: =SUMIFS($J$29:$J$528,$E$29:$E$528,$D16,$I$29:$I$528,"Income") -> 0 | G16: =SUMIFS($J$29:$J$528,$E$29:$E$528,$D16,$I$29:$I$528,"Opening Balance") -> 0
D17: Entertainment | E17: =SUMIFS($J$29:$J$528,$E$29:$E$528,$D17,$I$29:$I$528,"Expense") -> 210.77 | F17: =SUMIFS($J$29:$J$528,$E$29:$E$528,$D17,$I$29:$I$528,"Income") -> 0 | G17: =SUMIFS($J$29:$J$528,$E$29:$E$528,$D17,$I$29:$I$528,"Opening Balance") -> 0
D18: Travel | E18: =SUMIFS($J$29:$J$528,$E$29:$E$528,$D18,$I$29:$I$528,"Expense") -> 0 | F18: =SUMIFS($J$29:$J$528,$E$29:$E$528,$D18,$I$29:$I$528,"Income") -> 0 | G18: =SUMIFS($J$29:$J$528,$E$29:$E$528,$D18,$I$29:$I$528,"Opening Balance") -> 0
D19: Education | E19: =SUMIFS($J$29:$J$528,$E$29:$E$528,$D19,$I$29:$I$528,"Expense") -> 100.01 | F19: =SUMIFS($J$29:$J$528,$E$29:$E$528,$D19,$I$29:$I$528,"Income") -> 0 | G19: =SUMIFS($J$29:$J$528,$E$29:$E$528,$D19,$I$29:$I$528,"Opening Balance") -> 0
D20: Gifts & Donations | E20: =SUMIFS($J$29:$J$528,$E$29:$E$528,$D20,$I$29:$I$528,"Expense") -> 0 | F20: =SUMIFS($J$29:$J$528,$E$29:$E$528,$D20,$I$29:$I$528,"Income") -> 0 | G20: =SUMIFS($J$29:$J$528,$E$29:$E$528,$D20,$I$29:$I$528,"Opening Balance") -> 0
D21: Taxes | E21: =SUMIFS($J$29:$J$528,$E$29:$E$528,$D21,$I$29:$I$528,"Expense") -> 0 | F21: =SUMIFS($J$29:$J$528,$E$29:$E$528,$D21,$I$29:$I$528,"Income") -> 0 | G21: =SUMIFS($J$29:$J$528,$E$29:$E$528,$D21,$I$29:$I$528,"Opening Balance") -> 0
D22: Shipping | E22: =SUMIFS($J$29:$J$528,$E$29:$E$528,$D22,$I$29:$I$528,"Expense") -> 0 | F22: =SUMIFS($J$29:$J$528,$E$29:$E$528,$D22,$I$29:$I$528,"Income") -> 0 | G22: =SUMIFS($J$29:$J$528,$E$29:$E$528,$D22,$I$29:$I$528,"Opening Balance") -> 0
D23: Income | E23: =SUMIFS($J$29:$J$528,$E$29:$E$528,$D23,$I$29:$I$528,"Expense") -> 0 | F23: =SUMIFS($J$29:$J$528,$E$29:$E$528,$D23,$I$29:$I$528,"Income") -> 3126 | G23: =SUMIFS($J$29:$J$528,$E$29:$E$528,$D23,$I$29:$I$528,"Opening Balance") -> 0
D24: Transfers | E24: =SUMIFS($J$29:$J$528,$E$29:$E$528,$D24,$I$29:$I$528,"Expense") -> 0 | F24: =SUMIFS($J$29:$J$528,$E$29:$E$528,$D24,$I$29:$I$528,"Income") -> 0 | G24: =SUMIFS($J$29:$J$528,$E$29:$E$528,$D24,$I$29:$I$528,"Opening Balance") -> 0
D25: Existing Savings | E25: =SUMIFS($J$29:$J$528,$E$29:$E$528,$D25,$I$29:$I$528,"Expense") -> 0 | F25: =SUMIFS($J$29:$J$528,$E$29:$E$528,$D25,$I$29:$I$528,"Income") -> 0 | G25: =SUMIFS($J$29:$J$528,$E$29:$E$528,$D25,$I$29:$I$528,"Opening Balance") -> 0
D26: Essentials | E26: =SUMIFS($J$29:$J$528,$E$29:$E$528,$D26,$I$29:$I$528,"Expense") -> 0 | F26: =SUMIFS($J$29:$J$528,$E$29:$E$528,$D26,$I$29:$I$528,"Income") -> 0 | G26: =SUMIFS($J$29:$J$528,$E$29:$E$528,$D26,$I$29:$I$528,"Opening Balance") -> 0
A27: Transactions
A28: Date | B28: Week | C28: Description | D28: Merchant | E28: Category | F28: Subcategory | G28: Account | H28: Payment Method | I28: Type | J28: Amount | K28: Notes
A29: 46266 | B29: =IF(A29="","",INT(DAY(A29)/7)+1) -> 1 | C29: Zelle payment to Joshua 30637153868 | D29: Joshua | E29: Housing | F29: Rent | G29: Checking | H29: Zelle debit | I29: Expense | J29: 500 | K29: 9월 1주차; Chase Secure (...0119); Balance shown: $7,721.00; Rent
A30: 46266 | B30: =IF(A30="","",INT(DAY(A30)/7)+1) -> 1 | C30: MTA*NYCT PAYGO NEW YORK NY 08/31 (...0119) | D30: MTA NYCT Paygo | E30: Transportation | F30: Public transit | G30: Checking | H30: Debit Card | I30: Expense | J30: 3 | K30: 9월 1주차; Chase Secure (...0119); Balance shown: $8,221.00
A31: 46266 | B31: =IF(A31="","",INT(DAY(A31)/7)+1) -> 1 | C31: MCDONALD'S F39704 NEW YORK NY 08/31 (...0119) | D31: McDonald's | E31: Dining | F31: Fast food | G31: Checking | H31: Debit Card | I31: Expense | J31: 7.62 | K31: 9월 1주차; Chase Secure (...0119); Balance shown: $8,224.00
A32: 46266 | B32: =IF(A32="","",INT(DAY(A32)/7)+1) -> 1 | C32: FIVE BELOW 8008 NEW YORK NY 08/31 (...0119) | D32: Five Below | E32: Shopping | F32: Retail | G32: Checking | H32: Debit Card | I32: Expense | J32: 7.62 | K32: 9월 1주차; Chase Secure (...0119); Balance shown: $8,231.62
A33: 46266 | B33: =IF(A33="","",INT(DAY(A33)/7)+1) -> 1 | C33: MTA*NYCT PAYGO NEW YORK NY 08/31 (...0119) | D33: MTA NYCT Paygo | E33: Transportation | F33: Public transit | G33: Checking | H33: Debit Card | I33: Expense | J33: 3 | K33: 9월 1주차; Chase Secure (...0119); Balance shown: $8,239.24
A34: 46266 | B34: =IF(A34="","",INT(DAY(A34)/7)+1) -> 1 | C34: Additional rent paid in cash | D34: Housing | E34: Housing | F34: Rent | G34: Cash | H34: Cash | I34: Expense | J34: 600 | K34: 9월 1주차; Additional rent paid in cash on 2026-09-01
A35: 46267 | B35: =IF(A35="","",INT(DAY(A35)/7)+1) -> 1 | C35: MTA*NYCT PAYGO NEW YORK NY 09/01 (...0119) | D35: MTA NYCT Paygo | E35: Transportation | F35: Public transit | G35: Checking | H35: Debit Card | I35: Expense | J35: 3 | K35: 9월 1주차; Chase Secure (...0119); Balance shown: $7,514.31
A36: 46267 | B36: =IF(A36="","",INT(DAY(A36)/7)+1) -> 1 | C36: SONY ELECTRONICS 800-249-7669 CA 09/02 (...0119) | D36: Sony Electronics | E36: Shopping | F36: Electronics | G36: Checking | H36: Debit Card | I36: Expense | J36: 194.02 | K36: 9월 1주차; Chase Secure (...0119); Balance shown: $7,517.31
A37: 46267 | B37: =IF(A37="","",INT(DAY(A37)/7)+1) -> 1 | C37: MTA*NYCT PAYGO NEW YORK NY 09/01 (...0119) | D37: MTA NYCT Paygo | E37: Transportation | F37: Public transit | G37: Checking | H37: Debit Card | I37: Expense | J37: 3 | K37: 9월 1주차; Chase Secure (...0119); Balance shown: $7,711.33
A38: 46267 | B38: =IF(A38="","",INT(DAY(A38)/7)+1) -> 1 | C38: SQ *SUPREME NY PIZZA I BROOKLYN NY 09/01 (...0119) | D38: Supreme NY Pizza | E38: Dining | F38: Restaurant/Pizza | G38: Checking | H38: Debit Card | I38: Expense | J38: 3.67 | K38: 9월 1주차; Chase Secure (...0119); Balance shown: $7,714.33
A39: 46267 | B39: =IF(A39="","",INT(DAY(A39)/7)+1) -> 1 | C39: MTA*NYCT PAYGO NEW YORK NY 09/01 (...0119) | D39: MTA NYCT Paygo | E39: Transportation | F39: Public transit | G39: Checking | H39: Debit Card | I39: Expense | J39: 3 | K39: 9월 1주차; Chase Secure (...0119); Balance shown: $7,718.00
A40: 46268 | B40: =IF(A40="","",INT(DAY(A40)/7)+1) -> 1 | C40: JACKPOT DEALS BROOKLYN NY 493481 09/03 (...0119) | D40: Jackpot Deals | E40: Shopping | F40: Retail | G40: Checking | H40: Debit Card | I40: Expense | J40: 10.87 | K40: 9월 1주차; Chase Secure (...0119); Balance shown: $7,465.42
... A153: 46295 | B153: =IF(A153="","",INT(DAY(A153)/7)+1) -> 5 | C153: MTA*NYCT PAYGO NEW YORK NY 09/29 (...0119) | D153: MTA NYCT Paygo | E153: Transportation | F153: Public transit | G153: Checking | H153: Debit Card | I153: Expense | J153: 3 | K153: 9월 5주차; Chase Secure (...0119); Posted 2026-09-30; Balance shown: $9,264.31
B154: =IF(A154="","",INT(DAY(A154)/7)+1)
B155: =IF(A155="","",INT(DAY(A155)/7)+1)
B156: =IF(A156="","",INT(DAY(A156)/7)+1)
B157: =IF(A157="","",INT(DAY(A157)/7)+1)
B158: =IF(A158="","",INT(DAY(A158)/7)+1)
B159: =IF(A159="","",INT(DAY(A159)/7)+1)
B160: =IF(A160="","",INT(DAY(A160)/7)+1)
B161: =IF(A161="","",INT(DAY(A161)/7)+1)
B162: =IF(A162="","",INT(DAY(A162)/7)+1)
B163: =IF(A163="","",INT(DAY(A163)/7)+1)
B164: =IF(A164="","",INT(DAY(A164)/7)+1)
B165: =IF(A165="","",INT(DAY(A165)/7)+1)
... B528: =IF(A528="","",INT(DAY(A528)/7)+1)

Sheet Oct 2026
A1: October 2026 Ledger
A2: Use positive amounts. Choose Type to classify each transaction.
A4: Month Summary | D4: Category Summary | H4: Weekly Summary
A5: Total Income | B5: =SUMIFS($J$29:$J$528,$I$29:$I$528,"Income") -> 0 | D5: Category | E5: Expenses | F5: Income | G5: Existing Savings | H5: Week | I5: Expenses | J5: Income | K5: Net
A6: Total Expenses | B6: =SUMIFS($J$29:$J$528,$I$29:$I$528,"Expense") -> 1536.47 | D6: Housing | E6: =SUMIFS($J$29:$J$528,$E$29:$E$528,$D6,$I$29:$I$528,"Expense") -> 1100 | F6: =SUMIFS($J$29:$J$528,$E$29:$E$528,$D6,$I$29:$I$528,"Income") -> 0 | G6: =SUMIFS($J$29:$J$528,$E$29:$E$528,$D6,$I$29:$I$528,"Opening Balance") -> 0 | H6: Week 1 | I6: =SUMIFS($J$29:$J$528,$B$29:$B$528,1,$I$29:$I$528,"Expense",$F$29:$F$528,"<>Rent") -> 119.19 | J6: =SUMIFS($J$29:$J$528,$B$29:$B$528,1,$I$29:$I$528,"Income") -> 0 | K6: =J6-I6 -> -119.19
A7: Existing Savings | B7: =SUMIFS($J$29:$J$528,$I$29:$I$528,"Opening Balance") -> 0 | D7: Utilities | E7: =SUMIFS($J$29:$J$528,$E$29:$E$528,$D7,$I$29:$I$528,"Expense") -> 0 | F7: =SUMIFS($J$29:$J$528,$E$29:$E$528,$D7,$I$29:$I$528,"Income") -> 0 | G7: =SUMIFS($J$29:$J$528,$E$29:$E$528,$D7,$I$29:$I$528,"Opening Balance") -> 0 | H7: Week 2 | I7: =SUMIFS($J$29:$J$528,$B$29:$B$528,2,$I$29:$I$528,"Expense",$F$29:$F$528,"<>Rent") -> 330.78 | J7: =SUMIFS($J$29:$J$528,$B$29:$B$528,2,$I$29:$I$528,"Income") -> 0 | K7: =J7-I7 -> -330.78
A8: Transfers | B8: =SUMIFS($J$29:$J$528,$I$29:$I$528,"Transfer") -> 0 | D8: Groceries | E8: =SUMIFS($J$29:$J$528,$E$29:$E$528,$D8,$I$29:$I$528,"Expense") -> 98.76 | F8: =SUMIFS($J$29:$J$528,$E$29:$E$528,$D8,$I$29:$I$528,"Income") -> 0 | G8: =SUMIFS($J$29:$J$528,$E$29:$E$528,$D8,$I$29:$I$528,"Opening Balance") -> 0 | H8: Week 3 | I8: =SUMIFS($J$29:$J$528,$B$29:$B$528,3,$I$29:$I$528,"Expense",$F$29:$F$528,"<>Rent") -> 0 | J8: =SUMIFS($J$29:$J$528,$B$29:$B$528,3,$I$29:$I$528,"Income") -> 0 | K8: =J8-I8 -> 0
A9: Net Cash Flow | B9: =B5-B6 -> -1536.47 | D9: Dining | E9: =SUMIFS($J$29:$J$528,$E$29:$E$528,$D9,$I$29:$I$528,"Expense") -> 136.15 | F9: =SUMIFS($J$29:$J$528,$E$29:$E$528,$D9,$I$29:$I$528,"Income") -> 0 | G9: =SUMIFS($J$29:$J$528,$E$29:$E$528,$D9,$I$29:$I$528,"Opening Balance") -> 0 | H9: Week 4 | I9: =SUMIFS($J$29:$J$528,$B$29:$B$528,4,$I$29:$I$528,"Expense",$F$29:$F$528,"<>Rent") -> 0 | J9: =SUMIFS($J$29:$J$528,$B$29:$B$528,4,$I$29:$I$528,"Income") -> 0 | K9: =J9-I9 -> 0
A10: Current Balance | B10: 7577.09 | D10: Transportation | E10: =SUMIFS($J$29:$J$528,$E$29:$E$528,$D10,$I$29:$I$528,"Expense") -> 35 | F10: =SUMIFS($J$29:$J$528,$E$29:$E$528,$D10,$I$29:$I$528,"Income") -> 0 | G10: =SUMIFS($J$29:$J$528,$E$29:$E$528,$D10,$I$29:$I$528,"Opening Balance") -> 0 | H10: Week 5 | I10: =SUMIFS($J$29:$J$528,$B$29:$B$528,5,$I$29:$I$528,"Expense",$F$29:$F$528,"<>Rent") -> 0 | J10: =SUMIFS($J$29:$J$528,$B$29:$B$528,5,$I$29:$I$528,"Income") -> 0 | K10: =J10-I10 -> 0
D11: Health & Medical | E11: =SUMIFS($J$29:$J$528,$E$29:$E$528,$D11,$I$29:$I$528,"Expense") -> 0 | F11: =SUMIFS($J$29:$J$528,$E$29:$E$528,$D11,$I$29:$I$528,"Income") -> 0 | G11: =SUMIFS($J$29:$J$528,$E$29:$E$528,$D11,$I$29:$I$528,"Opening Balance") -> 0
D12: Insurance | E12: =SUMIFS($J$29:$J$528,$E$29:$E$528,$D12,$I$29:$I$528,"Expense") -> 0 | F12: =SUMIFS($J$29:$J$528,$E$29:$E$528,$D12,$I$29:$I$528,"Income") -> 0 | G12: =SUMIFS($J$29:$J$528,$E$29:$E$528,$D12,$I$29:$I$528,"Opening Balance") -> 0
D13: Debt Payments | E13: =SUMIFS($J$29:$J$528,$E$29:$E$528,$D13,$I$29:$I$528,"Expense") -> 0 | F13: =SUMIFS($J$29:$J$528,$E$29:$E$528,$D13,$I$29:$I$528,"Income") -> 0 | G13: =SUMIFS($J$29:$J$528,$E$29:$E$528,$D13,$I$29:$I$528,"Opening Balance") -> 0
D14: Savings & Investments | E14: =SUMIFS($J$29:$J$528,$E$29:$E$528,$D14,$I$29:$I$528,"Expense") -> 0 | F14: =SUMIFS($J$29:$J$528,$E$29:$E$528,$D14,$I$29:$I$528,"Income") -> 0 | G14: =SUMIFS($J$29:$J$528,$E$29:$E$528,$D14,$I$29:$I$528,"Opening Balance") -> 0
D15: Personal Care | E15: =SUMIFS($J$29:$J$528,$E$29:$E$528,$D15,$I$29:$I$528,"Expense") -> 0 | F15: =SUMIFS($J$29:$J$528,$E$29:$E$528,$D15,$I$29:$I$528,"Income") -> 0 | G15: =SUMIFS($J$29:$J$528,$E$29:$E$528,$D15,$I$29:$I$528,"Opening Balance") -> 0
D16: Shopping | E16: =SUMIFS($J$29:$J$528,$E$29:$E$528,$D16,$I$29:$I$528,"Expense") -> 47.78 | F16: =SUMIFS($J$29:$J$528,$E$29:$E$528,$D16,$I$29:$I$528,"Income") -> 0 | G16: =SUMIFS($J$29:$J$528,$E$29:$E$528,$D16,$I$29:$I$528,"Opening Balance") -> 0
D17: Entertainment | E17: =SUMIFS($J$29:$J$528,$E$29:$E$528,$D17,$I$29:$I$528,"Expense") -> 0 | F17: =SUMIFS($J$29:$J$528,$E$29:$E$528,$D17,$I$29:$I$528,"Income") -> 0 | G17: =SUMIFS($J$29:$J$528,$E$29:$E$528,$D17,$I$29:$I$528,"Opening Balance") -> 0
D18: Travel | E18: =SUMIFS($J$29:$J$528,$E$29:$E$528,$D18,$I$29:$I$528,"Expense") -> 0 | F18: =SUMIFS($J$29:$J$528,$E$29:$E$528,$D18,$I$29:$I$528,"Income") -> 0 | G18: =SUMIFS($J$29:$J$528,$E$29:$E$528,$D18,$I$29:$I$528,"Opening Balance") -> 0
D19: Education | E19: =SUMIFS($J$29:$J$528,$E$29:$E$528,$D19,$I$29:$I$528,"Expense") -> 118.78 | F19: =SUMIFS($J$29:$J$528,$E$29:$E$528,$D19,$I$29:$I$528,"Income") -> 0 | G19: =SUMIFS($J$29:$J$528,$E$29:$E$528,$D19,$I$29:$I$528,"Opening Balance") -> 0
D20: Gifts & Donations | E20: =SUMIFS($J$29:$J$528,$E$29:$E$528,$D20,$I$29:$I$528,"Expense") -> 0 | F20: =SUMIFS($J$29:$J$528,$E$29:$E$528,$D20,$I$29:$I$528,"Income") -> 0 | G20: =SUMIFS($J$29:$J$528,$E$29:$E$528,$D20,$I$29:$I$528,"Opening Balance") -> 0
D21: Taxes | E21: =SUMIFS($J$29:$J$528,$E$29:$E$528,$D21,$I$29:$I$528,"Expense") -> 0 | F21: =SUMIFS($J$29:$J$528,$E$29:$E$528,$D21,$I$29:$I$528,"Income") -> 0 | G21: =SUMIFS($J$29:$J$528,$E$29:$E$528,$D21,$I$29:$I$528,"Opening Balance") -> 0
D22: Shipping | E22: =SUMIFS($J$29:$J$528,$E$29:$E$528,$D22,$I$29:$I$528,"Expense") -> 0 | F22: =SUMIFS($J$29:$J$528,$E$29:$E$528,$D22,$I$29:$I$528,"Income") -> 0 | G22: =SUMIFS($J$29:$J$528,$E$29:$E$528,$D22,$I$29:$I$528,"Opening Balance") -> 0
... D26: Essentials | E26: =SUMIFS($J$29:$J$528,$E$29:$E$528,$D26,$I$29:$I$528,"Expense") -> 0 | F26: =SUMIFS($J$29:$J$528,$E$29:$E$528,$D26,$I$29:$I$528,"Income") -> 0 | G26: =SUMIFS($J$29:$J$528,$E$29:$E$528,$D26,$I$29:$I$528,"Opening Balance") -> 0
A27: Transactions
A28: Date | B28: Week | C28: Description | D28: Merchant | E28: Category | F28: Subcategory | G28: Account | H28: Payment Method | I28: Type | J28: Amount | K28: Notes
A29: 46296 | B29: =IF(A29="","",IF(DAY(A29)<=3,1,INT((DAY(A29)-4)/7)+2)) -> 1 | C29: Zelle payment to Joshua 31037164703 | D29: Joshua | E29: Housing | F29: Rent | G29: Checking | H29: Venmo/Zelle/PayPal | I29: Expense | J29: 100 | K29: 10월 1주차; Chase Secure (...0119); Posted 2026-10-01; Balance shown: $8,020.85; Rent (user confirmed)
A30: 46296 | B30: =IF(A30="","",IF(DAY(A30)<=3,1,INT((DAY(A30)-4)/7)+2)) -> 1 | C30: ATM WITHDRAWAL 002164 10/013359 BROA (...0119) | D30: ATM | E30: Housing | F30: Rent | G30: Checking | H30: Other | I30: Expense | J30: 500 | K30: 10월 1주차; Chase Secure (...0119); Posted 2026-10-01; Balance shown: $8,120.85; ATM withdrawal used for rent (user confirmed); counted as Housing/Rent expense
A31: 46296 | B31: =IF(A31="","",IF(DAY(A31)<=3,1,INT((DAY(A31)-4)/7)+2)) -> 1 | C31: ATM WITHDRAWAL 002162 10/013359 BROA (...0119) | D31: ATM | E31: Housing | F31: Rent | G31: Checking | H31: Other | I31: Expense | J31: 500 | K31: 10월 1주차; Chase Secure (...0119); Posted 2026-10-01; Balance shown: $8,620.85; ATM withdrawal used for rent (user confirmed); counted as Housing/Rent expense
A32: 46296 | B32: =IF(A32="","",IF(DAY(A32)<=3,1,INT((DAY(A32)-4)/7)+2)) -> 1 | C32: 99 CENT SUPREME PIZZA BROOKLYN NY 09/29 (...0119) | D32: 99 Cent Supreme Pizza | E32: Dining | F32: Restaurant/Pizza | G32: Checking | H32: Debit Card | I32: Expense | J32: 6.21 | K32: 10월 1주차; Chase Secure (...0119); Posted 2026-10-01; Balance shown: $9,120.85
A33: 46297 | B33: =IF(A33="","",IF(DAY(A33)<=3,1,INT((DAY(A33)-4)/7)+2)) -> 1 | C33: TRADER JOE S #54 445 G NEW YORK NY 172057 10/02 (...0119) | D33: Trader Joe's | E33: Groceries | F33: Groceries | G33: Checking | H33: Debit Card | I33: Expense | J33: 46.07 | K33: 10월 1주차; Chase Secure (...0119); Posted 2026-10-02; Balance shown: $7,907.87
A34: 46297 | B34: =IF(A34="","",IF(DAY(A34)<=3,1,INT((DAY(A34)-4)/7)+2)) -> 1 | C34: MTA*NYCT PAYGO NEW YORK NY 10/01 (...0119) | D34: MTA NYCT Paygo | E34: Transportation | F34: Public transit | G34: Checking | H34: Debit Card | I34: Expense | J34: 3 | K34: 10월 1주차; Chase Secure (...0119); Posted 2026-10-02; Balance shown: $7,953.94
A35: 46297 | B35: =IF(A35="","",IF(DAY(A35)<=3,1,INT((DAY(A35)-4)/7)+2)) -> 1 | C35: MTA*NYCT PAYGO NEW YORK NY 10/01 (...0119) | D35: MTA NYCT Paygo | E35: Transportation | F35: Public transit | G35: Checking | H35: Debit Card | I35: Expense | J35: 3 | K35: 10월 1주차; Chase Secure (...0119); Posted 2026-10-02; Balance shown: $7,956.94
A36: 46297 | B36: =IF(A36="","",IF(DAY(A36)<=3,1,INT((DAY(A36)-4)/7)+2)) -> 1 | C36: IHOP 3503 OLO BROOKLYN NY 10/01 (...0119) | D36: IHOP | E36: Dining | F36: Restaurant | G36: Checking | H36: Debit Card | I36: Expense | J36: 20.24 | K36: 10월 1주차; Chase Secure (...0119); Posted 2026-10-02; Balance shown: $7,959.94
A37: 46297 | B37: =IF(A37="","",IF(DAY(A37)<=3,1,INT((DAY(A37)-4)/7)+2)) -> 1 | C37: CHIPOTLE 2090 BROOKLYN NY 10/01 (...0119) | D37: Chipotle | E37: Dining | F37: Restaurant | G37: Checking | H37: Debit Card | I37: Expense | J37: 15.02 | K37: 10월 1주차; Chase Secure (...0119); Posted 2026-10-02; Balance shown: $7,980.18
A38: 46297 | B38: =IF(A38="","",IF(DAY(A38)<=3,1,INT((DAY(A38)-4)/7)+2)) -> 1 | C38: MTA*NYCT PAYGO NEW YORK NY 10/01 (...0119) | D38: MTA NYCT Paygo | E38: Transportation | F38: Public transit | G38: Checking | H38: Debit Card | I38: Expense | J38: 3 | K38: 10월 1주차; Chase Secure (...0119); Posted 2026-10-02; Balance shown: $7,995.20
A39: 46297 | B39: =IF(A39="","",IF(DAY(A39)<=3,1,INT((DAY(A39)-4)/7)+2)) -> 1 | C39: GOLDEN DELI CORP NEW YORK NY 09/30 (...0119) | D39: Golden Deli | E39: Dining | F39: Deli | G39: Checking | H39: Debit Card | I39: Expense | J39: 22.65 | K39: 10월 1주차; Chase Secure (...0119); Posted 2026-10-02; Balance shown: $7,998.20; Category inferred from merchant; purchase details unconfirmed
A40: 46300 | B40: =IF(A40="","",IF(DAY(A40)<=3,1,INT((DAY(A40)-4)/7)+2)) -> 2 | C40: Amazon.com*5924406G1 Amzn.com/bill WA 10/05 (...0119) | D40: Amazon | E40: Shopping | F40: Retail | G40: Checking | H40: Debit Card | I40: Expense | J40: 6.42 | K40: 10월 1주차; Chase Secure (...0119); Posted 2026-10-05; Balance shown: $7,764.09; Category inferred from merchant; purchase details unconfirmed
... A66: 46305 | B66: =IF(A66="","",IF(DAY(A66)<=3,1,INT((DAY(A66)-4)/7)+2)) -> 2 | C66: MTA*NYCT PAYGO NEW YORK NY 10/08 (...0119) | D66: MTA NYCT Paygo | E66: Transportation | F66: Public transit | G66: Checking | H66: Debit Card | I66: Expense | J66: 3 | K66: 10월 2주차; Chase Secure (...0119); Posted 2026-10-09; Balance shown: $7,577.09
B67: =IF(A67="","",INT((DAY(A67)-1)/7)+1)
B68: =IF(A68="","",INT((DAY(A68)-1)/7)+1)
B69: =IF(A69="","",INT((DAY(A69)-1)/7)+1)
B70: =IF(A70="","",INT((DAY(A70)-1)/7)+1)
B71: =IF(A71="","",INT((DAY(A71)-1)/7)+1)
B72: =IF(A72="","",INT((DAY(A72)-1)/7)+1)
B73: =IF(A73="","",INT((DAY(A73)-1)/7)+1)
B74: =IF(A74="","",INT((DAY(A74)-1)/7)+1)
B75: =IF(A75="","",INT((DAY(A75)-1)/7)+1)
B76: =IF(A76="","",INT((DAY(A76)-1)/7)+1)
B77: =IF(A77="","",INT((DAY(A77)-1)/7)+1)
B78: =IF(A78="","",INT((DAY(A78)-1)/7)+1)
... B528: =IF(A528="","",INT((DAY(A528)-1)/7)+1)

Sheet Nov 2026
A1: November 2026 Ledger
A2: Use positive amounts. Choose Type to classify each transaction.
A4: Month Summary | D4: Category Summary | H4: Weekly Summary
A5: Total Income | B5: =SUMIFS($J$29:$J$528,$I$29:$I$528,"Income") | D5: Category | E5: Expenses | F5: Income | G5: Existing Savings | H5: Week | I5: Expenses | J5: Income | K5: Net
A6: Total Expenses | B6: =SUMIFS($J$29:$J$528,$I$29:$I$528,"Expense") | D6: Housing | E6: =SUMIFS($J$29:$J$528,$E$29:$E$528,$D6,$I$29:$I$528,"Expense") | F6: =SUMIFS($J$29:$J$528,$E$29:$E$528,$D6,$I$29:$I$528,"Income") | G6: =SUMIFS($J$29:$J$528,$E$29:$E$528,$D6,$I$29:$I$528,"Opening Balance") | H6: Week 1 | I6: =SUMIFS($J$29:$J$528,$B$29:$B$528,1,$I$29:$I$528,"Expense",$F$29:$F$528,"<>Rent") | J6: =SUMIFS($J$29:$J$528,$B$29:$B$528,1,$I$29:$I$528,"Income") | K6: =J6-I6
A7: Existing Savings | B7: =SUMIFS($J$29:$J$528,$I$29:$I$528,"Opening Balance") | D7: Utilities | E7: =SUMIFS($J$29:$J$528,$E$29:$E$528,$D7,$I$29:$I$528,"Expense") | F7: =SUMIFS($J$29:$J$528,$E$29:$E$528,$D7,$I$29:$I$528,"Income") | G7: =SUMIFS($J$29:$J$528,$E$29:$E$528,$D7,$I$29:$I$528,"Opening Balance") | H7: Week 2 | I7: =SUMIFS($J$29:$J$528,$B$29:$B$528,2,$I$29:$I$528,"Expense",$F$29:$F$528,"<>Rent") | J7: =SUMIFS($J$29:$J$528,$B$29:$B$528,2,$I$29:$I$528,"Income") | K7: =J7-I7
A8: Transfers | B8: =SUMIFS($J$29:$J$528,$I$29:$I$528,"Transfer") | D8: Groceries | E8: =SUMIFS($J$29:$J$528,$E$29:$E$528,$D8,$I$29:$I$528,"Expense") | F8: =SUMIFS($J$29:$J$528,$E$29:$E$528,$D8,$I$29:$I$528,"Income") | G8: =SUMIFS($J$29:$J$528,$E$29:$E$528,$D8,$I$29:$I$528,"Opening Balance") | H8: Week 3 | I8: =SUMIFS($J$29:$J$528,$B$29:$B$528,3,$I$29:$I$528,"Expense",$F$29:$F$528,"<>Rent") | J8: =SUMIFS($J$29:$J$528,$B$29:$B$528,3,$I$29:$I$528,"Income") | K8: =J8-I8
A9: Net Cash Flow | B9: =B5-B6 | D9: Dining | E9: =SUMIFS($J$29:$J$528,$E$29:$E$528,$D9,$I$29:$I$528,"Expense") | F9: =SUMIFS($J$29:$J$528,$E$29:$E$528,$D9,$I$29:$I$528,"Income") | G9: =SUMIFS($J$29:$J$528,$E$29:$E$528,$D9,$I$29:$I$528,"Opening Balance") | H9: Week 4 | I9: =SUMIFS($J$29:$J$528,$B$29:$B$528,4,$I$29:$I$528,"Expense",$F$29:$F$528,"<>Rent") | J9: =SUMIFS($J$29:$J$528,$B$29:$B$528,4,$I$29:$I$528,"Income") | K9: =J9-I9
D10: Transportation | E10: =SUMIFS($J$29:$J$528,$E$29:$E$528,$D10,$I$29:$I$528,"Expense") | F10: =SUMIFS($J$29:$J$528,$E$29:$E$528,$D10,$I$29:$I$528,"Income") | G10: =SUMIFS($J$29:$J$528,$E$29:$E$528,$D10,$I$29:$I$528,"Opening Balance") | H10: Week 5 | I10: =SUMIFS($J$29:$J$528,$B$29:$B$528,5,$I$29:$I$528,"Expense",$F$29:$F$528,"<>Rent") | J10: =SUMIFS($J$29:$J$528,$B$29:$B$528,5,$I$29:$I$528,"Income") | K10: =J10-I10
D11: Health & Medical | E11: =SUMIFS($J$29:$J$528,$E$29:$E$528,$D11,$I$29:$I$528,"Expense") | F11: =SUMIFS($J$29:$J$528,$E$29:$E$528,$D11,$I$29:$I$528,"Income") | G11: =SUMIFS($J$29:$J$528,$E$29:$E$528,$D11,$I$29:$I$528,"Opening Balance")
D12: Insurance | E12: =SUMIFS($J$29:$J$528,$E$29:$E$528,$D12,$I$29:$I$528,"Expense") | F12: =SUMIFS($J$29:$J$528,$E$29:$E$528,$D12,$I$29:$I$528,"Income") | G12: =SUMIFS($J$29:$J$528,$E$29:$E$528,$D12,$I$29:$I$528,"Opening Balance")
D13: Debt Payments | E13: =SUMIFS($J$29:$J$528,$E$29:$E$528,$D13,$I$29:$I$528,"Expense") | F13: =SUMIFS($J$29:$J$528,$E$29:$E$528,$D13,$I$29:$I$528,"Income") | G13: =SUMIFS($J$29:$J$528,$E$29:$E$528,$D13,$I$29:$I$528,"Opening Balance")
D14: Savings & Investments | E14: =SUMIFS($J$29:$J$528,$E$29:$E$528,$D14,$I$29:$I$528,"Expense") | F14: =SUMIFS($J$29:$J$528,$E$29:$E$528,$D14,$I$29:$I$528,"Income") | G14: =SUMIFS($J$29:$J$528,$E$29:$E$528,$D14,$I$29:$I$528,"Opening Balance")
D15: Personal Care | E15: =SUMIFS($J$29:$J$528,$E$29:$E$528,$D15,$I$29:$I$528,"Expense") | F15: =SUMIFS($J$29:$J$528,$E$29:$E$528,$D15,$I$29:$I$528,"Income") | G15: =SUMIFS($J$29:$J$528,$E$29:$E$528,$D15,$I$29:$I$528,"Opening Balance")
D16: Shopping | E16: =SUMIFS($J$29:$J$528,$E$29:$E$528,$D16,$I$29:$I$528,"Expense") | F16: =SUMIFS($J$29:$J$528,$E$29:$E$528,$D16,$I$29:$I$528,"Income") | G16: =SUMIFS($J$29:$J$528,$E$29:$E$528,$D16,$I$29:$I$528,"Opening Balance")
D17: Entertainment | E17: =SUMIFS($J$29:$J$528,$E$29:$E$528,$D17,$I$29:$I$528,"Expense") | F17: =SUMIFS($J$29:$J$528,$E$29:$E$528,$D17,$I$29:$I$528,"Income") | G17: =SUMIFS($J$29:$J$528,$E$29:$E$528,$D17,$I$29:$I$528,"Opening Balance")
D18: Travel | E18: =SUMIFS($J$29:$J$528,$E$29:$E$528,$D18,$I$29:$I$528,"Expense") | F18: =SUMIFS($J$29:$J$528,$E$29:$E$528,$D18,$I$29:$I$528,"Income") | G18: =SUMIFS($J$29:$J$528,$E$29:$E$528,$D18,$I$29:$I$528,"Opening Balance")
D19: Education | E19: =SUMIFS($J$29:$J$528,$E$29:$E$528,$D19,$I$29:$I$528,"Expense") | F19: =SUMIFS($J$29:$J$528,$E$29:$E$528,$D19,$I$29:$I$528,"Income") | G19: =SUMIFS($J$29:$J$528,$E$29:$E$528,$D19,$I$29:$I$528,"Opening Balance")
D20: Gifts & Donations | E20: =SUMIFS($J$29:$J$528,$E$29:$E$528,$D20,$I$29:$I$528,"Expense") | F20: =SUMIFS($J$29:$J$528,$E$29:$E$528,$D20,$I$29:$I$528,"Income") | G20: =SUMIFS($J$29:$J$528,$E$29:$E$528,$D20,$I$29:$I$528,"Opening Balance")
D21: Taxes | E21: =SUMIFS($J$29:$J$528,$E$29:$E$528,$D21,$I$29:$I$528,"Expense") | F21: =SUMIFS($J$29:$J$528,$E$29:$E$528,$D21,$I$29:$I$528,"Income") | G21: =SUMIFS($J$29:$J$528,$E$29:$E$528,$D21,$I$29:$I$528,"Opening Balance")
D22: Shipping | E22: =SUMIFS($J$29:$J$528,$E$29:$E$528,$D22,$I$29:$I$528,"Expense") | F22: =SUMIFS($J$29:$J$528,$E$29:$E$528,$D22,$I$29:$I$528,"Income") | G22: =SUMIFS($J$29:$J$528,$E$29:$E$528,$D22,$I$29:$I$528,"Opening Balance")
... D26: Essentials | E26: =SUMIFS($J$29:$J$528,$E$29:$E$528,$D26,$I$29:$I$528,"Expense") | F26: =SUMIFS($J$29:$J$528,$E$29:$E$528,$D26,$I$29:$I$528,"Income") | G26: =SUMIFS($J$29:$J$528,$E$29:$E$528,$D26,$I$29:$I$528,"Opening Balance")
A27: Transactions
A28: Date | B28: Week | C28: Description | D28: Merchant | E28: Category | F28: Subcategory | G28: Account | H28: Payment Method | I28: Type | J28: Amount | K28: Notes
B29: =IF(A29="","",INT((DAY(A29)-1)/7)+1)
B30: =IF(A30="","",INT((DAY(A30)-1)/7)+1)
B31: =IF(A31="","",INT((DAY(A31)-1)/7)+1)
B32: =IF(A32="","",INT((DAY(A32)-1)/7)+1)
B33: =IF(A33="","",INT((DAY(A33)-1)/7)+1)
B34: =IF(A34="","",INT((DAY(A34)-1)/7)+1)
B35: =IF(A35="","",INT((DAY(A35)-1)/7)+1)
B36: =IF(A36="","",INT((DAY(A36)-1)/7)+1)
B37: =IF(A37="","",INT((DAY(A37)-1)/7)+1)
B38: =IF(A38="","",INT((DAY(A38)-1)/7)+1)
B39: =IF(A39="","",INT((DAY(A39)-1)/7)+1)
B40: =IF(A40="","",INT((DAY(A40)-1)/7)+1)
... B528: =IF(A528="","",INT((DAY(A528)-1)/7)+1)

Sheet Dec 2026
A1: December 2026 Ledger
A2: Use positive amounts. Choose Type to classify each transaction.
A4: Month Summary | D4: Category Summary | H4: Weekly Summary
A5: Total Income | B5: =SUMIFS($J$29:$J$528,$I$29:$I$528,"Income") | D5: Category | E5: Expenses | F5: Income | G5: Existing Savings | H5: Week | I5: Expenses | J5: Income | K5: Net
A6: Total Expenses | B6: =SUMIFS($J$29:$J$528,$I$29:$I$528,"Expense") | D6: Housing | E6: =SUMIFS($J$29:$J$528,$E$29:$E$528,$D6,$I$29:$I$528,"Expense") | F6: =SUMIFS($J$29:$J$528,$E$29:$E$528,$D6,$I$29:$I$528,"Income") | G6: =SUMIFS($J$29:$J$528,$E$29:$E$528,$D6,$I$29:$I$528,"Opening Balance") | H6: Week 1 | I6: =SUMIFS($J$29:$J$528,$B$29:$B$528,1,$I$29:$I$528,"Expense",$F$29:$F$528,"<>Rent") | J6: =SUMIFS($J$29:$J$528,$B$29:$B$528,1,$I$29:$I$528,"Income") | K6: =J6-I6
A7: Existing Savings | B7: =SUMIFS($J$29:$J$528,$I$29:$I$528,"Opening Balance") | D7: Utilities | E7: =SUMIFS($J$29:$J$528,$E$29:$E$528,$D7,$I$29:$I$528,"Expense") | F7: =SUMIFS($J$29:$J$528,$E$29:$E$528,$D7,$I$29:$I$528,"Income") | G7: =SUMIFS($J$29:$J$528,$E$29:$E$528,$D7,$I$29:$I$528,"Opening Balance") | H7: Week 2 | I7: =SUMIFS($J$29:$J$528,$B$29:$B$528,2,$I$29:$I$528,"Expense",$F$29:$F$528,"<>Rent") | J7: =SUMIFS($J$29:$J$528,$B$29:$B$528,2,$I$29:$I$528,"Income") | K7: =J7-I7
A8: Transfers | B8: =SUMIFS($J$29:$J$528,$I$29:$I$528,"Transfer") | D8: Groceries | E8: =SUMIFS($J$29:$J$528,$E$29:$E$528,$D8,$I$29:$I$528,"Expense") | F8: =SUMIFS($J$29:$J$528,$E$29:$E$528,$D8,$I$29:$I$528,"Income") | G8: =SUMIFS($J$29:$J$528,$E$29:$E$528,$D8,$I$29:$I$528,"Opening Balance") | H8: Week 3 | I8: =SUMIFS($J$29:$J$528,$B$29:$B$528,3,$I$29:$I$528,"Expense",$F$29:$F$528,"<>Rent") | J8: =SUMIFS($J$29:$J$528,$B$29:$B$528,3,$I$29:$I$528,"Income") | K8: =J8-I8
A9: Net Cash Flow | B9: =B5-B6 | D9: Dining | E9: =SUMIFS($J$29:$J$528,$E$29:$E$528,$D9,$I$29:$I$528,"Expense") | F9: =SUMIFS($J$29:$J$528,$E$29:$E$528,$D9,$I$29:$I$528,"Income") | G9: =SUMIFS($J$29:$J$528,$E$29:$E$528,$D9,$I$29:$I$528,"Opening Balance") | H9: Week 4 | I9: =SUMIFS($J$29:$J$528,$B$29:$B$528,4,$I$29:$I$528,"Expense",$F$29:$F$528,"<>Rent") | J9: =SUMIFS($J$29:$J$528,$B$29:$B$528,4,$I$29:$I$528,"Income") | K9: =J9-I9
D10: Transportation | E10: =SUMIFS($J$29:$J$528,$E$29:$E$528,$D10,$I$29:$I$528,"Expense") | F10: =SUMIFS($J$29:$J$528,$E$29:$E$528,$D10,$I$29:$I$528,"Income") | G10: =SUMIFS($J$29:$J$528,$E$29:$E$528,$D10,$I$29:$I$528,"Opening Balance") | H10: Week 5 | I10: =SUMIFS($J$29:$J$528,$B$29:$B$528,5,$I$29:$I$528,"Expense",$F$29:$F$528,"<>Rent") | J10: =SUMIFS($J$29:$J$528,$B$29:$B$528,5,$I$29:$I$528,"Income") | K10: =J10-I10
D11: Health & Medical | E11: =SUMIFS($J$29:$J$528,$E$29:$E$528,$D11,$I$29:$I$528,"Expense") | F11: =SUMIFS($J$29:$J$528,$E$29:$E$528,$D11,$I$29:$I$528,"Income") | G11: =SUMIFS($J$29:$J$528,$E$29:$E$528,$D11,$I$29:$I$528,"Opening Balance")
D12: Insurance | E12: =SUMIFS($J$29:$J$528,$E$29:$E$528,$D12,$I$29:$I$528,"Expense") | F12: =SUMIFS($J$29:$J$528,$E$29:$E$528,$D12,$I$29:$I$528,"Income") | G12: =SUMIFS($J$29:$J$528,$E$29:$E$528,$D12,$I$29:$I$528,"Opening Balance")
D13: Debt Payments | E13: =SUMIFS($J$29:$J$528,$E$29:$E$528,$D13,$I$29:$I$528,"Expense") | F13: =SUMIFS($J$29:$J$528,$E$29:$E$528,$D13,$I$29:$I$528,"Income") | G13: =SUMIFS($J$29:$J$528,$E$29:$E$528,$D13,$I$29:$I$528,"Opening Balance")
D14: Savings & Investments | E14: =SUMIFS($J$29:$J$528,$E$29:$E$528,$D14,$I$29:$I$528,"Expense") | F14: =SUMIFS($J$29:$J$528,$E$29:$E$528,$D14,$I$29:$I$528,"Income") | G14: =SUMIFS($J$29:$J$528,$E$29:$E$528,$D14,$I$29:$I$528,"Opening Balance")
D15: Personal Care | E15: =SUMIFS($J$29:$J$528,$E$29:$E$528,$D15,$I$29:$I$528,"Expense") | F15: =SUMIFS($J$29:$J$528,$E$29:$E$528,$D15,$I$29:$I$528,"Income") | G15: =SUMIFS($J$29:$J$528,$E$29:$E$528,$D15,$I$29:$I$528,"Opening Balance")
D16: Shopping | E16: =SUMIFS($J$29:$J$528,$E$29:$E$528,$D16,$I$29:$I$528,"Expense") | F16: =SUMIFS($J$29:$J$528,$E$29:$E$528,$D16,$I$29:$I$528,"Income") | G16: =SUMIFS($J$29:$J$528,$E$29:$E$528,$D16,$I$29:$I$528,"Opening Balance")
D17: Entertainment | E17: =SUMIFS($J$29:$J$528,$E$29:$E$528,$D17,$I$29:$I$528,"Expense") | F17: =SUMIFS($J$29:$J$528,$E$29:$E$528,$D17,$I$29:$I$528,"Income") | G17: =SUMIFS($J$29:$J$528,$E$29:$E$528,$D17,$I$29:$I$528,"Opening Balance")
D18: Travel | E18: =SUMIFS($J$29:$J$528,$E$29:$E$528,$D18,$I$29:$I$528,"Expense") | F18: =SUMIFS($J$29:$J$528,$E$29:$E$528,$D18,$I$29:$I$528,"Income") | G18: =SUMIFS($J$29:$J$528,$E$29:$E$528,$D18,$I$29:$I$528,"Opening Balance")
D19: Education | E19: =SUMIFS($J$29:$J$528,$E$29:$E$528,$D19,$I$29:$I$528,"Expense") | F19: =SUMIFS($J$29:$J$528,$E$29:$E$528,$D19,$I$29:$I$528,"Income") | G19: =SUMIFS($J$29:$J$528,$E$29:$E$528,$D19,$I$29:$I$528,"Opening Balance")
D20: Gifts & Donations | E20: =SUMIFS($J$29:$J$528,$E$29:$E$528,$D20,$I$29:$I$528,"Expense") | F20: =SUMIFS($J$29:$J$528,$E$29:$E$528,$D20,$I$29:$I$528,"Income") | G20: =SUMIFS($J$29:$J$528,$E$29:$E$528,$D20,$I$29:$I$528,"Opening Balance")
D21: Taxes | E21: =SUMIFS($J$29:$J$528,$E$29:$E$528,$D21,$I$29:$I$528,"Expense") | F21: =SUMIFS($J$29:$J$528,$E$29:$E$528,$D21,$I$29:$I$528,"Income") | G21: =SUMIFS($J$29:$J$528,$E$29:$E$528,$D21,$I$29:$I$528,"Opening Balance")
D22: Shipping | E22: =SUMIFS($J$29:$J$528,$E$29:$E$528,$D22,$I$29:$I$528,"Expense") | F22: =SUMIFS($J$29:$J$528,$E$29:$E$528,$D22,$I$29:$I$528,"Income") | G22: =SUMIFS($J$29:$J$528,$E$29:$E$528,$D22,$I$29:$I$528,"Opening Balance")
... D26: Essentials | E26: =SUMIFS($J$29:$J$528,$E$29:$E$528,$D26,$I$29:$I$528,"Expense") | F26: =SUMIFS($J$29:$J$528,$E$29:$E$528,$D26,$I$29:$I$528,"Income") | G26: =SUMIFS($J$29:$J$528,$E$29:$E$528,$D26,$I$29:$I$528,"Opening Balance")
A27: Transactions
A28: Date | B28: Week | C28: Description | D28: Merchant | E28: Category | F28: Subcategory | G28: Account | H28: Payment Method | I28: Type | J28: Amount | K28: Notes
B29: =IF(A29="","",INT((DAY(A29)-1)/7)+1)
B30: =IF(A30="","",INT((DAY(A30)-1)/7)+1)
B31: =IF(A31="","",INT((DAY(A31)-1)/7)+1)
B32: =IF(A32="","",INT((DAY(A32)-1)/7)+1)
B33: =IF(A33="","",INT((DAY(A33)-1)/7)+1)
B34: =IF(A34="","",INT((DAY(A34)-1)/7)+1)
B35: =IF(A35="","",INT((DAY(A35)-1)/7)+1)
B36: =IF(A36="","",INT((DAY(A36)-1)/7)+1)
B37: =IF(A37="","",INT((DAY(A37)-1)/7)+1)
B38: =IF(A38="","",INT((DAY(A38)-1)/7)+1)
B39: =IF(A39="","",INT((DAY(A39)-1)/7)+1)
B40: =IF(A40="","",INT((DAY(A40)-1)/7)+1)
... B528: =IF(A528="","",INT((DAY(A528)-1)/7)+1)

Sheet Lists
A1: Categories | B1: Types | C1: Payment Methods | D1: Accounts
A2: Housing | B2: Expense | C2: Credit Card | D2: Checking
A3: Utilities | B3: Income | C3: Debit Card | D3: Savings
A4: Groceries | B4: Transfer | C4: Bank Transfer | D4: Credit Card
A5: Dining | B5: Opening Balance | C5: ACH | D5: Cash
A6: Transportation | C6: Cash | D6: Investment
A7: Health & Medical | C7: Check | D7: Loan
A8: Insurance | C8: Venmo/Zelle/PayPal | D8: Other
A9: Debt Payments | C9: Other
A10: Savings & Investments
A11: Personal Care
A12: Shopping
A13: Entertainment
A14: Travel
A15: Education
A16: Gifts & Donations
A17: Taxes
A18: Shipping
A19: Income
A20: Transfers
A21: Existing Savings
A22: Essentials
